Workbook

Sheet Passo a Passo
A3: 1 | B3: Atualização da aba RESULTADO
A4: 1.1 | B4: Insira uma coluna após a última coluna com dados do mês anterior
A5: 1.2 | B5: Cole os dados disponibilizados na planilha do P&L da data-base atual
A6: 1.3 | B6: Verifique se os dados estão corretos conforme as linhas da tabela
A7: 1.4 | B7: Atualize a fórmula de variação na útlima coluna
A10: 2 | B10: Atualização da aba P&L Mensal - Anualizado
A11: 2.1 | B11: Pular uma coluna e inserir a data-base atualizada
A12: 2.2 | B12: Colar as colunas da aba P&L Mensal, na mesma formatação utilizada na planilha
A13: 2.3 | B13: Verificar se os valores correspondem com a linha presente
A16: 3 | B16: Atualização da aba P&L Acumulado
A17: 3.1 | B17: Colar os dados disponibilizados na planilha do P&L
A20: 4 | B20: Atualização da aba Comparativo 2026 x 2025
A21: 4.1 | B21: Colar os dados da aba P&L Acumulado
A22: 4.2 | B22: Colar os dados da aba P&L Acumulado referente ao mesmo período do ano passado
A25: 5 | B25: Atualização do Dashboard Streamlit
A26: 5.1 | B26: Anexe no Claude a planilha BASE_DASHBOARD_PL_2026 e o código atual do stream lit, salvo na pasta "G:\Drives compartilhados\Area - FPA\FPA\29. Checks Contabilidade\2026\Nova pasta\streamlit_app.py"
A27: 5.2 | B27: Encaminhe ao Claude o seguinte prompt
B28: Atualização mensal do dashboard de P&L (Banco Bari). Anexei dois arquivos: - BASE_DASHBOARD_PL_2026.xlsx → a planilha com a nova data base - streamlit_app.py → o código atual do dashboard Quero que você atualize o CÓDIGO para a nova data base. NÃO altere a planilha. Antes de editar, investigue a planilha e o dashboard atual e mantenha EXATAMENTE o mesmo formato/layout visual do dashboard (ordem das seções, cards, gráficos, cabeçalhos, cores, textos fixos) — não altere nada na estrutura ou no design. Atualize SOMENTE os valores e as comparações. No final, me devolva APENAS o streamlit_app.py completo e atualizado. Antes de editar, siga estas regras: 1) Descubra a data base e o nº de meses acumulados do ano lendo a planilha (na aba "Comparativo 2026 x 2025", linha 0: o campo "Até:" dá o último mês, e "Proporção anual" = 12 / nº de meses). Confirme também em "P&L Acumulado". 2) Rótulos do comparativo são VARIÁVEIS conforme o mês. Use o padrão "Acum. NM 26" / "Acum. NM 25", onde N = nº de meses acumulados (maio = 5M, junho = 6M, julho = 7M, e assim por diante). Troque em TODOS os lugares do comparativo (títulos de seção, cards, "vs ...", cabeçalhos de tabela e de gráfico). NÃO altere o dicionário mes_para_trimestre (é outro recurso). 3) Comparativo 2026 x 2025: monte o comparativo cruzando as abas "Comparativo 2026 x 2025" E "P&L Acumulado" (não use apenas uma das duas como fonte). Leia as colunas de cada produto (Consignado/Imobiliário/Total) de forma DINÂMICA em cada bloco. Os blocos de 2026 e de 2025 podem ter número de colunas diferente (ex.: o de 2025 às vezes tem uma coluna extra "BANCO DIGITAL"). Não use offsets fixos de coluna. 4) NÃO deixe nenhum valor numérico chumbado no código. Os valores de carteira, comissão e amortização devem vir da planilha: - Carteira (Total): casar por "contains carteira". - Comissão 2025 (Total): casamento EXATO com "comissao" (para NÃO pegar "Receita Comissão CRI", que também contém "comissão"). - Amortização (Total): "contains amortizacao". 5) Aba P&L Mensal: leia TODOS os meses. Detecte cada bloco mensal pela DATA do cabeçalho (que tem os produtos 2 linhas abaixo), e não pelo texto "DATA BASE -->" — só o bloco de janeiro tem esse texto; os demais trazem só a data. 6) As abas Resultados, P&L Mensal, P&L Acumulado e Comparativo 2026 x 2025 leem as datas dinamicamente. Confirme que todas já enxergam o novo mês. 7) Antes de me entregar: valide rodando os carregadores contra a planilha, conferindo que os valores batem (Receitas, Resultado Contábil, Carteira, Comissão, Amortização, comparativo 2026 x 2025 etc.) e que o app executa SEM erros. Reforço: mantenha exatamente o mesmo layout/formato visual do dashboard — a única mudança permitida são os valores e as comparações. 8) Se a estrutura da planilha tiver mudado de um jeito que exija uma decisão minha (ex.: rótulo de um período que não se encaixa no padrão "NM", ou divergência entre as abas "Comparativo 2026 x 2025" e "P&L Acumulado"), me pergunte de forma objetiva antes de finalizar.
A45: 5.3 | B45: Copie o código enviado pelo Claude e acesse o editor do código no Github e cole o novo código
A47: 1º
A64: 2º
A81: 3º
A96: 5.4 | B96: Verifique se o dashboard foi atualizado e se TODOS os valores estão corretos
B97: https://pl-dashboard-bariv2-e8vph2fztfoysynznzbmes.streamlit.app/

Sheet Premissas
B2: Receita Externa Cebraco:
B3: Apresenta todas as receitas, exceto receita das ligadas: Banco e Hipo. Desconsidera Securitizadora, pois os valores são pagos em patrimônio separado, ou seja, a sec apenas faz a intermediação.
B4: Conta "7.1.7.99.00.000007", "RENDAS CALL CENTER (PESSOA FISICA)" do Balancete e do arquivo de Resultados da Contabilidade
B6: Receita de Serviços, Interchange e Comissão CRI
B7: Serviços >> Grupo 7.1.7 do cosif do Banco, da Hipotecária, da DI (conta cosif: 7.1.7.00.00), receita de despachante da Service (conta cosif: 7.1.7.80.00.000024) e receita Call Center da Poio (conta cosif: 7.1.7.80.00.000002) . No arquivo de "Receitas e Despesas Contabilidade", salvo no diretório "G:\Drives compartilhados\Area - FPA\FPA\29. Checks Contabilidade\2025" há toda a relação dos "de-paras" nas abas do BANCO e da HIPO.
B8: A conta cosif "7.1.7.99.00.00.000013 - COORDENADOR LÍDER", é alocada em Receita de CRI
B9: As contas cosif "7.1.7.99.00.00.000015 - RECEITA INTERCHANGE - FUNCAO CREDITO", "7.1.7.99.00.00.000016 - RECEITA INTERCHANGE - FUNCAO DEBITO" e "7.1.7.99.00.00.000017 - BOLETO DE DEPOSITO LIQUIDADO" são alocada em Receita de Interchange. A divisão entre Consignado e Imobiliário é feita da seguinte forma: 42,6% para Consignado e 57,4% para Imobiliário.
B11: Receita cobrança externa Cebraco
B12: Receitas de prestação de serviços das empresas terceiras.
B13: Valor extraído da planilha "TD_P&L (Total)" do check contábil, célula "D12"
B14: Esse valor deve coincidir com a soma das contas cosif (7.1.7.99.00.000005 e 7.1.7.99.00.000007) do balancete da Cebraco
B16: Resultado de Seguros
... B77: 2) As demais rúbricas contábeis do cartão são alocadas da seguinte forma: 1) 42,6% para o Consignado e 57,4% para o Imobiliário.
A79: Não estamos utilizando os critérios específicados dessa linha para baixo
B81: PART. CONTROLADAS (SEC)
B82: 1) O dados é o mesmo que está na planilha "RESULTADO" e correspondente ao lucro líquido da Sec
B84: Critério de Rateio Captação:
B85: Lógica até Abril/2023
B86: Cartão é o resultado da receita de float/despesa da carteira de crédito que gera juros (desconsidera Creliq).
B87: Imobiliário --> LCI + CDB/LC - IPCA e IGPM + Resultado de Swap.
B88: Consignado --> CDB/LC - Pré/DI
B89: Outros (Receita Financeira, FGC, DPGE, e LFS) --> rateado pela carteira de consignado e imobiliário.
B90: Lógica após Maio/2023
B91: Cartão é o resultado da receita de float/despesa da carteira de crédito.
B92: Consignado --> Consome a despesa até fechar a carteira de ativa e passiva, na seguinte ordem quanto faltar carteira: CDB/LC - Pré, CDB/LC - DI, LCI - Pré e LCI - DI e Resultado Swap (DI x Pré)
B93: Imobiliário --> LCI + CDB/LC - IPCA e IGPM + Resultado de Swap (DI x IPCA), e o restante LCI Pré e DI que não forem utilizadas para fechar a carteira do consignado.
... B108: A partir de julho/24: versão de Março/24 adequando os rateios para retirada do banco digital.

Sheet RESULTADO
B2: Mês | C2: =EOMONTH(D2,-1) -> 44926 | D2: 44957 | E2: 44985 | F2: 45016 | G2: 1º TRIM | I2: =EOMONTH(F2:F2,1) -> 45046 | J2: =EOMONTH(I2:I2,1) -> 45077 | K2: =EOMONTH(J2:J2,1) -> 45107 | M2: 2º TRIM | O2: 1º SEM | Q2: =EOMONTH(K2,1) -> 45138 | R2: =EOMONTH(Q2:Q2,1) -> 45169 | S2: =EOMONTH(R2:R2,1) -> 45199 | U2: 3º TRIM | W2: =EOMONTH(S2:S2,1) -> 45230 | X2: 45260 | Y2: =EOMONTH(X2:X2,1) -> 45291 | AA2: 4º TRIM | AC2: 2º SEM | AE2: 2023 | AG2: 45322 | AH2: =EOMONTH(AG2,1) -> 45351 | AI2: =EOMONTH(AH2,1) -> 45382 | AK2: 1º TRIM | AM2: =EOMONTH(AI2:AI2,1) -> 45412 | AN2: =EOMONTH(AM2:AM2,1) -> 45443 | AO2: =EOMONTH(AN2:AN2,1) -> 45473 | AQ2: 2º TRIM | AS2: 1º SEM | AU2: =EOMONTH(AO2,1) -> 45504 | AV2: =EOMONTH(AU2:AU2,1) -> 45535 | AW2: =EOMONTH(AV2:AV2,1) -> 45565 | AY2: 3º TRIM | BA2: =EOMONTH(AW2:AW2,1) -> 45596 | BB2: =EOMONTH(BA2:BA2,1) -> 45626 | BC2: =EOMONTH(BB2:BB2,1) -> 45657 | BE2: 4º TRIM | BG2: 2º SEM | BI2: 2024 | BJ2: =EOMONTH(BC2,1) -> 45688 | BK2: =EOMONTH(BJ2,1) -> 45716 | BL2: =EOMONTH(BK2,1) -> 45747 | BM2: =EOMONTH(BL2:BL2,1) -> 45777 | BN2: =EOMONTH(BM2:BM2,1) -> 45808 | BO2: =EOMONTH(BN2:BN2,1) -> 45838 | BP2: =EOMONTH(BO2,1) -> 45869 | BQ2: =EOMONTH(BP2:BP2,1) -> 45900 | BR2: 45930 | BS2: =EOMONTH(BR2:BR2,1) -> 45961 | BT2: =EOMONTH(BS2,1) -> 45991 | BU2: =EOMONTH(BT2,1) -> 46022 | BW2: 4º TRIM | BY2: 2º SEM | CA2: YTD | CC2: =EOMONTH(BU2,1) -> 46053 | CD2: =EOMONTH(CC2,1) -> 46081 | CE2: =EOMONTH(CD2,1) -> 46112 | CF2: =EOMONTH(CE2,1) -> 46142 | CG2: =EOMONTH(CF2,1) -> 46173 | CH2: =EOMONTH(CG2,1) -> 46203 | CI2: 46234 | CJ2: 46265
B3: Banco | C3: -1225882.7 | D3: -2256281.8 | E3: -551555.87 | F3: 6437130.8 | G3: =SUM(D3:F3) -> 3629293.1 | I3: -1840435.7 | J3: 471919.39 | K3: 2444762.5 | M3: =SUM(I3:K3) -> 1076246.2 | O3: =SUM(I3:K3,D3:F3) -> 4705539.4 | Q3: -13238.56 | R3: -260697.35 | S3: 5983559.6 | U3: =SUM(Q3:S3) -> 5709623.7 | W3: 2301934.6 | X3: 2390376.4 | Y3: 7139953.1 | AA3: =SUM(W3:Y3) -> 11832264 | AC3: =SUM(W3:Y3,Q3:S3) -> 17541888 | AE3: =O3+AC3 -> 22247427 | AG3: 135333.08 | AH3: 1351348.1 | AI3: 1607493.6 | AK3: =SUM(AG3:AI3) -> 3094174.8 | AM3: 1778241.2 | AN3: 668906.43 | AO3: 4951864.8 | AQ3: =SUM(AM3:AO3) -> 7399012.4 | AS3: =SUM(AM3:AO3,AG3:AI3) -> 10493187 | AU3: 1208517.6 | AV3: 1317888.3 | AW3: 3497673 | AY3: =SUM(AU3:AW3) -> 6024078.8 | BA3: 407091.3 | BB3: 2060889.3 | BC3: 9185197.5 | BE3: =SUM(BA3:BC3) -> 11653178 | BG3: =SUM(BA3:BC3,AU3:AW3) -> 17677257 | BI3: =AS3+BG3 -> 28170444 | BJ3: 1184338 | BK3: 476737.52 | BL3: 5719093.2 | BM3: 4177224.8 | BN3: 2356700.7 | BO3: 4784053.5 | BP3: 2422631.3 | BQ3: 2180653 | BR3: 3140838.3 | BS3: 462356.73 | BT3: 3972262 | BU3: 4603577 | BW3: =SUM(BS3:BU3) -> 9038195.8 | BY3: =SUM(BS3:BU3,BP3:BR3) -> 16782318 | CA3: =SUM(BJ3:BU3) -> 35480466 | CC3: 1868086.1 | CD3: 2667098.7 | CE3: 4416073.4 | CF3: 8042710.4 | CG3: =6557176.22 -> 6557176.2 | CH3: 5852018.8 | CI3: 5038945.8 | CJ3: 4569526.3
B4: Equiv.Patr. | C4: 453185.32 | D4: 771628.33 | E4: 1431454.9 | F4: 2102188.9 | G4: =SUM(D4:F4) -> 4305272.2 | I4: 436785.4 | J4: 417689.25 | K4: 2852793 | M4: =SUM(I4:K4) -> 3707267.6 | O4: =SUM(I4:K4,D4:F4) -> 8012539.8 | Q4: 554506.77 | R4: 852807.67 | S4: -43758.08 | U4: =SUM(Q4:S4) -> 1363556.4 | W4: 944140.65 | X4: 1170510.6 | Y4: -2091085.1 | AA4: =SUM(W4:Y4) -> 23566.16 | AC4: =SUM(W4:Y4,Q4:S4) -> 1387122.5 | AE4: =O4+AC4 -> 9399662.3 | AG4: 172056.15 | AH4: 533427.26 | AI4: 444797.31 | AK4: =SUM(AG4:AI4) -> 1150280.7 | AM4: 485176.53 | AN4: 762992.45 | AO4: 512552.2 | AQ4: =SUM(AM4:AO4) -> 1760721.2 | AS4: =SUM(AM4:AO4,AG4:AI4) -> 2911001.9 | AU4: 754648.1 | AV4: 477878.87 | AW4: -268578.25 | AY4: =SUM(AU4:AW4) -> 963948.72 | BA4: -655785.64 | BB4: 745429.73 | BC4: 1669542.1 | BE4: =SUM(BA4:BC4) -> 1759186.2 | BG4: =SUM(BA4:BC4,AU4:AW4) -> 2723134.9 | BI4: =AS4+BG4 -> 5634136.8 | BJ4: 541079.53 | BK4: 991900.92 | BL4: 1442485.3 | BM4: 1665618.3 | BN4: 1190816.5 | BO4: 1675707.9 | BP4: 1137988.6 | BQ4: 322307.46 | BR4: 869987.47 | BS4: 382306.92 | BT4: 1854232.9 | BU4: 1765324.5 | BW4: =SUM(BS4:BU4) -> 4001864.3 | BY4: =SUM(BS4:BU4,BP4:BR4) -> 6332147.9 | CA4: =SUM(BJ4:BU4) -> 13839756 | CC4: 1404277.8 | CD4: 1441916.6 | CE4: 1955492.4 | CF4: 3042605.6 | CG4: 1756796.8 | CH4: 3257355.9 | CI4: 2265684.8 | CJ4: 1860242.3
B5: JCP + Dividendos | C5: 191960.21 | D5: 0 | E5: 0 | F5: 0 | G5: =SUM(D5:F5) -> 0 | I5: 0 | J5: 0 | K5: 0 | M5: =SUM(I5:K5) -> 0 | O5: =SUM(I5:K5,D5:F5) -> 0 | Q5: 0 | R5: 0 | S5: 0 | U5: =SUM(Q5:S5) -> 0 | W5: 0 | X5: 0 | Y5: 4864009.9 | AA5: =SUM(W5:Y5) -> 4864009.9 | AC5: =SUM(W5:Y5,Q5:S5) -> 4864009.9 | AE5: =O5+AC5 -> 4864009.9 | AG5: 0 | AH5: 0 | AI5: 0 | AK5: =SUM(AG5:AI5) -> 0 | AM5: 0 | AN5: 0 | AO5: 1018230.3 | AQ5: =SUM(AM5:AO5) -> 1018230.3 | AS5: =SUM(AM5:AO5,AG5:AI5) -> 1018230.3 | AU5: 0 | AV5: 0 | AW5: 0 | AY5: =SUM(AU5:AW5) -> 0 | BA5: 0 | BB5: 0 | BC5: 683065.86 | BE5: =SUM(BA5:BC5) -> 683065.86 | BG5: =SUM(BA5:BC5,AU5:AW5) -> 683065.86 | BI5: =AS5+BG5 -> 1701296.2 | BJ5: 0 | BK5: 0 | BL5: 0 | BM5: 0 | BN5: 0 | BO5: 0 | BP5: 0 | BQ5: 0 | BR5: 0 | BS5: 0 | BT5: 0 | BU5: 0 | BW5: =SUM(BS5:BU5) -> 0 | BY5: =SUM(BS5:BU5,BP5:BR5) -> 0 | CA5: =SUM(BJ5:BU5) -> 0 | CC5: 0 | CD5: 0 | CE5: 0 | CF5: 0 | CG5: 0
B6: Resultado Banco | C6: -1871028.2 | D6: =D3-D4-D5 -> -3027910.1 | E6: =E3-E4-E5 -> -1983010.8 | F6: =F3-F4-F5 -> 4334941.8 | G6: =SUM(D6:F6) -> -675979.02 | I6: =I3-I4-I5 -> -2277221.1 | J6: =J3-J4-J5 -> 54230.14 | K6: =K3-K4-K5 -> -408030.44 | M6: =SUM(I6:K6) -> -2631021.4 | O6: =O3-O4-O5 -> -3307000.4 | Q6: =Q3-Q4-Q5 -> -567745.33 | R6: =R3-R4-R5 -> -1113505 | S6: =S3-S4-S5 -> 6027317.7 | U6: =SUM(Q6:S6) -> 4346067.3 | W6: 1357793.9 | X6: 1219865.8 | Y6: 4367028.2 | AA6: =SUM(W6:Y6) -> 6944688 | AC6: =AC3-AC4-AC5 -> 11290755 | AE6: =AE3-AE4-AE5 -> 7983754.9 | AG6: -36723.07 | AH6: 817920.86 | AI6: 1162696.3 | AK6: =SUM(AG6:AI6) -> 1943894.1 | AM6: 1293064.6 | AN6: -94086.02 | AO6: 3421082.3 | AQ6: =SUM(AM6:AO6) -> 4620060.9 | AS6: =AS3-AS4-AS5 -> 6563955 | AU6: 453869.49 | AV6: 840009.4 | AW6: 3766251.2 | AY6: =SUM(AU6:AW6) -> 5060130.1 | BA6: 1062876.9 | BB6: 1315459.6 | BC6: 6832589.5 | BE6: =SUM(BA6:BC6) -> 9210926.1 | BG6: =BG3-BG4-BG5 -> 14271056 | BI6: =BI3-BI4-BI5 -> 20835011 | BJ6: 643258.46 | BK6: -515163.4 | BL6: 4276607.9 | BM6: 2511606.5 | BN6: 1165884.2 | BO6: 3108345.6 | BP6: 1284642.7 | BQ6: 1858345.5 | BR6: 2270850.8 | BS6: 80049.81 | BT6: 2118029.2 | BU6: 2838252.5 | BW6: =SUM(BS6:BU6) -> 5036331.4 | BY6: =BY3-BY4-BY5 -> 10450170 | CA6: =SUM(BJ6:BU6) -> 21640710 | CC6: 463808.25 | CD6: 1225182.2 | CE6: =CE3-CE4 -> 2460581.1 | CF6: =CF3-CF4-CF5 -> 5000104.9 | CG6: =CG3-CG4-CG5 -> 4800379.4 | CH6: =CH3-CH4 -> 2594662.9 | CI6: 2773261 | CJ6: 2709283.9
B7: Hipotecária | C7: 569477.66 | D7: 184324.92 | E7: 1250477.1 | F7: 2071688.5 | G7: =SUM(D7:F7) -> 3506490.6 | I7: 411267.6 | J7: -80452.38 | K7: 2556900.1 | M7: =SUM(I7:K7) -> 2887715.3 | O7: =SUM(I7:K7,D7:F7) -> 6394205.9 | Q7: 370274.9 | R7: 507165.18 | S7: -90122.92 | U7: =SUM(Q7:S7) -> 787317.16 | W7: 886582.6 | X7: 857060.12 | Y7: 2345408.5 | AA7: =SUM(W7:Y7) -> 4089051.2 | AC7: =SUM(W7:Y7,Q7:S7) -> 4876368.4 | AE7: =O7+AC7 -> 11270574 | AG7: 110976.49 | AH7: 411297.69 | AI7: 236500.31 | AK7: =SUM(AG7:AI7) -> 758774.49 | AM7: 434611.59 | AN7: 404507.76 | AO7: 1338115.9 | AQ7: =SUM(AM7:AO7) -> 2177235.2 | AS7: =SUM(AM7:AO7,AG7:AI7) -> 2936009.7 | AU7: 617707.85 | AV7: 430066.94 | AW7: -305419.29 | AY7: =SUM(AU7:AW7) -> 742355.5 | BA7: -811427.31 | BB7: 850419.33 | BC7: 1712350.7 | BE7: =SUM(BA7:BC7) -> 1751342.7 | BG7: =SUM(BA7:BC7,AU7:AW7) -> 2493698.2 | BI7: =AS7+BG7 -> 5429707.9 | BJ7: 464703.12 | BK7: 871800.97 | BL7: 1249780.1 | BM7: 1592797.9 | BN7: 1100442.5 | BO7: 1636029.5 | BP7: 1078640.2 | BQ7: 108896.66 | BR7: 685150.93 | BS7: 198757.09 | BT7: 1665017.2 | BU7: 1403074.8 | BW7: =SUM(BS7:BU7) -> 3266849.1 | BY7: =SUM(BS7:BU7,BP7:BR7) -> 5139537 | CA7: =SUM(BJ7:BU7) -> 12055091 | CC7: 1359401.9 | CD7: 1158533.6 | CE7: 2104762.7 | CF7: 1998240.2 | CG7: =1774617.16 -> 1774617.2 | CH7: 2199968.1 | CI7: 1782672.4 | CJ7: 1028611.4
B8: Resultado Congl. Financeiro | C8: -1301550.5 | D8: -2843585.2 | E8: -732533.64 | F8: 6406630.4 | G8: =SUM(D8:F8) -> 2830511.5 | I8: -1865953.5 | J8: -26222.24 | K8: 2148869.7 | M8: =SUM(I8:K8) -> 256693.93 | O8: =SUM(I8:K8,D8:F8) -> 3087205.5 | Q8: -197470.43 | R8: -606339.84 | S8: 5937194.8 | U8: =SUM(Q8:S8) -> 5133384.5 | W8: 2244376.5 | X8: 2076926 | Y8: 6712436.7 | AA8: =SUM(W8:Y8) -> 11033739 | AC8: =SUM(W8:Y8,Q8:S8) -> 16167124 | AE8: =O8+AC8 -> 19254329 | AG8: 74253.42 | AH8: 1229218.5 | AI8: 1399196.6 | AK8: =SUM(AG8:AI8) -> 2702668.6 | AM8: 1727676.2 | AN8: 310421.74 | AO8: 4759198.2 | AQ8: =SUM(AM8:AO8) -> 6797296.1 | AS8: =SUM(AM8:AO8,AG8:AI8) -> 9499964.7 | AU8: 1071577.3 | AV8: 1270076.3 | AW8: 3460831.9 | AY8: =SUM(AU8:AW8) -> 5802485.6 | BA8: 251449.63 | BB8: 2165878.9 | BC8: 8544940.2 | BE8: =SUM(BA8:BC8) -> 10962269 | BG8: =SUM(BA8:BC8,AU8:AW8) -> 16764754 | BI8: =AS8+BG8 -> 26264719 | BJ8: =SUM(BJ6:BJ7) -> 1107961.6 | BK8: =SUM(BK6:BK7) -> 356637.57 | BL8: =SUM(BL6:BL7) -> 5526388 | BM8: =SUM(BM6:BM7) -> 4104404.4 | BN8: =SUM(BN6:BN7) -> 2266326.7 | BO8: =SUM(BO6:BO7) -> 4744375.1 | BP8: =SUM(BP6:BP7) -> 2363282.9 | BQ8: =SUM(BQ6:BQ7) -> 1967242.2 | ... BU8: =SUM(BU6:BU7) -> 4241327.3 | BW8: =SUM(BS8:BU8) -> 8303180.6 | BY8: =SUM(BS8:BU8,BP8:BR8) -> 15589707 | CA8: =SUM(CA6:CA7) -> 33695801 | CC8: =CC6+CC7 -> 1823210.1 | CD8: =CD6+CD7 -> 2383715.7 | CE8: =CE6+CE7 -> 4565343.7 | CF8: =CF6+CF7 -> 6998345 | CG8: =CG6+CG7 -> 6574996.5 | CH8: =CH6+CH7 -> 4794631.1 | CI8: 4555933.5 | CJ8: 3737895.3 | CK8: =(CJ8/CI8)-1 -> -0.17955445
B10: Apoio | C10: 3097.06 | D10: 45761.36 | E10: 41357.84 | F10: 179237.57 | G10: =SUM(D10:F10) -> 266356.77 | I10: -41623.05 | J10: 187462.07 | K10: -169417.16 | M10: =SUM(I10:K10) -> -23578.14 | O10: =SUM(I10:K10,D10:F10) -> 242778.63 | Q10: 63133.63 | R10: -208725.83 | S10: -304926.61 | U10: =SUM(Q10:S10) -> -450518.81 | W10: 64962.49 | X10: -408320.5 | Y10: -388305.66 | AA10: =SUM(W10:Y10) -> -731663.67 | AC10: =SUM(W10:Y10,Q10:S10) -> -1182182.5 | AE10: =O10+AC10 -> -939403.85 | AG10: 97102.96 | AH10: 301216.36 | AI10: -88491.62 | AK10: =SUM(AG10:AI10) -> 309827.7 | AM10: 113308.82 | AN10: 67062.17 | AO10: -111222.36 | AQ10: =SUM(AM10:AO10) -> 69148.63 | AS10: =SUM(AM10:AO10,AG10:AI10) -> 378976.33 | AU10: 103829.47 | AV10: -140484.96 | AW10: 170123.99 | AY10: =SUM(AU10:AW10) -> 133468.5 | BA10: -220088.02 | BB10: 900.53 | BC10: 94783.98 | BE10: =SUM(BA10:BC10) -> -124403.51 | BG10: =SUM(BA10:BC10,AU10:AW10) -> 9064.99 | BI10: =AS10+BG10 -> 388041.32 | BJ10: 8662.4 | BK10: -46398.02 | BL10: -198223.76 | BM10: 286595.95 | BN10: 250051.98 | BO10: 454587.93 | BP10: 531355.39 | BQ10: 457762.47 | BR10: 267242.22 | BS10: 668876.32 | BT10: 368998.71 | BU10: -137032.85 | BW10: =SUM(BS10:BU10) -> 900842.18 | BY10: =SUM(BS10:BU10,BP10:BR10) -> 2157202.3 | CA10: =SUM(BJ10:BL10)+SUM(BM10:BO10)+SUM(BP10:BR10)+SUM(BS10:BU10) -> 2912478.7 | CC10: -67205.14 | CD10: 307562.98 | CE10: 558365.81 | CF10: -249369.6 | CG10: =209420.16 -> 209420.16 | CH10: =438606.58 -> 438606.58 | CI10: 191269.86 | CJ10: 394267.68
B11: Service | C11: -682901.3 | D11: 992683.36 | E11: -497496.4 | F11: 560056.26 | G11: =SUM(D11:F11) -> 1055243.2 | I11: 50070 | J11: 52449.68 | K11: -58278.43 | M11: =SUM(I11:K11) -> 44241.25 | O11: =SUM(I11:K11,D11:F11) -> 1099484.5 | Q11: -107595.78 | R11: -143340.37 | S11: -49664.58 | U11: =SUM(Q11:S11) -> -300600.73 | W11: -83197.01 | X11: -191600.36 | Y11: -144210.21 | AA11: =SUM(W11:Y11) -> -419007.58 | AC11: =SUM(W11:Y11,Q11:S11) -> -719608.31 | AE11: =O11+AC11 -> 379876.16 | AG11: -132549.64 | AH11: -53812.19 | AI11: -164625.97 | AK11: =SUM(AG11:AI11) -> -350987.8 | AM11: -198315.59 | AN11: -50199.64 | AO11: 12376.66 | AQ11: =SUM(AM11:AO11) -> -236138.57 | AS11: =SUM(AM11:AO11,AG11:AI11) -> -587126.37 | AU11: -117486.72 | AV11: -47222 | AW11: 7254.56 | AY11: =SUM(AU11:AW11) -> -157454.16 | BA11: -74550.02 | BB11: -39497.45 | BC11: 46645.51 | BE11: =SUM(BA11:BC11) -> -67401.96 | BG11: =SUM(BA11:BC11,AU11:AW11) -> -224856.12 | BI11: =AS11+BG11 -> -811982.49 | BJ11: 21886.98 | BK11: -131785.62 | BL11: 92197.89 | BM11: 39268.28 | BN11: 324440.4 | BO11: 182046.23 | BP11: 167219.5 | BQ11: 129182.02 | BR11: 203916.29 | BS11: 245380.69 | BT11: 172928.84 | BU11: 212227.37 | BW11: =SUM(BS11:BU11) -> 630536.9 | BY11: =SUM(BS11:BU11,BP11:BR11) -> 1130854.7 | CA11: =SUM(BJ11:BL11)+SUM(BM11:BO11)+SUM(BP11:BR11)+SUM(BS11:BU11) -> 1658908.9 | CC11: 336620.5 | CD11: 238788.3 | CE11: 348085 | CF11: 319657.08 | CG11: =341150.66 -> 341150.66 | CH11: =377910.27 -> 377910.27 | CI11: 470112.91 | CJ11: 327634.99
B12: Sec | C12: -117389.37 | D12: 403864.17 | E12: 37532.65 | F12: 35087.87 | G12: =SUM(D12:F12) -> 476484.69 | I12: 20981.69 | J12: 302749.95 | K12: 24903.45 | M12: =SUM(I12:K12) -> 348635.09 | O12: =SUM(I12:K12,D12:F12) -> 825119.78 | Q12: 22459.15 | R12: 373949.41 | S12: 92606.79 | U12: =SUM(Q12:S12) -> 489015.35 | W12: 96234.81 | X12: 284203.71 | Y12: 192942.88 | AA12: =SUM(W12:Y12) -> 573381.4 | AC12: =SUM(W12:Y12,Q12:S12) -> 1062396.8 | AE12: =O12+AC12 -> 1887516.5 | AG12: 93813.74 | AH12: 135265.85 | AI12: 219542.37 | AK12: =SUM(AG12:AI12) -> 448621.96 | AM12: 114837.02 | AN12: 356560.25 | AO12: 208072.75 | AQ12: =SUM(AM12:AO12) -> 679470.02 | AS12: =SUM(AM12:AO12,AG12:AI12) -> 1128092 | AU12: 123558.82 | AV12: 40796.91 | AW12: 65236.66 | AY12: =SUM(AU12:AW12) -> 229592.39 | BA12: 171614.12 | BB12: -77824.7 | BC12: 584288.66 | BE12: =SUM(BA12:BC12) -> 678078.08 | BG12: =SUM(BA12:BC12,AU12:AW12) -> 907670.47 | BI12: =AS12+BG12 -> 2035762.5 | BJ12: 55268.02 | BK12: 91252.77 | BL12: 263356.18 | BM12: 62767.15 | BN12: 98598.14 | BO12: 54470.74 | BP12: 91139.91 | BQ12: 214580.78 | BR12: 198117.49 | BS12: 178204.25 | BT12: 188001.86 | BU12: 387325.03 | BW12: =SUM(BS12:BU12) -> 753531.14 | BY12: =SUM(BS12:BU12,BP12:BR12) -> 1257369.3 | CA12: =SUM(BJ12:BL12)+SUM(BM12:BO12)+SUM(BP12:BR12)+SUM(BS12:BU12) -> 1883082.3 | CC12: 56226.37 | CD12: 243037.75 | CE12: 521291.11 | CF12: 483457.04 | CG12: 491462.47 | CH12: 1118794.2 | CI12: 499564.42 | CJ12: 838499.34
B13: Cebraco | C13: 156241.1 | D13: 251871.21 | E13: 45403.03 | F13: 327936.67 | G13: =SUM(D13:F13) -> 625210.91 | I13: 138298.78 | J13: 144880.25 | K13: 186119.58 | M13: =SUM(I13:K13) -> 469298.61 | O13: =SUM(I13:K13,D13:F13) -> 1094509.5 | Q13: 141568.1 | R13: 89515.94 | S13: 134228.26 | U13: =SUM(Q13:S13) -> 365312.3 | W13: 216658.5 | X13: 190560.57 | Y13: 195389.68 | AA13: =SUM(W13:Y13) -> 602608.75 | AC13: =SUM(W13:Y13,Q13:S13) -> 967921.05 | AE13: =O13+AC13 -> 2062430.6 | AG13: 281362.26 | AH13: 228173.23 | AI13: 367935.48 | AK13: =SUM(AG13:AI13) -> 877470.97 | AM13: 416560.49 | AN13: 493559.89 | AO13: 254753.61 | AQ13: =SUM(AM13:AO13) -> 1164874 | AS13: =SUM(AM13:AO13,AG13:AI13) -> 2042345 | AU13: 414080.85 | AV13: 435825.79 | AW13: 431763.56 | AY13: =SUM(AU13:AW13) -> 1281670.2 | BA13: 305013.57 | BB13: 298153 | BC13: 244333.2 | BE13: =SUM(BA13:BC13) -> 847499.77 | BG13: =SUM(BA13:BC13,AU13:AW13) -> 2129170 | BI13: =AS13+BG13 -> 4171514.9 | BJ13: 383753.36 | BK13: 247766.94 | BL13: 197344.81 | BM13: 348062.45 | BN13: 323628.41 | BO13: 296101.84 | BP13: 214279.3 | BQ13: 295074.06 | BR13: 255574.77 | BS13: 270061.93 | BT13: 196618.29 | BU13: 334510.67 | BW13: =SUM(BS13:BU13) -> 801190.89 | BY13: =SUM(BS13:BU13,BP13:BR13) -> 1566119 | CA13: =SUM(BJ13:BL13)+SUM(BM13:BO13)+SUM(BP13:BR13)+SUM(BS13:BU13) -> 3362776.8 | CC13: 294487.17 | CD13: 193404.44 | CE13: 504122.76 | CF13: 345912.66 | CG13: =361593.45 -> 361593.45 | CH13: =441809.41 -> 441809.41 | CI13: 363630.38 | CJ13: 357928.67
B14: Marumbi | C14: -10022.49 | D14: 6101.14 | E14: 5599.87 | F14: 8798.99 | G14: =SUM(D14:F14) -> 20500 | I14: 7479.12 | J14: 9028.82 | K14: 91166.22 | M14: =SUM(I14:K14) -> 107674.16 | O14: =SUM(I14:K14,D14:F14) -> 128174.16 | Q14: -80984.46 | R14: 6475.46 | S14: -102983.23 | U14: =SUM(Q14:S14) -> -177492.23 | W14: 5833.58 | X14: 5190.32 | Y14: 4246.43 | AA14: =SUM(W14:Y14) -> 15270.33 | AC14: =SUM(W14:Y14,Q14:S14) -> -162221.9 | AE14: =O14+AC14 -> -34047.74 | AG14: 4972.24 | AH14: 4496.2 | AI14: -90847.58 | AK14: =SUM(AG14:AI14) -> -81379.14 | AM14: 4208.76 | AN14: 328.11 | AO14: 2786.93 | AQ14: =SUM(AM14:AO14) -> 7323.8 | AS14: =SUM(AM14:AO14,AG14:AI14) -> -74055.34 | AU14: -74768.8 | AV14: -131095.45 | AW14: 3837.14 | AY14: =SUM(AU14:AW14) -> -202027.11 | BA14: -100170.1 | BB14: -1819.17 | BC14: -2292.54 | BE14: =SUM(BA14:BC14) -> -104281.81 | BG14: =SUM(BA14:BC14,AU14:AW14) -> -306308.92 | BI14: =AS14+BG14 -> -380364.26 | BJ14: -2520.6 | BK14: -3154.34 | BL14: -2221.54 | BM14: -1911.07 | BN14: -1765.32 | BO14: -13358.99 | BP14: -12817.43 | BQ14: -13598.6 | BR14: -13542.27 | BS14: -13644.72 | BT14: -15611.28 | BU14: -14857.27 | BW14: =SUM(BS14:BU14) -> -44113.27 | BY14: =SUM(BS14:BU14,BP14:BR14) -> -84071.57 | CA14: =SUM(BJ14:BL14)+SUM(BM14:BO14)+SUM(BP14:BR14)+SUM(BS14:BU14) -> -109003.43 | CC14: -17113.78 | CD14: -14676.51 | CE14: -115574.2 | CF14: -20243.74 | CG14: -19919.31 | CH14: -28424.2 | CI14: -82721.05 | CJ14: -28038.71
B15: Tec | C15: -791480.18 | D15: 731451.37 | E15: -308631 | F15: 199923.47 | G15: =SUM(D15:F15) -> 622743.84 | I15: -21687.43 | J15: 10700.66 | K15: -2039.33 | M15: =SUM(I15:K15) -> -13026.1 | O15: =SUM(I15:K15,D15:F15) -> 609717.74 | Q15: -20611.62 | R15: 3981.71 | S15: 13111.09 | U15: =SUM(Q15:S15) -> -3518.82 | W15: -79586.88 | X15: -148771.42 | Y15: -71492.45 | AA15: =SUM(W15:Y15) -> -299850.75 | AC15: =SUM(W15:Y15,Q15:S15) -> -303369.57 | AE15: =O15+AC15 -> 306348.17 | AG15: -26043.14 | AH15: 8362.07 | AI15: 168585.77 | AK15: =SUM(AG15:AI15) -> 150904.7 | AM15: -24037.35 | AN15: -16277.97 | AO15: 1932.08 | AQ15: =SUM(AM15:AO15) -> -38383.24 | AS15: =SUM(AM15:AO15,AG15:AI15) -> 112521.46 | AU15: 45009.27 | AV15: -19884.46 | AW15: -1861.78 | AY15: =SUM(AU15:AW15) -> 23263.03 | BA15: -67172.13 | BB15: -2038.33 | BC15: -6070.28 | BE15: =SUM(BA15:BC15) -> -75280.74 | BG15: =SUM(BA15:BC15,AU15:AW15) -> -52017.71 | BI15: =AS15+BG15 -> 60503.75 | BJ15: -40549.83 | BK15: -34014.34 | BL15: 2298.89 | BM15: 253236.47 | BN15: -91675.21 | BO15: -113088.48 | BP15: -139859.02 | BQ15: -10120.06 | BR15: -59334.21 | BS15: 186513.9 | BT15: -75603.34 | BU15: 32313.39 | BW15: =SUM(BS15:BU15) -> 143223.95 | BY15: =SUM(BS15:BU15,BP15:BR15) -> -66089.34 | CA15: =SUM(BJ15:BU15) -> -89881.84 | CC15: 6528.27 | CD15: -37526.59 | CE15: 76283.56 | CF15: 249.65 | CG15: =31564.18 -> 31564.18 | CH15: =38995.65 -> 38995.65 | CI15: 52818.07 | CJ15: 31684.85
B16: Bariseg | C16: 384459.99 | D16: 392200.68 | E16: 398056.12 | F16: 375279.68 | G16: =SUM(D16:F16) -> 1165536.5 | I16: -14816.54 | J16: -10399 | K16: -2698.56 | M16: =SUM(I16:K16) -> -27914.1 | O16: =SUM(I16:K16,D16:F16) -> 1137622.4 | Q16: -1222.42 | R16: 13842.24 | S16: 56539.34 | U16: =SUM(Q16:S16) -> 69159.16 | W16: 31595.86 | X16: 25703.99 | Y16: -205781.68 | AA16: =SUM(W16:Y16) -> -148481.83 | AC16: =SUM(W16:Y16,Q16:S16) -> -79322.67 | AE16: =O16+AC16 -> 1058299.7 | AG16: 57666.95 | AH16: 27904.34 | AI16: 66053.48 | AK16: =SUM(AG16:AI16) -> 151624.77 | AM16: 89488.39 | AN16: 112473.42 | AO16: 112826.47 | AQ16: =SUM(AM16:AO16) -> 314788.28 | AS16: =SUM(AM16:AO16,AG16:AI16) -> 466413.05 | AU16: 105280.44 | AV16: 143270.29 | AW16: 159460.57 | AY16: =SUM(AU16:AW16) -> 408011.3 | BA16: 151077.13 | BB16: 187338.62 | BC16: 197245.09 | BE16: =SUM(BA16:BC16) -> 535660.84 | BG16: =SUM(BA16:BC16,AU16:AW16) -> 943672.14 | BI16: =AS16+BG16 -> 1410085.2 | BJ16: 207239.06 | BK16: 195013.08 | BL16: 144849.37 | BM16: 714727.3 | BN16: 777002.52 | BO16: 744540.08 | BP16: 672727.21 | BQ16: 726660.72 | BR16: 786885.56 | BS16: 1080237.8 | BT16: 791082.68 | BU16: 885803.25 | BW16: =SUM(BS16:BU16) -> 2757123.8 | BY16: =SUM(BS16:BU16,BP16:BR16) -> 4943397.3 | CA16: =SUM(BJ16:BU16) -> 7726768.7 | CC16: 828615.88 | CD16: 743112.13 | CE16: 853652.17 | CF16: 814124.26 | CG16: =855737.79 -> 855737.79 | CH16: =869844.14 -> 869844.14 | CI16: 855755.83 | CJ16: 922828.38
B17: DI | C17: 109356.42 | D17: 301296.69 | E17: 139257.8 | F17: 232489.41 | G17: =SUM(D17:F17) -> 673043.9 | I17: 263989.08 | J17: 49350.59 | K17: 39650.02 | M17: =SUM(I17:K17) -> 352989.69 | O17: =SUM(I17:K17,D17:F17) -> 1026033.6 | Q17: 112270.02 | R17: 124876.76 | S17: 45239.83 | U17: =SUM(Q17:S17) -> 282386.61 | W17: 134299.5 | X17: 83571.06 | Y17: 57294.26 | AA17: =SUM(W17:Y17) -> 275164.82 | AC17: =SUM(W17:Y17,Q17:S17) -> 557551.43 | AE17: =O17+AC17 -> 1583585 | AG17: 466252.26 | AH17: 248335.25 | AI17: 203476.8 | AK17: =SUM(AG17:AI17) -> 918064.31 | AM17: 282459.26 | AN17: 245432.29 | AO17: 206602.16 | AQ17: =SUM(AM17:AO17) -> 734493.71 | AS17: =SUM(AM17:AO17,AG17:AI17) -> 1652558 | AU17: 270758.64 | AV17: 266385.47 | AW17: 271784.93 | AY17: =SUM(AU17:AW17) -> 808929.04 | BA17: 249579.28 | BB17: 275812.11 | BC17: 211510.14 | BE17: =SUM(BA17:BC17) -> 736901.53 | BG17: =SUM(BA17:BC17,AU17:AW17) -> 1545830.6 | BI17: =AS17+BG17 -> 3198388.6 | BJ17: 240407.82 | BK17: 411839.17 | BL17: 279665.81 | BM17: 373531.63 | BN17: 295129.34 | BO17: 298405.16 | BP17: 423635.39 | BQ17: 406830.35 | BR17: 414584.86 | BS17: 503719.17 | BT17: 349160.14 | BU17: 326824.55 | BW17: =SUM(BS17:BU17) -> 1179703.9 | BY17: =SUM(BS17:BU17,BP17:BR17) -> 2424754.5 | CA17: =SUM(BJ17:BU17) -> 4323733.4 | CC17: 397092.06 | CD17: 252933.85 | CE17: 478274.25 | CF17: 370838.59 | CG17: =527546.49 -> 527546.49 | CH17: =546825.31 -> 546825.31 | CI17: 488496.52 | CJ17: 466122.93
B18: Bari Capital | BJ18: 25293.19 | BK18: 19767.84 | BL18: 20060.59 | BM18: 30800.68 | BN18: 15422.58 | BO18: 26663.53 | BP18: 51975.09 | BQ18: 44285.86 | BR18: 86107.31 | BS18: 79295.22 | BT18: 68143.26 | BU18: 77136.36 | BW18: =SUM(BS18:BU18) -> 224574.84 | BY18: =SUM(BS18:BU18,BP18:BR18) -> 406943.1 | CA18: =SUM(BJ18:BU18) -> 544951.51 | CC18: 113327.59 | CD18: -629.72 | CE18: -202789.07 | CF18: 23664.61 | CG18: -87553.01 | CH18: 15935.41 | CI18: 24659.56 | CJ18: 16626.2
B19: Resultado Coligadas | C19: -647967.51 | D19: 3413438.7 | E19: 76555.93 | F19: 1854471.9 | G19: =SUM(D19:F19) -> 5344466.5 | I19: 947786.42 | J19: 1044795.3 | K19: 383120.09 | M19: =SUM(I19:K19) -> 2375701.8 | O19: =SUM(I19:K19,D19:F19) -> 7720168.3 | Q19: 370689.56 | R19: 260575.32 | S19: -115849.11 | U19: =SUM(Q19:S19) -> 515415.77 | W19: 386800.85 | X19: -159462.63 | Y19: -359916.75 | AA19: =SUM(W19:Y19) -> -132578.53 | AC19: =SUM(W19:Y19,Q19:S19) -> 382837.24 | AE19: =O19+AC19 -> 8103005.5 | AG19: 842577.63 | AH19: 899941.11 | AI19: 681628.73 | AK19: =SUM(AG19:AI19) -> 2424147.5 | AM19: 798509.8 | AN19: 1208938.5 | AO19: 688128.3 | AQ19: =SUM(AM19:AO19) -> 2695576.6 | AS19: =SUM(AM19:AO19,AG19:AI19) -> 5119724.1 | AU19: 870261.97 | AV19: 547591.59 | AW19: 1107599.6 | AY19: =SUM(AU19:AW19) -> 2525453.2 | BA19: 415303.83 | BB19: 641024.61 | BC19: 1370443.8 | BE19: =SUM(BA19:BC19) -> 2426772.2 | BG19: =SUM(BA19:BC19,AU19:AW19) -> 4952225.4 | BI19: =AS19+BG19 -> 10071949 | BJ19: =SUM(BJ10:BJ18) -> 899440.4 | BK19: =SUM(BK10:BK18) -> 750287.48 | BL19: =SUM(BL10:BL18) -> 799328.24 | BM19: =SUM(BM10:BM18) -> 2107078.8 | BN19: =SUM(BN10:BN18) -> 1990832.8 | BO19: =SUM(BO10:BO18) -> 1930368 | BP19: =SUM(BP10:BP18) -> 1999655.3 | BQ19: =SUM(BQ10:BQ18) -> 2250657.6 | ... BU19: =SUM(BU10:BU18) -> 2104250.5 | BW19: =SUM(BS19:BU19) -> 7346614.3 | BY19: =SUM(BS19:BU19,BP19:BR19) -> 13736479 | CA19: =SUM(CA10:CA18) -> 22213815 | CC19: =SUM(CC10:CC18) -> 1948578.9 | CD19: =SUM(CD10:CD18) -> 1926006.6 | CE19: =SUM(CE10:CE18) -> 3021711.4 | CF19: =SUM(CF10:CF18) -> 2088290.6 | CG19: =SUM(CG10:CG18) -> 2711002.9 | CH19: =SUM(CH10:CH18) -> 3820296.8 | CI19: 2863586.5 | CJ19: 3327554.3 | CK19: =(CJ19/CI19)-1 -> 0.16202333
B21: Resultado Congl. + Coligadas | C21: -1949518 | D21: 569853.53 | E21: -655977.71 | F21: 8261102.2 | G21: =SUM(D21:F21) -> 8174978.1 | I21: -918167.08 | J21: 1018573 | K21: 2531989.8 | M21: =SUM(I21:K21) -> 2632395.7 | O21: =SUM(I21:K21,D21:F21) -> 10807374 | Q21: 173219.13 | R21: -345764.52 | S21: 5821345.6 | U21: =SUM(Q21:S21) -> 5648800.2 | W21: 2631177.4 | X21: 1917463.3 | Y21: 6352520 | AA21: =SUM(W21:Y21) -> 10901161 | AC21: =SUM(W21:Y21,Q21:S21) -> 16549961 | AE21: =O21+AC21 -> 27357335 | AG21: 916831.05 | AH21: 2129159.7 | AI21: 2080825.3 | AK21: =SUM(AG21:AI21) -> 5126816 | AM21: 2526186 | AN21: 1519360.3 | AO21: 5447326.5 | AQ21: =SUM(AM21:AO21) -> 9492872.7 | AS21: =SUM(AM21:AO21,AG21:AI21) -> 14619689 | AU21: 1941839.3 | AV21: 1817667.9 | AW21: 4568431.6 | AY21: =SUM(AU21:AW21) -> 8327938.8 | BA21: 666753.46 | BB21: 2806903.5 | BC21: 9915384 | BE21: =SUM(BA21:BC21) -> 13389041 | BG21: =SUM(BA21:BC21,AU21:AW21) -> 21716980 | BI21: =AS21+BG21 -> 36336669 | BJ21: =BJ8+BJ19 -> 2007402 | BK21: =BK8+BK19 -> 1106925.1 | BL21: =BL8+BL19 -> 6325716.2 | BM21: =BM8+BM19 -> 6211483.2 | BN21: =BN8+BN19 -> 4257159.5 | BO21: =BO8+BO19 -> 6674743.2 | BP21: =BP8+BP19 -> 4362938.2 | BQ21: =BQ8+BQ19 -> 4217899.8 | ... BU21: =BU8+BU19 -> 6345577.8 | BW21: =SUM(BS21:BU21) -> 15649795 | BY21: =SUM(BS21:BU21,BP21:BR21) -> 29326187 | CA21: =CA19+CA8 -> 55909616 | CC21: =CC8+CC19 -> 3771789.1 | CD21: =CD8+CD19 -> 4309722.3 | CE21: =CE8+CE19 -> 7587055.1 | CF21: =CF8+CF19 -> 9086635.6 | CG21: =CG8+CG19 -> 9285999.4 | CH21: =CH8+CH19 -> 8614927.9 | CI21: 7419520 | CJ21: 7065449.6 | CK21: =(CJ21/CI21)-1 -> -0.047721458
B23: BR Cards | C23: -744679.01 | D23: 2842467.5 | E23: -84774.05 | F23: 1734470.1 | G23: =SUM(D23:F23) -> 4492163.5 | I23: 336223.28 | J23: 424533.92 | K23: 146560.61 | M23: =SUM(I23:K23) -> 907317.81 | O23: =SUM(I23:K23,D23:F23) -> 5399481.3 | Q23: 91429.05 | R23: -137973.28 | S23: -239435.31 | U23: =SUM(Q23:S23) -> -285979.54 | W23: 273119.44 | X23: -431524.45 | Y23: -600734.72 | AA23: =SUM(W23:Y23) -> -759139.73 | AC23: =SUM(W23:Y23,Q23:S23) -> -1045119.3 | AE23: =O23+AC23 -> 4354362 | AG23: 767440.02 | AH23: 750979.9 | AI23: 432757.06 | AK23: =SUM(AG23:AI23) -> 1951177 | AM23: 662524.89 | AN23: 842029.62 | AO23: 593382.21 | AQ23: =SUM(AM23:AO23) -> 2097936.7 | AS23: =SUM(AM23:AO23,AG23:AI23) -> 4049113.7 | AU23: 744180.93 | AV23: 486306.52 | AW23: 1014721.4 | AY23: =SUM(AU23:AW23) -> 2245208.9 | BA23: 214691.41 | BB23: 875982.28 | BC23: 798970.02 | BE23: =SUM(BA23:BC23) -> 1889643.7 | BG23: =SUM(BA23:BC23,AU23:AW23) -> 4134852.6 | BI23: =AS23+BG23 -> 8183966.3 | BJ23: 828965.29 | BK23: 642854.08 | BL23: 537859.73 | BM23: 2092438.7 | BN23: 1856223.5 | BO23: 1915228.4 | BP23: 1829491.1 | BQ23: 2018509.1 | BR23: 2651795.3 | BS23: 2635218.8 | BT23: 1724928.1 | BU23: 1816891.3 | BW23: =SUM(BS23:BU23) -> 6177038.2 | BY23: =SUM(BS23:BU23,BP23:BR23) -> 12676834 | CA23: 21120255 | CC23: 1918146.6 | CD23: 1655619 | CE23: 2648896.4 | CF23: 1615034.6 | CG23: =2312442.5 -> 2312442.5 | CH23: 2732955.2 | CI23: 2399904.2 | CJ23: 2485883
B24: Resultado MEP | CC24: 1872781.9 | CD24: 1605888.7 | CE24: 2563268.6 | CF24: 1553760.1 | CG24: 2289452.1 | CH24: 2650413.2 | CI24: 2316461.2 | CJ24: 2453169.1
B25: Resulta Br Cards | CA25: =CA23-#REF!-#REF! -> #REF! | CC25: 45364.75 | CD25: 49730.27 | CE25: =CE23-CE24 -> 85627.77 | CF25: =CF23-CF24 -> 61274.51 | CG25: =CG23-CG24 -> 22990.37 | CH25: =CH23-CH24 -> 82542.05 | CI25: 83442.94 | CJ25: 32713.88
B26: RES. TOTAL | C26: =C21+#REF! -> #REF! | D26: =D21+#REF! -> #REF! | E26: =E21+#REF! -> #REF! | F26: =F21+#REF! -> #REF! | G26: =G21+#REF! -> #REF! | I26: =I21+#REF! -> #REF! | J26: =J21+#REF! -> #REF! | K26: =K21+#REF! -> #REF! | M26: =SUM(I26:K26) -> #REF! | O26: =SUM(I26:K26,D26:F26) -> #REF! | Q26: =Q21+#REF! -> #REF! | R26: =R21+#REF! -> #REF! | S26: =S21+#REF! -> #REF! | U26: =SUM(Q26:S26) -> #REF! | W26: =W21+#REF! -> #REF! | X26: =X21+#REF! -> #REF! | Y26: =Y21+#REF! -> #REF! | AA26: =SUM(W26:Y26) -> #REF! | AC26: =SUM(W26:Y26,Q26:S26) -> #REF! | AE26: =AE21+#REF! -> #REF! | AG26: =AG21+#REF! -> #REF! | AH26: =AH21+#REF! -> #REF! | AI26: =AI21+#REF! -> #REF! | AK26: =AK21+#REF! -> #REF! | AM26: =AM21+#REF! -> #REF! | AN26: =AN21+#REF! -> #REF! | AO26: =AO21+#REF! -> #REF! | AQ26: =SUM(AM26:AO26) -> #REF! | AS26: =SUM(AM26:AO26,AG26:AI26) -> #REF! | AU26: =AU21+#REF! -> #REF! | AV26: =AV21+#REF! -> #REF! | AW26: =AW21+#REF! -> #REF! | AY26: =SUM(AU26:AW26) -> #REF! | BA26: =BA21+#REF! -> #REF! | BB26: =BB21+#REF! -> #REF! | BC26: =BC21+#REF! -> #REF! | BE26: =SUM(BA26:BC26) -> #REF! | BG26: =SUM(BA26:BC26,AU26:AW26) -> #REF! | BI26: =BI21+#REF! -> #REF! | BJ26: =BJ21+#REF! -> #REF! | BK26: =BK21+#REF! -> #REF! | BL26: =BL21+#REF! -> #REF! | BM26: =BM21+#REF! -> #REF! | BN26: =BN21+#REF! -> #REF! | BO26: =BO21+#REF! -> #REF! | BP26: =BP21+#REF! -> #REF! | ... BU26: =BU21+#REF! -> #REF! | BW26: =SUM(BS26:BU26) -> #REF! | BY26: =#REF!+BW26 -> #REF! | CA26: =CA21+CA25 -> #REF! | CC26: =CC21+CC25 -> 3817153.8 | CD26: =CD21+CD25 -> 4359452.6 | CE26: =CE21+CE25 -> 7672682.9 | CF26: =CF21+CF25 -> 9147910.1 | CG26: =CG21+CG25 -> 9308989.8 | CH26: =CH21+CH25 -> 8697469.9 | CI26: 7502962.9 | CJ26: 7098163.5 | CK26: =(CJ26/CI26)-1 -> -0.053951935

Sheet P&L Mensal - Anualizado
A1: DATA BASE --> | B1: 46053 | M1: 46081 | X1: 46112 | AI1: 46142 | AT1: 46173 | BE1: 46174 | BH1: 46203 | BP1: 46204 | BS1: 46203 | CA1: 46235 | CD1: 46203
B3: CONSIGNADO | E3: IMOBILIARIO | H3: TOTAL | M3: CONSIGNADO | P3: IMOBILIARIO | S3: TOTAL | X3: CONSIGNADO | AA3: IMOBILIARIO | AD3: TOTAL | AI3: CONSIGNADO | AL3: IMOBILIARIO | AO3: TOTAL | AT3: CONSIGNADO | AW3: IMOBILIARIO | AZ3: TOTAL | BE3: CONSIGNADO | BH3: IMOBILIARIO | BK3: TOTAL | BP3: CONSIGNADO | BS3: IMOBILIARIO | BV3: TOTAL | CA3: CONSIGNADO | CD3: IMOBILIARIO | CG3: TOTAL
B4: Realizado | C4: Orçado | D4: ∆ (%) | E4: Realizado | F4: Orçado | G4: ∆ (%) | H4: Realizado | I4: Orçado | J4: ∆ (%) | K4: ∆ (R$) | M4: Realizado | N4: Orçado | O4: ∆ (%) | P4: Realizado | Q4: Orçado | R4: ∆ (%) | S4: Realizado | T4: Orçado | U4: ∆ (%) | V4: ∆ (R$) | X4: Realizado | Y4: Orçado | Z4: ∆ (%) | AA4: Realizado | AB4: Orçado | AC4: ∆ (%) | AD4: Realizado | AE4: Orçado | AF4: ∆ (%) | AG4: ∆ (R$) | AI4: Realizado | AJ4: Orçado | AK4: ∆ (%) | AL4: Realizado | AM4: Orçado | AN4: ∆ (%) | AO4: Realizado | AP4: Orçado | AQ4: ∆ (%) | AR4: ∆ (R$) | AT4: Realizado | AU4: Orçado | AV4: ∆ (%) | AW4: Realizado | AX4: Orçado | AY4: ∆ (%) | AZ4: Realizado | BA4: Orçado | BB4: ∆ (%) | BC4: ∆ (R$) | BE4: Realizado | BF4: Orçado | BG4: ∆ (%) | BH4: Realizado | BI4: Orçado | BJ4: ∆ (%) | BK4: Realizado | BL4: Orçado | BM4: ∆ (%) | BN4: ∆ (R$) | BP4: Realizado | BQ4: Orçado | BR4: ∆ (%) | BS4: Realizado | BT4: Orçado | BU4: ∆ (%) | BV4: Realizado | BW4: Orçado | BX4: ∆ (%) | BY4: ∆ (R$) | CA4: Realizado | CB4: Orçado | CC4: ∆ (%) | CD4: Realizado | CE4: Orçado | CF4: ∆ (%) | CG4: Realizado | CH4: Orçado | CI4: ∆ (%) | CJ4: ∆ (R$)
A5: RECEITAS | B5: 7802027.9 | C5: 7701714.3 | D5: 0.013024833 | E5: 23859887 | F5: 24532548 | G5: -0.027419124 | H5: 31661915 | I5: 32234263 | J5: -0.017755872 | K5: -572347.44 | M5: 7098724.1 | N5: 6991516.2 | O5: 0.015333991 | P5: 23773864 | Q5: 23417973 | R5: 0.015197351 | S5: 30872588 | T5: 30409489 | U5: 0.015228766 | V5: 463099 | X5: 7877352.9 | Y5: 7759392.7 | Z5: 0.015202255 | AA5: 33774613 | AB5: 29464374 | AC5: 0.14628643 | AD5: 41651965 | AE5: 37223767 | AF5: 0.11896159 | AG5: 4428198.4 | AI5: 7513769.7 | AJ5: 7551512 | AK5: -0.0049979825 | AL5: 34391853 | AM5: 27827307 | AN5: 0.23590304 | AO5: 41905623 | AP5: 35378819 | AQ5: 0.18448337 | AR5: 6526803.9 | AT5: 7585530.4 | AU5: 7837760.5 | AV5: -0.032181401 | AW5: 37483958 | AX5: 26639239 | AY5: 0.40709565 | AZ5: 45069488 | BA5: 34477000 | BB5: 0.30723347 | BC5: 10592488 | BE5: 7768119.1 | BF5: 7626952.8 | BG5: 0.018508878 | BH5: 34678251 | BI5: 29052906 | BJ5: 0.1936242 | BK5: 42446371 | BL5: 36679859 | BM5: 0.15721194 | BN5: 5766511.9 | BP5: 7825364.1 | BQ5: 7915101.7 | BR5: -0.011337516 | BS5: 32306467 | BT5: 29113454 | BU5: 0.10967483 | BV5: 40131831 | BW5: 37028556 | BX5: 0.083807632 | BY5: 3103275.6 | CA5: 7659976.8 | CB5: 7957281.7 | CC5: -0.037362619 | CD5: 28759886 | CE5: 29754492 | CF5: -0.0334271 | CG5: 36419863 | CH5: 37711774 | CI5: -0.034257505 | CJ5: -1291911.3
A6: Operações de Crédito | B6: 7793026.2 | C6: 7689247.8 | D6: 0.013496567 | E6: 21036305 | F6: 21210590 | G6: -0.0082168929 | H6: 28829331 | I6: 28899838 | J6: -0.0024396921 | K6: -70506.705 | M6: 7090560.7 | N6: 6979049.7 | O6: 0.015977969 | P6: 21137849 | Q6: 20364605 | R6: 0.037969994 | S6: 28228410 | T6: 27343655 | U6: 0.032356866 | V6: 884754.96 | X6: 7868473.4 | Y6: 7746926.1 | Z6: 0.015689749 | AA6: 29656161 | AB6: 26280606 | AC6: 0.12844279 | AD6: 37524634 | AE6: 34027532 | AF6: 0.10277271 | AG6: 3497101.8 | AI6: 7505271.2 | AJ6: 7539045.4 | AK6: -0.0044799064 | AL6: 30286317 | AM6: 24677939 | AN6: 0.22726283 | AO6: 37791589 | AP6: 32216985 | AQ6: 0.17303308 | AR6: 5574604 | AT6: 7577110.4 | AU6: 7825293.9 | AV6: -0.031715559 | AW6: 33233799 | AX6: 23584471 | AY6: 0.40913905 | AZ6: 40810910 | BA6: 31409765 | BB6: 0.29930642 | BC6: 9401144.5 | BE6: 7760330.2 | BF6: 7614486.2 | BG6: 0.019153487 | BH6: 29172318 | BI6: 25869138 | BJ6: 0.12768805 | BK6: 36932648 | BL6: 33483624 | BM6: 0.10300628 | BN6: 3449023.7 | BP6: 7817377.2 | BQ6: 7902635.1 | BR6: -0.010788542 | BS6: 27673852 | BT6: 25706086 | BU6: 0.076548649 | BV6: 35491229 | BW6: 33608721 | BX6: 0.056012493 | BY6: 1882508.3 | CA6: 7659976.8 | CB6: 7944815.2 | CC6: -0.035852102 | CD6: 24000775 | CE6: 26433124 | CF6: -0.092018977 | CG6: 31660752 | CH6: 34377940 | CI6: -0.079038692 | CJ6: -2717187.4
A7: Receita Juros | B7: 5986044.8 | C7: 5963467 | D7: 0.003786019 | E7: 17780387 | F7: 18019560 | G7: -0.01327294 | H7: 23766432 | I7: 23983027 | J7: -0.0090311673 | K7: -216594.73 | M7: 5423105.9 | N7: 5428491 | O7: -0.00099200565 | P7: 17032219 | Q7: 16315715 | R7: 0.043914918 | S7: 22455324 | T7: 21744206 | U7: 0.032703802 | V7: 711118.21 | X7: 6041460.8 | Y7: 6046154.6 | Z7: -0.00077634449 | AA7: 21983325 | AB7: 20556772 | AC7: 0.0693958 | AD7: 28024786 | AE7: 26602926 | AF7: 0.053447493 | AG7: 1421859.7 | AI7: 5722335.5 | AJ7: 5903016.4 | AK7: -0.030608248 | AL7: 18968832 | AM7: 19154707 | AN7: -0.009703897 | AO7: 24691167 | AP7: 25057724 | AQ7: -0.014628475 | AR7: -366556.29 | AT7: 5720927.6 | AU7: 6147095.5 | AV7: -0.069328331 | AW7: 20864074 | AX7: 18901932 | AY7: 0.10380643 | AZ7: 26585002 | BA7: 25049027 | BB7: 0.061318718 | BC7: 1535974.3 | BE7: 5951734.4 | BF7: 6000520.8 | BG7: -0.0081303582 | BH7: 18927414 | BI7: 20741537 | BJ7: -0.08746327 | BK7: 24879148 | BL7: 26742057 | BM7: -0.069662142 | BN7: -1862909 | BP7: 5950868.3 | BQ7: 6247547 | BR7: -0.047487227 | BS7: 21589769 | BT7: 20594778 | BU7: 0.048312772 | BV7: 27540637 | BW7: 26842325 | BX7: 0.026015337 | BY7: 698312.14 | CA7: 5808125.9 | CB7: 6300778.4 | CC7: -0.078189139 | CD7: 22603099 | CE7: 21164553 | CF7: 0.067969567 | CG7: 28411225 | CH7: 27465332 | CI7: 0.034439529 | CJ7: 945893.07
A10: Receita CM - Crédito Imobiliário | B10: 0 | C10: 0 | D10: - | E10: 2865754.8 | F10: 2790874.1 | G10: 0.026830562 | H10: 2865754.8 | I10: 2790874.1 | J10: 0.026830562 | K10: 74880.721 | M10: 0 | N10: 0 | O10: - | P10: 3752222.7 | Q10: 3641713.1 | R10: 0.030345476 | S10: 3752222.7 | T10: 3641713.1 | U10: 0.030345476 | V10: 110509.52 | X10: 0 | Y10: 0 | Z10: - | AA10: 7200722.4 | AB10: 5309468.9 | AC10: 0.35620388 | AD10: 7200722.4 | AE10: 5309468.9 | AF10: 0.35620388 | AG10: 1891253.4 | AI10: 0 | AJ10: 0 | AK10: - | AL10: 10881663 | AM10: 5098166.9 | AN10: 1.1344266 | AO10: 10881663 | AP10: 5098166.9 | AQ10: 1.1344266 | AR10: 5783496.4 | AT10: 0 | AU10: 0 | AV10: - | AW10: 11873778 | AX10: 4248792.5 | AY10: 1.7946242 | AZ10: 11873778 | BA10: 4248792.5 | BB10: 1.7946242 | BC10: 7624986 | BE10: 0 | BF10: 0 | BG10: - | BH10: 9615604.4 | BI10: 4701365 | BJ10: 1.0452793 | BK10: 9615604.4 | BL10: 4701365 | BM10: 1.0452793 | BN10: 4914239.4 | BP10: 0 | BQ10: 0 | BR10: - | BS10: 5589199.1 | BT10: 4675672.4 | BU10: 0.19537868 | BV10: 5589199.1 | BW10: 4675672.4 | BX10: 0.19537868 | BY10: 913526.71 | CA10: 0 | CB10: 0 | CC10: - | CD10: 729854.06 | CE10: 4821979.5 | CF10: -0.84864016 | CG10: 729854.06 | CH10: 4821979.5 | CI10: -0.84864016 | CJ10: -4092125.4
A11: Multa + Mora - Crédito Imobiliário | B11: 0 | C11: 0 | D11: - | E11: 348775.09 | F11: 358704.27 | G11: -0.027680676 | H11: 348775.09 | I11: 358704.27 | J11: -0.027680676 | K11: -9929.1765 | M11: 0 | N11: 0 | O11: - | P11: 312401.05 | Q11: 365724.09 | R11: -0.14580127 | S11: 312401.05 | T11: 365724.09 | U11: -0.14580127 | V11: -53323.037 | X11: 0 | Y11: 0 | Z11: - | AA11: 394865.93 | AB11: 372913.43 | AC11: 0.058867538 | AD11: 394865.93 | AE11: 372913.43 | AF11: 0.058867538 | AG11: 21952.496 | AI11: 0 | AJ11: 0 | AK11: - | AL11: 370357.59 | AM11: 383612.66 | AN11: -0.034553267 | AO11: 370357.59 | AP11: 383612.66 | AQ11: -0.034553267 | AR11: -13255.071 | AT11: 0 | AU11: 0 | AV11: - | AW11: 420468.1 | AX11: 392294.41 | AY11: 0.071817711 | AZ11: 420468.1 | BA11: 392294.41 | BB11: 0.071817711 | BC11: 28173.687 | BE11: 0 | BF11: 0 | BG11: - | BH11: 560900.65 | BI11: 384783.72 | BJ11: 0.4577037 | BK11: 560900.65 | BL11: 384783.72 | BM11: 0.4577037 | BN11: 176116.93 | BP11: 0 | BQ11: 0 | BR11: - | BS11: 425490.79 | BT11: 394182.82 | BU11: 0.079424986 | BV11: 425490.79 | BW11: 394182.82 | BX11: 0.079424986 | BY11: 31307.965 | CA11: 0 | CB11: 0 | CC11: - | CD11: 602666.7 | CE11: 405139.32 | CF11: 0.48755422 | CG11: 602666.7 | CH11: 405139.32 | CI11: 0.48755422 | CJ11: 197527.38
A12: Receita Juros - Cartão | B12: 1806981.4 | C12: 1725780.8 | D12: 0.047051542 | E12: 41388.299 | F12: 41452.468 | G12: -0.0015480233 | H12: 1848369.7 | I12: 1767233.2 | J12: 0.045911583 | K12: 81136.476 | M12: 1667454.8 | N12: 1550558.7 | O12: 0.075389688 | P12: 41006.606 | Q12: 41452.468 | R12: -0.010755986 | S12: 1708461.4 | T12: 1592011.1 | U12: 0.073146645 | V12: 116450.27 | X12: 1827012.7 | Y12: 1700771.4 | Z12: 0.074225863 | AA12: 77247.43 | AB12: 41452.468 | AC12: 0.86351823 | AD12: 1904260.1 | AE12: 1742223.9 | AF12: 0.093005376 | AG12: 162036.19 | AI12: 1782935.8 | AJ12: 1636029 | AK12: 0.089794723 | AL12: 65464.72 | AM12: 41452.468 | AN12: 0.57927195 | AO12: 1848400.5 | AP12: 1677481.5 | AQ12: 0.10189026 | AR12: 170919.02 | AT12: 1856182.8 | AU12: 1678198.5 | AV12: 0.10605676 | AW12: 75478.73 | AX12: 41452.468 | AY12: 0.82085008 | AZ12: 1931661.5 | BA12: 1719650.9 | BB12: 0.12328697 | BC12: 212010.56 | BE12: 1808595.8 | BF12: 1613965.5 | BG12: 0.12059139 | BH12: 68398.49 | BI12: 41452.468 | BJ12: 0.65004626 | BK12: 1876994.3 | BL12: 1655417.9 | BM12: 0.1338492 | BN12: 221576.37 | BP12: 1866508.9 | BQ12: 1655088.1 | BR12: 0.12773989 | BS12: 69393.13 | BT12: 41452.468 | BU12: 0.67404097 | BV12: 1935902 | BW12: 1696540.6 | BX12: 0.14108795 | BY12: 239361.43 | CA12: 1851850.9 | CB12: 1644036.8 | CC12: 0.12640478 | CD12: 65155.91 | CE12: 41452.468 | CF12: 0.57182221 | CG12: 1917006.8 | CH12: 1685489.2 | CI12: 0.13735926 | CJ12: 231517.56
A13: Receita Serviços | B13: 0 | C13: 0 | D13: - | E13: 1148925 | F13: 1642600 | G13: -0.30054484 | H13: 1148925 | I13: 1642600 | J13: -0.30054484 | K13: -493674.96 | M13: 0 | N13: 0 | O13: - | P13: 1421204 | Q13: 1591000 | R13: -0.10672279 | S13: 1421204 | T13: 1591000 | U13: -0.10672279 | V13: -169795.96 | X13: 0 | Y13: 0 | Z13: - | AA13: 2558364.6 | AB13: 1754400 | AC13: 0.45825613 | AD13: 2558364.6 | AE13: 1754400 | AF13: 0.45825613 | AG13: 803964.56 | AI13: 0 | AJ13: 0 | AK13: - | AL13: 1909358.2 | AM13: 1720000 | AN13: 0.11009201 | AO13: 1909358.2 | AP13: 1720000 | AQ13: 0.11009201 | AR13: 189358.25 | AT13: 0 | AU13: 0 | AV13: - | AW13: 2264503.4 | AX13: 1625400 | AY13: 0.39319759 | AZ13: 2264503.4 | BA13: 1625400 | BB13: 0.39319759 | BC13: 639103.37 | BE13: 0 | BF13: 0 | BG13: - | BH13: 2087666.2 | BI13: 1754400 | BJ13: 0.18996024 | BK13: 2087666.2 | BL13: 1754400 | BM13: 0.18996024 | BN13: 333266.25 | BP13: 0 | BQ13: 0 | BR13: - | BS13: 2315531.5 | BT13: 1978000 | BU13: 0.1706428 | BV13: 2315531.5 | BW13: 1978000 | BX13: 0.1706428 | BY13: 337531.46 | CA13: 0 | CB13: 0 | CC13: - | CD13: 1993030.1 | CE13: 1892000 | CF13: 0.053398589 | CG13: 1993030.1 | CH13: 1892000 | CI13: 0.053398589 | CJ13: 101030.13
A14: Receita Interchange | B14: 9001.6569 | C14: 12466.562 | D14: -0.27793588 | E14: 12128.993 | F14: 16829.858 | G14: -0.27931698 | H14: 21130.65 | I14: 29296.42 | J14: -0.27872928 | K14: -8165.77 | M14: 8163.3698 | N14: 12466.562 | O14: -0.34517872 | P14: 10999.47 | Q14: 16829.858 | R14: -0.34643121 | S14: 19162.84 | T14: 29296.42 | U14: -0.34589824 | V14: -10133.58 | X14: 8879.4971 | Y14: 12466.562 | Z14: -0.28773487 | AA14: 11964.393 | AB14: 16829.858 | AC14: -0.28909723 | AD14: 20843.89 | AE14: 29296.42 | AF14: -0.2885175 | AG14: -8452.53 | AI14: 8498.4553 | AJ14: 12466.562 | AK14: -0.31829998 | AL14: 11472.915 | AM14: 16829.858 | AN14: -0.31829998 | AO14: 19971.37 | AP14: 29296.42 | AQ14: -0.31829998 | AR14: -9325.05 | AT14: 8420.0255 | AU14: 12466.562 | AV14: -0.3245912 | AW14: 11367.034 | AX14: 16829.858 | AY14: -0.3245912 | AZ14: 19787.06 | BA14: 29296.42 | BB14: -0.3245912 | BC14: -9509.36 | BE14: 7788.9371 | BF14: 12466.562 | BG14: -0.37521369 | BH14: 10494.953 | BI14: 16829.858 | BJ14: -0.37640872 | BK14: 18283.89 | BL14: 29296.42 | BM14: -0.3759002 | BN14: -11012.53 | BP14: 7986.8823 | BQ14: 12466.562 | BR14: -0.3593356 | BS14: 10761.668 | BT14: 16829.858 | BU14: -0.360561 | BV14: 18748.55 | BW14: 29296.42 | BX14: -0.36003955 | BY14: -10547.87 | CA14: 0 | CB14: 12466.562 | CC14: -1 | CD14: 17196.73 | CE14: 16829.858 | CF14: 0.021798859 | CG14: 17196.73 | CH14: 29296.42 | CI14: -0.41300917 | CJ14: -12099.69
A15: Receita Comissão CRI | B15: 0 | C15: 0 | D15: - | E15: 0 | F15: 0 | G15: - | H15: 0 | I15: 0 | J15: - | K15: 0 | M15: 0 | N15: 0 | O15: - | P15: 0 | Q15: 0 | R15: - | S15: 0 | T15: 0 | U15: - | V15: 0 | X15: 0 | Y15: 0 | Z15: - | AA15: 0 | AB15: 0 | AC15: - | AD15: 0 | AE15: 0 | AF15: - | AG15: 0 | AI15: 0 | AJ15: 0 | AK15: - | AL15: 0 | AM15: 0 | AN15: - | AO15: 0 | AP15: 0 | AQ15: - | AR15: 0 | AT15: 0 | AU15: 0 | AV15: - | AW15: 0 | AX15: 0 | AY15: - | AZ15: 0 | BA15: 0 | BB15: - | BC15: 0 | BE15: 0 | BF15: 0 | BG15: - | BH15: 0 | BI15: 0 | BJ15: - | BK15: 0 | BL15: 0 | BM15: - | BN15: 0 | BP15: 0 | BQ15: 0 | BR15: - | BS15: 0 | BT15: 0 | BU15: - | BV15: 0 | BW15: 0 | BX15: - | BY15: 0 | CA15: 0 | CB15: 0 | CC15: - | CD15: 0 | CE15: 0 | CF15: - | CG15: 0 | CH15: 0 | CI15: - | CJ15: 0
A16: Receita Cobrança Ext. Cebraco | B16: 0 | C16: 0 | D16: - | E16: 364301.13 | F16: 364301.13 | G16: 0 | H16: 364301.13 | I16: 364301.13 | J16: 0 | K16: 0 | M16: 0 | N16: 0 | O16: - | P16: 168561.35 | Q16: 282753.77 | R16: -0.40385817 | S16: 168561.35 | T16: 282753.77 | U16: -0.40385817 | V16: -114192.42 | X16: 0 | Y16: 0 | Z16: - | AA16: 155899.01 | AB16: 282753.77 | AC16: -0.44864039 | AD16: 155899.01 | AE16: 282753.77 | AF16: -0.44864039 | AG16: -126854.76 | AI16: 0 | AJ16: 0 | AK16: - | AL16: 396916.38 | AM16: 282753.77 | AN16: 0.40375273 | AO16: 396916.38 | AP16: 282753.77 | AQ16: 0.40375273 | AR16: 114162.61 | AT16: 0 | AU16: 0 | AV16: - | AW16: 405034.85 | AX16: 282753.77 | AY16: 0.43246488 | AZ16: 405034.85 | BA16: 282753.77 | BB16: 0.43246488 | BC16: 122281.08 | BE16: 0 | BF16: 0 | BG16: - | BH16: 434422.58 | BI16: 282753.77 | BJ16: 0.53639888 | BK16: 434422.58 | BL16: 282753.77 | BM16: 0.53639888 | BN16: 151668.81 | BP16: 0 | BQ16: 0 | BR16: - | BS16: 379623.97 | BT16: 282753.77 | BU16: 0.3425956 | BV16: 379623.97 | BW16: 282753.77 | BX16: 0.3425956 | BY16: 96870.198 | CA16: 0 | CB16: 0 | CC16: - | CD16: 324764.68 | CE16: 282753.77 | CF16: 0.14857771 | CG16: 324764.68 | CH16: 282753.77 | CI16: 0.14857771 | CJ16: 42010.908
A17: Resultado de Seguros | B17: 0 | C17: 0 | D17: - | E17: 976784.38 | F17: 976784.38 | G17: 0 | H17: 976784.38 | I17: 976784.38 | J17: 0 | K17: 0 | M17: 0 | N17: 0 | O17: - | P17: 743112.13 | Q17: 900000 | R17: -0.17431986 | S17: 743112.13 | T17: 900000 | U17: -0.17431986 | V17: -156887.87 | X17: 0 | Y17: 0 | Z17: - | AA17: 1006702.7 | AB17: 900000 | AC17: 0.11855856 | AD17: 1006702.7 | AE17: 900000 | AF17: 0.11855856 | AG17: 106702.7 | AI17: 0 | AJ17: 0 | AK17: - | AL17: 948906.08 | AM17: 900000 | AN17: 0.054340089 | AO17: 948906.08 | AP17: 900000 | AQ17: 0.054340089 | AR17: 48906.08 | AT17: 0 | AU17: 0 | AV17: - | AW17: 1018281 | AX17: 900000 | AY17: 0.1314233 | AZ17: 1018281 | BA17: 900000 | BB17: 0.1314233 | BC17: 118280.97 | BE17: 0 | BF17: 0 | BG17: - | BH17: 1045395.2 | BI17: 900000 | BJ17: 0.16155027 | BK17: 1045395.2 | BL17: 900000 | BM17: 0.16155027 | BN17: 145395.24 | BP17: 0 | BQ17: 0 | BR17: - | BS17: 1027683.8 | BT17: 900000 | BU17: 0.14187087 | BV17: 1027683.8 | BW17: 900000 | BX17: 0.14187087 | BY17: 127683.78 | CA17: 0 | CB17: 0 | CC17: - | CD17: 1097822.6 | CE17: 900000 | CF17: 0.21980283 | CG17: 1097822.6 | CH17: 900000 | CI17: 0.21980283 | CJ17: 197822.55
A18: Resultado Brasil Cards | B18: 0 | C18: 0 | D18: - | E18: 65704.18 | F18: 65704.18 | G18: 0 | H18: 65704.18 | I18: 65704.18 | J18: 0 | K18: 0 | M18: 0 | N18: 0 | O18: - | P18: 49730.27 | Q18: -163.435 | R18: -305.28164 | S18: 49730.27 | T18: -163.435 | U18: -305.28164 | V18: 49893.705 | X18: 0 | Y18: 0 | Z18: - | AA18: 126708.72 | AB18: -163.435 | AC18: -776.2851 | AD18: 126708.72 | AE18: -163.435 | AF18: -776.2851 | AG18: 126872.15 | AI18: 0 | AJ18: 0 | AK18: - | AL18: 89809.88 | AM18: -163.435 | AN18: -550.51436 | AO18: 89809.88 | AP18: -163.435 | AQ18: 550.51436 | AR18: 89973.315 | AT18: 0 | AU18: 0 | AV18: - | AW18: 40616.85 | AX18: -163.435 | AY18: -249.5199 | AZ18: 40616.85 | BA18: -163.435 | BB18: 249.5199 | BC18: 40780.285 | BE18: 0 | BF18: 0 | BG18: - | BH18: 82542.05 | BI18: -163.435 | BJ18: -506.04512 | BK18: 82542.05 | BL18: -163.435 | BM18: 506.04512 | BN18: 82705.485 | BP18: 0 | BQ18: 0 | BR18: - | BS18: 123398.41 | BT18: -163.435 | BU18: -756.0305 | BV18: 123398.41 | BW18: -163.435 | BX18: 756.0305 | BY18: 123561.84 | CA18: 0 | CB18: 0 | CC18: - | CD18: 46536.18 | CE18: -163.435 | CF18: -285.73815 | CG18: 46536.18 | CH18: -163.435 | CI18: 285.73815 | CJ18: 46699.615
A19: Resultado Bari Capital | B19: 0 | C19: 0 | D19: - | E19: 168678.17 | F19: 168678.17 | G19: 0 | H19: 168678.17 | I19: 168678.17 | J19: 0 | K19: 0 | M19: 0 | N19: 0 | O19: - | P19: -629.72 | Q19: 52800 | R19: -1.0119265 | S19: -629.72 | T19: 52800 | U19: -1.0119265 | V19: -53429.72 | X19: 0 | Y19: 0 | Z19: - | AA19: -262478.75 | AB19: 19800 | AC19: -14.256503 | AD19: -262478.75 | AE19: 19800 | AF19: -14.256503 | AG19: -282278.75 | AI19: 0 | AJ19: 0 | AK19: - | AL19: 23664.61 | AM19: 19800 | AN19: 0.19518232 | AO19: 23664.61 | AP19: 19800 | AQ19: 0.19518232 | AR19: 3864.61 | AT19: 0 | AU19: 0 | AV19: - | AW19: -87553.01 | AX19: 19800 | AY19: -5.4218692 | AZ19: -87553.01 | BA19: 19800 | BB19: -5.4218692 | BC19: -107353.01 | BE19: 0 | BF19: 0 | BG19: - | BH19: 15935.41 | BI19: 19800 | BJ19: -0.19518131 | BK19: 15935.41 | BL19: 19800 | BM19: -0.19518131 | BN19: -3864.59 | BP19: 0 | BQ19: 0 | BR19: - | BS19: 24659.56 | BT19: 19800 | BU19: 0.24543232 | BV19: 24659.56 | BW19: 19800 | BX19: 0.24543232 | BY19: 4859.56 | CA19: 0 | CB19: 0 | CC19: - | CD19: 16626.2 | CE19: 19800 | CF19: -0.16029293 | CG19: 16626.2 | CH19: 19800 | CI19: -0.16029293 | CJ19: -3173.8
A20: Resultado Sec | B20: 0 | C20: 0 | D20: - | E20: 87060.33 | F20: 87060.33 | G20: 0 | H20: 87060.33 | I20: 87060.33 | J20: 0 | K20: 0 | M20: 0 | N20: 0 | O20: - | P20: 243037.75 | Q20: 210147.87 | R20: 0.15650829 | S20: 243037.75 | T20: 210147.87 | U20: 0.15650829 | V20: 32889.883 | X20: 0 | Y20: 0 | Z20: - | AA20: 521291.11 | AB20: 210147.87 | AC20: 1.480592 | AD20: 521291.11 | AE20: 210147.87 | AF20: 1.480592 | AG20: 311143.24 | AI20: 0 | AJ20: 0 | AK20: - | AL20: 725407.97 | AM20: 210147.87 | AN20: 2.4518931 | AO20: 725407.97 | AP20: 210147.87 | AQ20: 2.4518931 | AR20: 515260.1 | AT20: 0 | AU20: 0 | AV20: - | AW20: 597908.29 | AX20: 210147.87 | AY20: 1.845179 | AZ20: 597908.29 | BA20: 210147.87 | BB20: 1.845179 | BC20: 387760.42 | BE20: 0 | BF20: 0 | BG20: - | BH20: 1829477.4 | BI20: 210147.87 | BJ20: 7.7056673 | BK20: 1829477.4 | BL20: 210147.87 | BM20: 7.7056673 | BN20: 1619329.5 | BP20: 0 | BQ20: 0 | BR20: - | BS20: 750956.22 | BT20: 210147.87 | BU20: 2.5734658 | BV20: 750956.22 | BW20: 210147.87 | BX20: 2.5734658 | BY20: 540808.35 | CA20: 0 | CB20: 0 | CC20: - | CD20: 1263134.2 | CE20: 210147.87 | CF20: 5.0106927 | CG20: 1263134.2 | CH20: 210147.87 | CI20: 5.0106927 | CJ20: 1052986.4
A21: DESPESAS DE ORIGINAÇÃO | B21: -4115579.3 | C21: -4007372 | D21: 0.027002072 | E21: -13893293 | F21: -13901145 | G21: -0.0005648475 | H21: -18008872 | I21: -17908517 | J21: 0.005603776 | K21: 100355.32 | M21: -3458538.1 | N21: -3324628.9 | O21: 0.040277941 | P21: -11194223 | Q21: -12699380 | R21: -0.11852208 | S21: -14652761 | T21: -16024009 | U21: -0.085574575 | V21: -1371247.8 | X21: -4803644.1 | Y21: -4620516.9 | Z21: 0.039633491 | AA21: -17862654 | AB21: -15301310 | AC21: 0.16739376 | AD21: -22666298 | AE21: -19921827 | AF21: 0.13776202 | AG21: 2744471.1 | AI21: -4383516.3 | AJ21: -4409897.3 | AK21: -0.0059822152 | AL21: -17657422 | AM21: -13769320 | AN21: 0.28237426 | AO21: -22040938 | AP21: -18179217 | AQ21: 0.21242502 | AR21: 3861720.6 | AT21: -4480613.7 | AU21: -4475939 | AV21: 0.0010444098 | AW21: -15739911 | AX21: -13995733 | AY21: 0.12462214 | AZ21: -20220525 | BA21: -18471672 | BB21: 0.094677562 | BC21: 1748852.9 | BE21: -4804004.9 | BF21: -4848789.1 | BG21: -0.0092361716 | BH21: -17194338 | BI21: -14559699 | BJ21: 0.1809542 | BK21: -21998343 | BL21: -19408488 | BM21: 0.13343927 | BN21: 2589854.5 | BP21: -5126638.3 | BQ21: -5185752.6 | BR21: -0.011399367 | BS21: -15385685 | BT21: -16115171 | BU21: -0.045267019 | BV21: -20512323 | BW21: -21300923 | BX21: -0.037021871 | BY21: -788600.05 | CA21: -5025450.5 | CB21: -4722997.6 | CC21: 0.064038339 | CD21: -13507739 | CE21: -15393726 | CF21: -0.12251655 | CG21: -18533190 | CH21: -20116723 | CI21: -0.078717256 | CJ21: -1583533.2
A22: Despesa de Captação* | B22: -4115579.3 | C22: -4007372 | D22: 0.027002072 | E22: -13893293 | F22: -13901145 | G22: -0.0005648475 | H22: -18008872 | I22: -17908517 | J22: 0.005603776 | K22: 100355.32 | M22: -3458538.1 | N22: -3324628.9 | O22: 0.040277941 | P22: -11194223 | Q22: -12699380 | R22: -0.11852208 | S22: -14652761 | T22: -16024009 | U22: -0.085574575 | V22: -1371247.8 | X22: -4803644.1 | Y22: -4620516.9 | Z22: 0.039633491 | AA22: -17862654 | AB22: -15301310 | AC22: 0.16739376 | AD22: -22666298 | AE22: -19921827 | AF22: 0.13776202 | AG22: 2744471.1 | AI22: -4383516.3 | AJ22: -4409897.3 | AK22: -0.0059822152 | AL22: -17657422 | AM22: -13769320 | AN22: 0.28237426 | AO22: -22040938 | AP22: -18179217 | AQ22: 0.21242502 | AR22: 3861720.6 | AT22: -4480613.7 | AU22: -4475939 | AV22: 0.0010444098 | AW22: -15739911 | AX22: -13995733 | AY22: 0.12462214 | AZ22: -20220525 | BA22: -18471672 | BB22: 0.094677562 | BC22: 1748852.9 | BE22: -4804004.9 | BF22: -4848789.1 | BG22: -0.0092361716 | BH22: -17194338 | BI22: -14559699 | BJ22: 0.1809542 | BK22: -21998343 | BL22: -19408488 | BM22: 0.13343927 | BN22: 2589854.5 | BP22: -5126638.3 | BQ22: -5185752.6 | BR22: -0.011399367 | BS22: -15385685 | BT22: -16115171 | BU22: -0.045267019 | BV22: -20512323 | BW22: -21300923 | BX22: -0.037021871 | BY22: -788600.05 | CA22: -5025450.5 | CB22: -4722997.6 | CC22: 0.064038339 | CD22: -13507739 | CE22: -15393726 | CF22: -0.12251655 | CG22: -18533190 | CH22: -20116723 | CI22: -0.078717256 | CJ22: -1583533.2
A23: Inflação | B23: 0 | C23: 0 | D23: - | E23: -4338842.1 | F23: -4518124.4 | G23: -0.039680693 | H23: -4338842.1 | I23: -4518124.4 | J23: -0.039680693 | K23: -179282.3 | M23: 0 | N23: 0 | O23: - | P23: -2862311.8 | Q23: -4228882.5 | R23: -0.32315172 | S23: -2862311.8 | T23: -4228882.5 | U23: -0.32315172 | V23: -1366570.6 | X23: 0 | Y23: 0 | Z23: - | AA23: -6665373.2 | AB23: -5380522.2 | AC23: 0.23879672 | AD23: -6665373.2 | AE23: -5380522.2 | AF23: 0.23879672 | AG23: 1284851 | AI23: 0 | AJ23: 0 | AK23: - | AL23: -6969927.4 | AM23: -4629193.2 | AN23: 0.50564626 | AO23: -6969927.4 | AP23: -4629193.2 | AQ23: 0.50564626 | AR23: 2340734.2 | AT23: 0 | AU23: 0 | AV23: - | AW23: -6000837.3 | AX23: -4876832.3 | AY23: 0.2304785 | AZ23: -6000837.3 | BA23: -4876832.3 | BB23: 0.2304785 | BC23: 1124005 | BE23: 0 | BF23: 0 | BG23: - | BH23: -5905393.9 | BI23: -5484976.1 | BJ23: 0.076648977 | BK23: -5905393.9 | BL23: -5484976.1 | BM23: 0.076648977 | BN23: 420417.8 | BP23: 0 | BQ23: 0 | BR23: - | BS23: -4071249.5 | BT23: -6454051.8 | BU23: -0.3691948 | BV23: -4071249.5 | BW23: -6454051.8 | BX23: -0.3691948 | BY23: -2382802.3 | CA23: 0 | CB23: 0 | CC23: - | CD23: -2947018.9 | CE23: -6691989.2 | CF23: -0.5596199 | CG23: -2947018.9 | CH23: -6691989.2 | CI23: -0.5596199 | CJ23: -3744970.3
A24: Componente Juros | E24: -2698465 | F24: -2734250.7 | H24: -2698465 | I24: -2734250.7 | P24: 0 | Q24: -2303836.3 | S24: 0 | T24: -2303836.3 | AA24: 0 | AB24: -2734250.7 | AD24: 0 | AE24: -2734250.7 | AL24: -1317867.5 | AM24: -2734250.7 | AO24: -1317867.5 | AP24: -2734250.7 | AW24: 0 | AX24: -2734250.7 | AZ24: 0 | BA24: -2734250.7 | BH24: 0 | BI24: -2734250.7 | BK24: 0 | BL24: -2734250.7 | BS24: 0 | BT24: -2734250.7 | BV24: 0 | BW24: -2734250.7 | CD24: 0 | CE24: -2734250.7 | CG24: 0 | CH24: -2734250.7
A25: Componente Inflação | E25: -1640377 | F25: -1783873.7 | H25: -1640377 | I25: -1783873.7 | P25: 0 | Q25: -1925046.1 | S25: 0 | T25: -1925046.1 | AA25: 0 | AB25: -1783873.7 | AD25: 0 | AE25: -1783873.7 | AL25: -5652059.9 | AM25: -1783873.7 | AO25: -5652059.9 | AP25: -1783873.7 | AW25: 0 | AX25: -1783873.7 | AZ25: 0 | BA25: -1783873.7 | BH25: 0 | BI25: -1783873.7 | BK25: 0 | BL25: -1783873.7 | BS25: 0 | BT25: -1783873.7 | BV25: 0 | BW25: -1783873.7 | CD25: 0 | CE25: -1783873.7 | CG25: 0 | CH25: -1783873.7
A26: DI/Pré | B26: -4984061.2 | C26: -4887881.8 | D26: 0.019677121 | E26: -11789044 | F26: -11585572 | G26: 0.01756256 | H26: -16773105 | I26: -16473453 | J26: 0.018189977 | K26: 299651.74 | M26: -4152791.2 | N26: -4008310.8 | O26: 0.03604519 | P26: -10408000 | Q26: -10215152 | R26: 0.018878589 | S26: -14560791 | T26: -14223463 | U26: 0.023716305 | V26: 337327.98 | X26: -5760280.5 | Y26: -5697287.1 | Z26: 0.011056736 | AA26: -13440654 | AB26: -12757576 | AC26: 0.053542988 | AD26: -19200935 | AE26: -18454863 | AF26: 0.040426859 | AG26: 746072.13 | AI26: -5204115.9 | AJ26: -5117668.8 | AK26: 0.01689189 | AL26: -12741111 | AM26: -11271781 | AN26: 0.13035475 | AO26: -17945227 | AP26: -16389450 | AQ26: 0.094925535 | AR26: 1555777.3 | AT26: -5266286.5 | AU26: -5078309.7 | AV26: 0.037015619 | AW26: -12674669 | AX26: -11127174 | AY26: 0.13907345 | AZ26: -17940955 | BA26: -16205484 | BB26: 0.1070916 | BC26: 1735471.3 | BE26: -5559732.4 | BF26: -5501427.3 | BG26: 0.010598163 | BH26: -13383138 | BI26: -11245629 | BJ26: 0.19007464 | BK26: -18942870 | BL26: -16747056 | BM26: 0.13111641 | BN26: 2195813.9 | BP26: -6167797.6 | BQ26: -5895987.6 | BR26: 0.046100843 | BS26: -14955231 | BT26: -12018373 | BU26: 0.24436399 | BV26: -21123028 | BW26: -17914361 | BX26: 0.17911148 | BY26: 3208667.6 | CA26: -5808990.2 | CB26: -5299733.4 | CC26: 0.096091022 | CD26: -13554310 | CE26: -10761383 | CF26: 0.25953234 | CG26: -19363301 | CH26: -16061117 | CI26: 0.20560113 | CJ26: 3302183.8
A27: Receita Financeira + Outros | B27: 533676.18 | C27: 531727.93 | D27: 0.0036639906 | E27: 1892124.6 | F27: 1901930.8 | G27: -0.005155904 | H27: 2425800.8 | I27: 2433658.7 | J27: -0.0032288531 | K27: -7857.9266 | M27: 421756.82 | N27: 403487.21 | O27: 0.045279273 | P27: 1687027.3 | Q27: 1470614.5 | R27: 0.14715804 | S27: 2108784.1 | T27: 1874101.7 | U27: 0.12522392 | V27: 234682.36 | X27: 683833.18 | Y27: 685924.94 | Z27: -0.0030495583 | AA27: 2424498.8 | AB27: 2565677.8 | AC27: -0.055025999 | AD27: 3108332 | AE27: 3251602.8 | AF27: -0.044061579 | AG27: -143270.75 | AI27: 632916.77 | AJ27: 463465.43 | AK27: 0.36561809 | AL27: 2243977.1 | AM27: 1769377.3 | AN27: 0.26822984 | AO27: 2876893.8 | AP27: 2232842.7 | AQ27: 0.28844447 | AR27: 644051.12 | AT27: 653443.91 | AU27: 442543.5 | AV27: 0.47656425 | AW27: 2542606.5 | AX27: 1721974.8 | AY27: 0.47656425 | AZ27: 3196050.4 | BA27: 2164518.3 | BB27: 0.47656425 | BC27: 1031532.1 | BE27: 646501.36 | BF27: 459367.83 | BG27: 0.40737186 | BH27: 2586005.4 | BI27: 1828004.2 | BJ27: 0.41466057 | BK27: 3232506.8 | BL27: 2287372 | BM27: 0.4131968 | BN27: 945134.79 | BP27: 797904.45 | BQ27: 500253.85 | BR27: 0.59499911 | BS27: 3191617.8 | BT27: 2040947.9 | BU27: 0.56379194 | BV27: 3989522.3 | BW27: 2541201.7 | BX27: 0.5699353 | BY27: 1448320.6 | CA27: 672996.15 | CB27: 449216.63 | CC27: 0.49815503 | CD27: 2691984.6 | CE27: 1875600.6 | CF27: 0.43526538 | CG27: 3364980.8 | CH27: 2324817.2 | CI27: 0.44741734 | CJ27: 1040163.5
A28: Swap | B28: 334805.76 | C28: 348781.91 | D28: -0.040071313 | E28: 342468.2 | F28: 300620.01 | G28: 0.13920628 | H28: 677273.96 | I28: 649401.92 | J28: 0.04291956 | K28: 27872.044 | M28: 272496.22 | N28: 280194.71 | O28: -0.027475496 | P28: 389061.42 | Q28: 274040.18 | R28: 0.419724 | S28: 661557.64 | T28: 554234.89 | U28: 0.19364128 | V28: 107322.75 | X28: 272803.21 | Y28: 390845.25 | Z28: -0.30201734 | AA28: -181125.23 | AB28: 271109.87 | AC28: -1.6680879 | AD28: 91677.98 | AE28: 661955.12 | AF28: -0.86150424 | AG28: -570277.14 | AI28: 187682.84 | AJ28: 244306.13 | AK28: -0.23177187 | AL28: -190359.85 | AM28: 362277.06 | AN28: -1.5254538 | AO28: -2677.01 | AP28: 606583.19 | AQ28: -1.0044133 | AR28: -603906.18 | AT28: 132228.9 | AU28: 159827.25 | AV28: -0.17267613 | AW28: 392988.54 | AX28: 286298.84 | AY28: 0.37265152 | AZ28: 525217.44 | BA28: 446126.09 | BB28: 0.17728474 | BC28: 79091.347 | BE28: 109226.11 | BF28: 193270.37 | BG28: -0.4348533 | BH28: -491811.7 | BI28: 342901.61 | BJ28: -2.4342648 | BK28: -382585.59 | BL28: 536171.98 | BM28: -1.7135501 | BN28: -153586.39 | BP28: 243254.8 | BQ28: 209981.1 | BR28: 0.15846045 | BS28: 449177.28 | BT28: 316306.27 | BU28: 0.42007075 | BV28: 692432.08 | BW28: 526287.37 | BX28: 0.315692 | BY28: 166144.71 | CA28: 110543.56 | CB28: 127519.2 | CC28: -0.13312224 | CD28: 301605.31 | CE28: 184046.44 | CF28: 0.63874572 | CG28: 412148.87 | CH28: 311565.64 | CI28: 0.3228316 | CJ28: 100583.23
A29: Impostos Diretos | B29: -182166.93 | C29: -135078 | D29: 0.34860546 | E29: -395690.12 | F29: -478914 | G29: -0.17377625 | H29: -577857.05 | I29: -613992 | J29: -0.058852477 | K29: -36134.95 | M29: -175268.7 | N29: -138230.37 | O29: 0.2679464 | P29: -692764.18 | Q29: -490089.49 | R29: 0.41354628 | S29: -868032.88 | T29: -628319.86 | U29: 0.38151431 | V29: 239713.02 | X29: -220529.89 | Y29: -169005.8 | Z29: 0.30486581 | AA29: -871661.11 | AB29: -599202.39 | AC29: 0.45470232 | AD29: -1092191 | AE29: -768208.19 | AF29: 0.42173829 | AG29: 323982.81 | AI29: -171495.89 | AJ29: -168402.62 | AK29: 0.018368302 | AL29: -888547.03 | AM29: -597063.83 | AN29: 0.48819437 | AO29: -1060042.9 | AP29: -765466.45 | AQ29: 0.38483263 | AR29: 294576.47 | AT29: -313022.82 | AU29: -156646.84 | AV29: 0.99827087 | AW29: -1109808.2 | AX29: -555384.26 | AY29: 0.99827087 | AZ29: -1422831 | BA29: -712031.11 | BB29: 0.99827087 | BC29: 710799.91 | BE29: -323969.33 | BF29: -170010.17 | BG29: 0.90558788 | BH29: -1148618.5 | BI29: -602763.35 | BJ29: 0.90558788 | BK29: -1472587.9 | BL29: -772773.52 | BM29: 0.90558788 | BN29: 699814.33 | BP29: -282755.63 | BQ29: -154750.92 | BR29: 0.82716611 | BS29: -1002497.2 | BT29: -548662.34 | BU29: 0.82716611 | BV29: -1285252.9 | BW29: -703413.26 | BX29: 0.82716611 | BY29: 581839.6 | CA29: -259689.54 | CB29: -174347.38 | CC29: 0.48949492 | CD29: -920717.46 | CE29: -618140.72 | CF29: 0.48949492 | CG29: -1180407 | CH29: -792488.1 | CI29: 0.48949492 | CJ29: 387918.9
A30: MARGEM INTERMEDIAÇÃO | B30: 3504281.6 | C30: 3559264.4 | D30: -0.01544778 | E30: 9570904.2 | F30: 10152489 | G30: -0.057284973 | H30: 13075186 | I30: 13711754 | J30: -0.046424974 | K30: -636567.8 | M30: 3464917.2 | N30: 3528656.9 | O30: -0.018063442 | P30: 11886877 | Q30: 10228503 | R30: 0.16213256 | S30: 15351794 | T30: 13757160 | U30: 0.115913 | V30: 1594633.7 | X30: 2853178.9 | Y30: 2969870 | Z30: -0.039291633 | AA30: 15040297 | AB30: 13563862 | AC30: 0.10885068 | AD30: 17893476 | AE30: 16533732 | AF30: 0.082240631 | AG30: 1359744.5 | AI30: 2958757.4 | AJ30: 2973212.1 | AK30: -0.0048616244 | AL30: 15845885 | AM30: 13460923 | AN30: 0.17717666 | AO30: 18804642 | AP30: 16434135 | AQ30: 0.14424287 | AR30: 2370506.8 | AT30: 2791893.9 | AU30: 3205174.7 | AV30: -0.12894174 | AW30: 20634238 | AX30: 12088122 | AY30: 0.70698461 | AZ30: 23426132 | BA30: 15293297 | BB30: 0.53179086 | BC30: 8132835.5 | BE30: 2640144.9 | BF30: 2608153.5 | BG30: 0.012265932 | BH30: 16335295 | BI30: 13890443 | BJ30: 0.17600962 | BK30: 18975440 | BL30: 16498597 | BM30: 0.15012447 | BN30: 2476843.1 | BP30: 2415970.1 | BQ30: 2574598.1 | BR30: -0.061612724 | BS30: 15918285 | BT30: 12449621 | BU30: 0.27861603 | BV30: 18334255 | BW30: 15024219 | BX30: 0.22031335 | BY30: 3310036 | CA30: 2374836.8 | CB30: 3059936.8 | CC30: -0.2238935 | CD30: 14331429 | CE30: 13742626 | CF30: 0.042845014 | CG30: 16706266 | CH30: 16802563 | CI30: -0.0057310865 | CJ30: -96296.942
A31: Provisões | B31: -725978.64 | C31: -724707 | D31: 0.0017546987 | E31: -1516697.2 | F31: -1528471.5 | G31: -0.007703321 | H31: -2242675.9 | I31: -2253178.5 | J31: -0.004661266 | K31: -10502.664 | M31: -403888.51 | N31: -555191.52 | O31: -0.272524 | P31: -1775414.1 | Q31: -916664.33 | R31: 0.93682033 | S31: -2179302.6 | T31: -1471855.9 | U31: 0.48064949 | V31: 707446.77 | X31: -610260.52 | Y31: -577819.12 | Z31: 0.056144559 | AA31: -439697.65 | AB31: -1292046.2 | AC31: -0.65968892 | AD31: -1049958.2 | AE31: -1869865.4 | AF31: -0.43848461 | AG31: -819907.19 | AI31: -483020.98 | AJ31: -572342.1 | AK31: -0.15606247 | AL31: -2252289.5 | AM31: -1105001.8 | AN31: 1.0382678 | AO31: -2735310.5 | AP31: -1677343.9 | AQ31: 0.63073926 | AR31: 1057966.6 | AT31: -706208.48 | AU31: -579408.77 | AV31: 0.21884327 | AW31: -2828879.5 | AX31: -1110416.4 | AY31: 1.5475843 | AZ31: -3535088 | BA31: -1689825.2 | BB31: 1.0919844 | BC31: 1845262.8 | BE31: -455481.61 | BF31: -569041.42 | BG31: -0.19956335 | BH31: -1360932.6 | BI31: -1629488.8 | BJ31: -0.16481008 | BK31: -1816414.2 | BL31: -2198530.2 | BM31: -0.17380521 | BN31: -382115.99 | BP31: -618169.09 | BQ31: -640107.42 | BR31: -0.034272888 | BS31: -1454128.3 | BT31: -1848475.3 | BU31: -0.21333637 | BV31: -2072297.4 | BW31: -2488582.8 | BX31: -0.16727808 | BY31: -416285.34 | CA31: -646083.22 | CB31: -637930.47 | CC31: 0.012779991 | CD31: 163085.18 | CE31: -1812314.4 | CF31: -1.0899872 | CG31: -482998.04 | CH31: -2450244.9 | CI31: -0.80287764 | CJ31: -1967246.8
A32: Provisões | B32: -725978.64 | C32: -724707 | D32: 0.0017546987 | E32: -1516697.2 | F32: -1528471.5 | G32: -0.007703321 | H32: -2242675.9 | I32: -2253178.5 | J32: -0.004661266 | K32: -10502.664 | M32: -403888.51 | N32: -555191.52 | O32: -0.272524 | P32: -1775414.1 | Q32: -916664.33 | R32: 0.93682033 | S32: -2179302.6 | T32: -1471855.9 | U32: 0.48064949 | V32: 707446.77 | X32: -610260.52 | Y32: -577819.12 | Z32: 0.056144559 | AA32: -439697.65 | AB32: -1292046.2 | AC32: -0.65968892 | AD32: -1049958.2 | AE32: -1869865.4 | AF32: -0.43848461 | AG32: -819907.19 | AI32: -483020.98 | AJ32: -572342.1 | AK32: -0.15606247 | AL32: -1281924.5 | AM32: -1105001.8 | AN32: 0.16011082 | AO32: -1764945.5 | AP32: -1677343.9 | AQ32: 0.05222639 | AR32: 87601.616 | AT32: -706208.48 | AU32: -579408.77 | AV32: 0.21884327 | AW32: -2070863.1 | AX32: -1110416.4 | AY32: 0.86494273 | AZ32: -2777071.6 | BA32: -1689825.2 | BB32: 0.64340757 | BC32: 1087246.3 | BE32: -455481.61 | BF32: -569041.42 | BG32: -0.19956335 | BH32: -1395283.6 | BI32: -1629488.8 | BJ32: -0.14372923 | BK32: -1850765.2 | BL32: -2198530.2 | BM32: -0.15818067 | BN32: -347764.97 | BP32: -618169.09 | BQ32: -640107.42 | BR32: -0.034272888 | BS32: -1454128.3 | BT32: -1848475.3 | BU32: -0.21333637 | BV32: -2072297.4 | BW32: -2488582.8 | BX32: -0.16727808 | BY32: -416285.34 | CA32: -646083.22 | CB32: -637930.47 | CC32: 0.012779991 | CD32: 438242.42 | CE32: -1812314.4 | CF32: -1.2418137 | CG32: -207840.8 | CH32: -2450244.9 | CI32: -0.9151755 | CJ32: -2242404.1
A33: Desvalorização de BNDU | B33: 0 | C33: 0 | D33: - | E33: 0 | F33: 0 | G33: - | H33: 0 | I33: 0 | J33: - | K33: 0 | M33: 0 | N33: 0 | O33: - | P33: 0 | Q33: 0 | R33: - | S33: 0 | T33: 0 | U33: - | V33: 0 | X33: 0 | Y33: 0 | Z33: - | AA33: 0 | AB33: 0 | AC33: - | AD33: 0 | AE33: 0 | AF33: - | AG33: 0 | AI33: 0 | AJ33: 0 | AK33: - | AL33: -970365.02 | AM33: 0 | AN33: - | AO33: -970365.02 | AP33: 0 | AQ33: - | AR33: -970365.02 | AT33: 0 | AU33: 0 | AV33: - | AW33: -758016.47 | AX33: 0 | AY33: - | AZ33: -758016.47 | BA33: 0 | BB33: - | BC33: -758016.47 | BE33: 0 | BF33: 0 | BG33: - | BH33: 34351.02 | BI33: 0 | BJ33: - | BK33: 34351.02 | BL33: 0 | BM33: - | BN33: 34351.02 | BP33: 0 | BQ33: 0 | BR33: - | BS33: 0 | BT33: 0 | BU33: - | BV33: 0 | BW33: 0 | BX33: - | BY33: 0 | CA33: 0 | CB33: 0 | CC33: - | CD33: -275157.24 | CE33: 0 | CF33: - | CG33: -275157.24 | CH33: 0 | CI33: - | CJ33: -275157.24
A34: MG INTERMEDIAÇÃO LIQ | B34: 2778303 | C34: 2834557.4 | D34: -0.019845912 | E34: 8054207 | F34: 8624017.8 | G34: -0.066072541 | H34: 10832510 | I34: 11458575 | J34: -0.054637259 | K34: -626065.14 | M34: 3061028.7 | N34: 2973465.4 | O34: 0.02944824 | P34: 10111463 | Q34: 9311839.1 | R34: 0.085871719 | S34: 13172492 | T34: 12285305 | U34: 0.072215301 | V34: 887186.96 | X34: 2242918.4 | Y34: 2392050.8 | Z34: -0.062345013 | AA34: 14600600 | AB34: 12271816 | AC34: 0.18976688 | AD34: 16843518 | AE34: 14663866 | AF34: 0.148641 | AG34: 2179651.7 | AI34: 2475736.5 | AJ34: 2400870 | AK34: 0.031183064 | AL34: 13593595 | AM34: 12355922 | AN34: 0.10016847 | AO34: 16069332 | AP34: 14756792 | AQ34: 0.088944823 | AR34: 1312540.2 | AT34: 2085685.4 | AU34: 2625765.9 | AV34: -0.20568494 | AW34: 17805359 | AX34: 10977706 | AY34: 0.6219563 | AZ34: 19891044 | BA34: 13603472 | BB34: 0.46220354 | BC34: 6287572.7 | BE34: 2184663.3 | BF34: 2039112.1 | BG34: 0.071379717 | BH34: 14974362 | BI34: 12260955 | BJ34: 0.22130478 | BK34: 17159026 | BL34: 14300067 | BM34: 0.19992628 | BN34: 2858959.1 | BP34: 1797801 | BQ34: 1934490.7 | BR34: -0.070659256 | BS34: 14464157 | BT34: 10601146 | BU34: 0.36439562 | BV34: 16261958 | BW34: 12535636 | BX34: 0.29725825 | BY34: 3726321.4 | CA34: 1728753.6 | CB34: 2422006.3 | CC34: -0.28623076 | CD34: 14494514 | CE34: 11930312 | CF34: 0.21493173 | CG34: 16223268 | CH34: 14352318 | CI34: 0.13035873 | CJ34: 1870949.9
A35: Despesas Administrativas Diretas | B35: -412401.31 | C35: -423570.09 | D35: -0.02636819 | E35: -1446214.8 | F35: -1512538.6 | G35: -0.043849325 | H35: -1858616.1 | I35: -1936108.7 | J35: -0.040024909 | K35: -77492.573 | M35: -472978.66 | N35: -475521.66 | O35: -0.0053478109 | P35: -2407184.8 | Q35: -2399769.7 | R35: 0.0030899086 | S35: -2880163.5 | T35: -2875291.4 | U35: 0.001694461 | V35: 4872.0692 | X35: -466515.01 | Y35: -486890.14 | Z35: -0.041847489 | AA35: -1829214.4 | AB35: -2394625.7 | AC35: -0.23611677 | AD35: -2295729.4 | AE35: -2881515.8 | AF35: -0.20329106 | AG35: -585786.41 | AI35: -447760.78 | AJ35: -486890.14 | AK35: -0.08036589 | AL35: -2334541.2 | AM35: -2394625.7 | AN35: -0.025091398 | AO35: -2782302 | AP35: -2881515.8 | AQ35: -0.034431137 | AR35: -99213.866 | AT35: -440290.51 | AU35: -486890.14 | AV35: -0.095708725 | AW35: -2295592.6 | AX35: -2394625.7 | AY35: -0.041356412 | AZ35: -2735883.1 | BA35: -2881515.8 | BB35: -0.05054033 | BC35: -145632.76 | BE35: -417622.83 | BF35: -497979.28 | BG35: -0.16136505 | BH35: -2177407.6 | BI35: -2479321.3 | BJ35: -0.12177273 | BK35: -2595030.4 | BL35: -2977300.6 | BM35: -0.12839489 | BN35: -382270.17 | BP35: -445130.89 | BQ35: -498703.08 | BR35: -0.10742303 | BS35: -2320829.4 | BT35: -2483961.2 | BU35: -0.065674053 | BV35: -2765960.3 | BW35: -2982664.3 | BX35: -0.072654504 | BY35: -216704 | CA35: -447905.42 | CB35: -498703.08 | CC35: -0.10185952 | CD35: -2335295.3 | CE35: -2483961.2 | CF35: -0.059850325 | CG35: -2783200.8 | CH35: -2982664.3 | CI35: -0.066874285 | CJ35: -199463.54
A36: Comissão (Apoio - Comercial - Mídia Paga) | B36: -37516.142 | C36: 0 | D36: - | E36: -133011.78 | F36: -180000 | G36: -0.26104568 | H36: -170527.92 | I36: -180000 | J36: -0.052622667 | K36: -9472.08 | M36: -223720.53 | N36: -42428.571 | O36: 4.2728745 | P36: -793190.98 | Q36: -150428.57 | R36: 4.2728745 | S36: -1016911.5 | T36: -192857.14 | U36: 4.2728745 | V36: 824054.37 | X36: -40765.595 | Y36: 0 | Z36: - | AA36: -144532.27 | AB36: -233766.23 | AC36: -0.38172309 | AD36: -185297.86 | AE36: -233766.23 | AF36: -0.20733693 | AG36: -48468.374 | AI36: -91815.924 | AJ36: 0 | AK36: - | AL36: -325529.18 | AM36: -202207.79 | AN36: 0.60987458 | AO36: -417345.11 | AP36: -202207.79 | AQ36: 1.0639418 | AR36: 215137.32 | AT36: -35594.348 | AU36: 0 | AV36: - | AW36: -126198.14 | AX36: -209220.78 | AY36: -0.39681831 | AZ36: -161792.49 | BA36: -209220.78 | BB36: -0.22669015 | BC36: -47428.289 | BE36: 16837.295 | BF36: -48857.143 | BG36: -1.344623 | BH36: 59695.865 | BI36: -173220.78 | BJ36: -1.344623 | BK36: 76533.16 | BL36: -222077.92 | BM36: -1.344623 | BN36: -145544.76 | BP36: -61056.041 | BQ36: -55542.857 | BR36: 0.099260001 | BS36: -216471.42 | BT36: -196924.68 | BU36: 0.099260001 | BV36: -277527.46 | BW36: -252467.53 | BX36: 0.099260001 | BY36: 25059.928 | CA36: -19132.828 | CB36: -54771.429 | CC36: -0.65067868 | CD36: -847168.85 | CE36: -194189.61 | CF36: 3.3625859 | CG36: -866301.68 | CH36: -248961.04 | CI36: 2.4796677 | CJ36: 617340.64
A37: MG CONTRIBUIÇÃO DIRETA | B37: 2328385.5 | C37: 2410987.3 | D37: -0.034260547 | E37: 6474980.4 | F37: 6931479.2 | G37: -0.065858777 | H37: 8803366 | I37: 9342466.5 | J37: -0.0577043 | K37: -539100.49 | M37: 2364329.5 | N37: 2455515.2 | O37: -0.037135034 | P37: 6911087 | Q37: 6761640.8 | R37: 0.022102056 | S37: 9275416.5 | T37: 9217156 | U37: 0.0063208786 | V37: 58260.524 | X37: 1735637.8 | Y37: 1905160.7 | Z37: -0.088980896 | AA37: 12626853 | AB37: 9643423.6 | AC37: 0.30937451 | AD37: 14362491 | AE37: 11548584 | AF37: 0.24365813 | AG37: 2813906.5 | AI37: 1936159.8 | AJ37: 1913979.8 | AK37: 0.011588376 | AL37: 10933525 | AM37: 9759088.1 | AN37: 0.12034289 | AO37: 12869685 | AP37: 11673068 | AQ37: 0.1025109 | AR37: 1196616.8 | AT37: 1609800.5 | AU37: 2138875.8 | AV37: -0.24736136 | AW37: 15383568 | AX37: 8373859.1 | AY37: 0.83709421 | AZ37: 16993369 | BA37: 10512735 | BB37: 0.61645555 | BC37: 6480633.7 | BE37: 1783877.8 | BF37: 1492275.6 | BG37: 0.19540769 | BH37: 12856651 | BI37: 9608412.6 | BJ37: 0.3380619 | BK37: 14640529 | BL37: 11100688 | BM37: 0.31888476 | BN37: 3539840.3 | BP37: 1291614.1 | BQ37: 1380244.8 | BR37: -0.064213729 | BS37: 11926856 | BT37: 7920259.8 | BU37: 0.50586675 | BV37: 13218470 | BW37: 9300504.6 | BX37: 0.42126375 | BY37: 3917965.4 | CA37: 1261715.4 | CB37: 1868531.8 | CC37: -0.32475575 | CD37: 11312050 | CE37: 9252161 | CF37: 0.22263872 | CG37: 12573766 | CH37: 11120693 | CI37: 0.13066387 | CJ37: 1453072.8
A38: Desp. Administrativas Indiretas | B38: -676373.11 | C38: -728263.17 | D38: -0.071251795 | E38: -2282965.8 | F38: -2438098.4 | G38: -0.063628527 | H38: -2959338.9 | I38: -3166361.6 | J38: -0.065381879 | K38: -207022.67 | M38: -633048.18 | N38: -476449.99 | O38: 0.32867707 | P38: -1750601.7 | Q38: -1689231.8 | R38: 0.036330046 | S38: -2383649.8 | T38: -2165681.8 | U38: 0.10064639 | V38: 217968.05 | X38: -533709.79 | Y38: -575798.96 | Z38: -0.073096977 | AA38: -1806616 | AB38: -2041469 | AC38: -0.11504117 | AD38: -2340325.8 | AE38: -2617268 | AF38: -0.10581345 | AG38: -276942.15 | AI38: -542073.63 | AJ38: -487798.96 | AK38: 0.11126443 | AL38: -1981635.4 | AM38: -1729469 | AN38: 0.14580567 | AO38: -2523709 | AP38: -2217268 | AQ38: 0.1382066 | AR38: 306441.06 | AT38: -533029.87 | AU38: -487798.96 | AV38: 0.09272451 | AW38: -1948574.5 | AX38: -1729469 | AY38: 0.12668947 | AZ38: -2481604.4 | BA38: -2217268 | BB38: 0.11921718 | BC38: 264336.44 | BE38: -505587.66 | BF38: -500863.85 | BG38: 0.0094313324 | BH38: -1854718.7 | BI38: -1775790 | BJ38: 0.044447079 | BK38: -2360306.3 | BL38: -2276653.9 | BM38: 0.036743615 | BN38: 83652.493 | BP38: -538889.8 | BQ38: -501808.3 | BR38: 0.073895733 | BS38: -1969996.4 | BT38: -1779138.5 | BU38: 0.10727544 | BV38: -2508886.2 | BW38: -2280946.8 | BX38: 0.099931908 | BY38: 227939.37 | CA38: -542248.74 | CB38: -501808.3 | CC38: 0.080589411 | CD38: -1982275.6 | CE38: -1779138.5 | CF38: 0.11417718 | CG38: -2524524.3 | CH38: -2280946.8 | CI38: 0.10678787 | CJ38: 243577.46
A39: Amortização | B39: -98141.795 | C39: -107178.79 | D39: -0.084316994 | E39: -349715.66 | F39: -379997.52 | G39: -0.079689622 | H39: -447857.46 | I39: -487176.31 | J39: -0.080707644 | K39: -39318.852 | M39: -95397.185 | N39: -97517.009 | O39: -0.021737984 | P39: -338226.38 | Q39: -345742.12 | R39: -0.021737984 | S39: -433623.57 | T39: -443259.13 | U39: -0.021737984 | V39: -9635.5597 | X39: -93401.924 | Y39: -88082.166 | Z39: 0.060395399 | AA39: -331152.28 | AB39: -312291.32 | AC39: 0.060395399 | AD39: -424554.2 | AE39: -400373.48 | AF39: 0.060395399 | AG39: 24180.716 | AI39: -68173.244 | AJ39: -79650.623 | AK39: -0.14409654 | AL39: -241705.14 | AM39: -282397.66 | AN39: -0.14409654 | AO39: -309878.38 | AP39: -362048.29 | AQ39: -0.14409654 | AR39: -52169.906 | AT39: -80103.962 | AU39: -75611.866 | AV39: 0.059409937 | AW39: -284004.96 | AX39: -268078.43 | AY39: 0.059409937 | AZ39: -364108.92 | BA39: -343690.3 | BB39: 0.059409937 | BC39: 20418.619 | BE39: -73558.008 | BF39: -73105.71 | BG39: 0.006186905 | BH39: -260796.57 | BI39: -259192.97 | BJ39: 0.006186905 | BK39: -334354.58 | BL39: -332298.68 | BM39: 0.006186905 | BN39: 2055.9004 | BP39: -71164.799 | BQ39: -68492.853 | BR39: 0.039010587 | BS39: -252311.56 | BT39: -242838.3 | BU39: 0.039010587 | BV39: -323476.36 | BW39: -311331.15 | BX39: 0.039010587 | BY39: 12145.211 | CA39: -70639.644 | CB39: -63800.946 | CC39: 0.10718802 | CD39: -250449.65 | CE39: -226203.36 | CF39: 0.10718802 | CG39: -321089.29 | CH39: -290004.3 | CI39: 0.10718802 | CJ39: 31084.988
A40: RESULTADO ANTES IMPOSTO | B40: 1553870.6 | C40: 1575545.3 | D40: -0.013756945 | E40: 3842298.9 | F40: 4113383.2 | G40: -0.065902995 | H40: 5396169.6 | I40: 5688928.6 | J40: -0.051461178 | K40: -292758.96 | M40: 1635884.2 | N40: 1881548.2 | O40: -0.13056482 | P40: 4822258.9 | Q40: 4726666.9 | R40: 0.020223983 | S40: 6458143.1 | T40: 6608215.1 | U40: -0.02270991 | V40: -150071.97 | X40: 1108526.1 | Y40: 1241279.6 | Z40: -0.10694891 | AA40: 10489085 | AB40: 7289663.3 | AC40: 0.43889838 | AD40: 11597611 | AE40: 8530942.9 | AF40: 0.35947585 | AG40: 3066667.9 | AI40: 1325912.9 | AJ40: 1346530.3 | AK40: -0.015311484 | AL40: 8710184.4 | AM40: 7747221.4 | AN40: 0.12429785 | AO40: 10036097 | AP40: 9093751.7 | AQ40: 0.10362561 | AR40: 942345.6 | AT40: 996666.71 | AU40: 1575464.9 | AV40: -0.36738249 | AW40: 13150989 | AX40: 6376311.7 | AY40: 1.0624758 | AZ40: 14147655 | BA40: 7951776.6 | BB40: 0.77918168 | BC40: 6195878.7 | BE40: 1204732.1 | BF40: 918306.07 | BG40: 0.31190692 | BH40: 10741136 | BI40: 7573429.6 | BJ40: 0.41826571 | BK40: 11945868 | BL40: 8491735.7 | BM40: 0.40676395 | BN40: 3454131.9 | BP40: 681559.52 | BQ40: 809943.62 | BR40: -0.15850993 | BS40: 9704547.9 | BT40: 5898283 | BU40: 0.64531745 | BV40: 10386107 | BW40: 6708226.6 | BX40: 0.54826425 | BY40: 3677880.8 | CA40: 648826.98 | CB40: 1302922.6 | CC40: -0.50202184 | CD40: 9079325 | CE40: 7246819.1 | CF40: 0.25287038 | CG40: 9728152 | CH40: 8549741.6 | CI40: 0.13782994 | CJ40: 1178410.3
A41: Impostos (IR/CSLL) | B41: -115374.99 | C41: -325141 | D41: -0.64515398 | E41: -1463640.8 | F41: -1157412.4 | G41: 0.26458017 | H41: -1579015.8 | I41: -1482553.4 | J41: 0.065065019 | K41: -96462.367 | M41: -544207.13 | N41: -489202.52 | O41: 0.11243729 | P41: -1604213.6 | Q41: -1228933.4 | R41: 0.30537069 | S41: -2148420.8 | T41: -1718135.9 | U41: 0.25043703 | V41: -430284.85 | X41: -375153.56 | Y41: -487969.93 | Z41: -0.23119534 | AA41: -3549774.4 | AB41: -1730075.2 | AC41: 1.0518035 | AD41: -3924927.9 | AE41: -2218045.1 | AF41: 0.76954374 | AG41: -1706882.8 | AI41: -117342.31 | AJ41: -520162.59 | AK41: -0.77441225 | AL41: -770844.86 | AM41: -1844212.8 | AN41: -0.58201958 | AO41: -888187.17 | AP41: -2364375.4 | AQ41: -0.62434597 | AR41: -1476188.3 | AT41: -340871.81 | AU41: -454841.62 | AV41: -0.25057033 | AW41: -4497793.7 | AX41: -1612620.3 | AY41: 1.7891213 | AZ41: -4838665.5 | BA41: -2067461.9 | BB41: 1.3403892 | BC41: 2771203.6 | BE41: -327605.81 | BF41: -485727.28 | BG41: -0.3255355 | BH41: -2920791.9 | BI41: -1722124 | BJ41: 0.69604041 | BK41: -3248397.7 | BL41: -2207851.3 | BM41: 0.47129371 | BN41: 1040546.4 | BP41: -215563.35 | BQ41: -383710.56 | BR41: -0.43821368 | BS41: -2667581.2 | BT41: -1360428.4 | BU41: 0.96083917 | BV41: -2883144.6 | BW41: -1744138.9 | BX41: 0.65304754 | BY41: 1139005.6 | CA41: -175409.21 | CB41: -489045.22 | CC41: -0.64132313 | CD41: -2454579.2 | CE41: -1733887.6 | CF41: 0.41565072 | CG41: -2629988.4 | CH41: -2222932.8 | CI41: 0.18311647 | CJ41: 407055.62
A42: RESULTADO CONTÁBIL | B42: 1438495.7 | C42: 1250404.3 | D42: 0.1504244 | E42: 2378658.1 | F42: 2955970.8 | G42: -0.19530391 | H42: 3817153.8 | I42: 4206375.1 | J42: -0.092531293 | K42: -389221.33 | M42: 1091677 | N42: 1392345.6 | O42: -0.21594394 | P42: 3218045.3 | Q42: 3497733.5 | R42: -0.079962699 | S42: 4309722.3 | T42: 4890079.2 | U42: -0.11868045 | V42: -580356.82 | X42: 733372.52 | Y42: 753309.65 | Z42: -0.026466044 | AA42: 6939310.4 | AB42: 5559588.1 | AC42: 0.24816988 | AD42: 7672682.9 | AE42: 6312897.7 | AF42: 0.21539794 | AG42: 1359785.2 | AI42: 1208570.6 | AJ42: 826367.67 | AK42: 0.46250951 | AL42: 7939339.5 | AM42: 5903008.6 | AN42: 0.34496493 | AO42: 9147910.1 | AP42: 6729376.2 | AQ42: 0.35939941 | AR42: 2418533.9 | AT42: 655794.9 | AU42: 1120623.3 | AV42: -0.41479453 | AW42: 8653194.9 | AX42: 4763691.4 | AY42: 0.8164894 | AZ42: 9308989.8 | BA42: 5884314.7 | BB42: 0.58200067 | BC42: 3424675.1 | BE42: 877126.28 | BF42: 432578.79 | BG42: 1.0276682 | BH42: 7820343.6 | BI42: 5851305.6 | BJ42: 0.33651259 | BK42: 8697469.9 | BL42: 6283884.4 | BM42: 0.38409133 | BN42: 2413585.5 | BP42: 465996.17 | BQ42: 426233.06 | BR42: 0.093289602 | BS42: 7036966.7 | BT42: 4537854.6 | BU42: 0.55072547 | BV42: 7502962.9 | BW42: 4964087.7 | BX42: 0.5114485 | BY42: 2538875.2 | CA42: 473417.77 | CB42: 813877.33 | CC42: -0.41831804 | CD42: 6624745.8 | CE42: 5512931.5 | CF42: 0.20167388 | CG42: 7098163.5 | CH42: 6326808.8 | CI42: 0.12191845 | CJ42: 771354.73
A43: RESULTADO ANTES IMPOSTO RECORRENTE | B43: 1652012.4 | C43: 1682724.1 | D43: -0.01825117 | E43: 4104954.3 | F43: 4406320.4 | G43: -0.068394057 | H43: 5756966.7 | I43: 6089044.5 | J43: -0.054536933 | K43: -332077.82 | M43: #REF! | N43: #REF! | O43: - | P43: #REF! | Q43: #REF! | R43: - | S43: #REF! | T43: #REF! | U43: - | V43: #REF! | X43: #REF! | Y43: #REF! | Z43: - | AA43: #REF! | AB43: #REF! | AC43: - | AD43: #REF! | AE43: #REF! | AF43: - | AG43: #REF! | AI43: #REF! | AJ43: #REF! | AK43: - | AL43: #REF! | AM43: #REF! | AN43: - | AO43: #REF! | AP43: #REF! | AQ43: - | AR43: #REF! | AT43: #REF! | AU43: #REF! | AV43: - | AW43: #REF! | AX43: #REF! | AY43: - | AZ43: #REF! | BA43: #REF! | BB43: - | BC43: #REF! | BE43: #REF! | BF43: #REF! | BG43: - | BH43: #REF! | BI43: #REF! | BJ43: - | BK43: #REF! | BL43: #REF! | BM43: - | BN43: #REF! | BP43: #REF! | BQ43: #REF! | BR43: - | BS43: #REF! | BT43: #REF! | BU43: - | BV43: #REF! | BW43: #REF! | BX43: - | BY43: #REF! | CA43: #REF! | CB43: #REF! | CC43: - | CD43: #REF! | CE43: #REF! | CF43: - | CG43: #REF! | CH43: #REF! | CI43: - | CJ43: #REF!
A44: Margem Bruta | B44: 0.10253457 | C44: 0.10399955 | D44: -0.0014649789 | E44: 0.075901792 | F44: 0.082559764 | G44: -0.0066579723 | H44: 0.081580979 | I44: 0.087227538 | J44: -0.0056465589 | M44: 0.10131605 | N44: 0.10294537 | O44: -0.16293204 | P44: 0.092978013 | Q44: 0.082323328 | R44: 1.0654684 | S44: 0.094737728 | T44: 0.086782321 | U44: 0.79554067 | X44: 0.083519809 | Y44: 0.086426297 | Z44: -0.29064877 | AA44: 0.11378117 | AB44: 0.10533598 | AC44: 0.84451929 | AD44: 0.10756661 | AE44: 0.10135271 | AF44: 0.62139021 | AI44: 0.086786826 | AJ44: 0.086301232 | AK44: 0.048559393 | AL44: 0.11618429 | AM44: 0.1017956 | AN44: 1.4388696 | AO44: 0.11030538 | AP44: 0.098593144 | AQ44: 1.1712234 | AT44: 0.082226951 | AU44: 0.092790411 | AV44: -1.056346 | AW44: 0.14916905 | AX44: 0.089326715 | AY44: 5.9842336 | AZ44: 0.13597599 | BA44: 0.09003105 | BB44: 4.5944936 | BE44: 0.077596036 | BF44: 0.075318217 | BG44: 0.22778188 | BH44: 0.11453586 | BI44: 0.10021265 | BJ44: 1.4323213 | BK44: 0.10742078 | BL44: 0.095236516 | BM44: 1.2184268 | BP44: 0.070682905 | BQ44: 0.074162354 | BR44: -0.34794494 | BS44: 0.10762179 | BT44: 0.087425968 | BU44: 2.0195818 | BV44: 0.10068793 | BW44: 0.084826251 | BX44: 1.5861676 | CA44: 0.069556815 | CB44: 0.087893446 | CC44: -1.8336631 | CD44: 0.094525582 | CE44: 0.093879319 | CF44: 0.064626263 | CG44: 0.089936279 | CH44: 0.092729248 | CI44: -0.27929691
A45: Margem Liquida | B45: 0.081292582 | C45: 0.082824049 | D45: -0.0015314672 | E45: 0.063873667 | F45: 0.070130276 | G45: -0.0062566093 | H45: 0.067588085 | I45: 0.072893907 | J45: -0.0053058223 | M45: 0.089506135 | N45: 0.086748163 | O45: 0.27579716 | P45: 0.079090894 | Q45: 0.074945626 | R45: 0.41452681 | S45: 0.081288995 | T45: 0.077497624 | U45: 0.37913709 | X45: 0.065655931 | Y45: 0.069611161 | Z45: -0.39552306 | AA45: 0.11045482 | AB45: 0.095302041 | AC45: 1.515278 | AD45: 0.10125479 | AE45: 0.089890326 | AF45: 1.136446 | AI45: 0.072618765 | AJ45: 0.069688281 | AK45: 0.2930484 | AL45: 0.099670183 | AM45: 0.093439236 | AN45: 0.62309471 | AO45: 0.094260433 | AP45: 0.088530272 | AQ45: 0.57301607 | AT45: 0.061427675 | AU45: 0.076016418 | AV45: -1.4588742 | AW45: 0.12871851 | AX45: 0.081121151 | AY45: 4.7597362 | AZ45: 0.11545672 | BA45: 0.080083114 | BB45: 3.5373605 | BE45: 0.064209056 | BF45: 0.058885448 | BG45: 0.53236083 | BH45: 0.1049936 | BI45: 0.088456695 | BJ45: 1.6536908 | BK45: 0.097137985 | BL45: 0.082545718 | BM45: 1.4592267 | BP45: 0.052597422 | BQ45: 0.055723798 | BR45: -0.3126376 | BS45: 0.097790583 | BT45: 0.074445272 | BU45: 2.3345311 | BV45: 0.089307299 | BW45: 0.070775794 | BX45: 1.8531505 | CA45: 0.050633624 | CB45: 0.069569568 | CC45: -1.8935944 | CD45: 0.09560124 | CE45: 0.081498946 | CF45: 1.4102294 | CG45: 0.087336114 | CH45: 0.079206944 | CI45: 0.81291701
A46: Rácio de Eficiência | B46: -0.31069832 | C46: -0.32361554 | D46: 0.012917217 | E46: -0.38963723 | F46: -0.38912989 | G46: -0.00050734222 | H46: -0.36848081 | I46: -0.37212383 | J46: 0.0036430224 | M46: -0.31920729 | N46: -0.269783 | O46: -4.9424289 | P46: -0.34977955 | Q46: -0.39976538 | R46: 4.9985824 | S46: -0.34287936 | T46: -0.36642541 | U46: 2.3546056 | X46: -0.35056505 | Y46: -0.35782344 | Z46: 0.72583961 | AA46: -0.24173927 | AB46: -0.32705249 | AC46: 8.5313219 | AD46: -0.25909193 | AE46: -0.33257972 | AF46: 7.3487789 | AI46: 0.33454395 | AJ46: 0.3278236 | AK46: -0.67203506 | AL46: 0.2723847 | AM46: 0.30637532 | AN46: 3.3990621 | AO46: 0.28216495 | AP46: 0.31025568 | AQ46: 2.8090724 | AT46: 0.3486237 | AU46: 0.30409859 | AV46: -4.4525114 | AW46: 0.20568567 | AX46: 0.34116918 | AY46: 13.548351 | AZ46: 0.22272082 | BA46: 0.33339991 | BB46: 11.067909 | BE46: 0.34968175 | BF46: 0.38296946 | BG46: 3.328771 | BH46: 0.24683523 | BI46: 0.30633373 | BJ46: 5.94985 | BK46: 0.26114476 | BL46: 0.31844856 | BM46: 5.7303798 | BP46: 0.40729836 | BQ46: 0.38860876 | BR46: -1.8689606 | BS46: 0.26955327 | BT46: 0.34242807 | BU46: 7.2874801 | BV46: 0.28770443 | BW46: 0.35034174 | BX46: 6.2637309 | CA46: 0.41693566 | CB46: 0.32697126 | CC46: -8.9964402 | CD46: 0.3012659 | CE46: 0.31020998 | CF46: 0.8944079 | CG46: 0.31770864 | CH46: 0.3132624 | CI46: -0.44462434
A47: Rácio de Eficiência Recorrente | B47: -0.33870457 | C47: -0.35372816 | D47: 0.015023589 | E47: -0.42617669 | F47: -0.42655889 | G47: 0.00038219873 | H47: -0.40273328 | I47: -0.40765366 | J47: 0.0049203813 | M47: -0.3467396 | N47: -0.29741873 | O47: -4.9320872 | P47: -0.37823332 | Q47: -0.4335672 | R47: 5.5333889 | S47: -0.37112515 | T47: -0.39864566 | U47: 2.7520513 | X47: -0.38330114 | Y47: -0.38748204 | Z47: 0.41808991 | AA47: -0.26375693 | AB47: -0.35007626 | AC47: 8.6319327 | AD47: -0.28281869 | AE47: -0.35679527 | AF47: 7.3976584 | AI47: -0.35758513 | AJ47: -0.35461302 | AK47: -0.29721055 | AL47: -0.2876382 | AM47: -0.32735439 | AN47: 3.9716196 | AO47: -0.29864378 | AP47: -0.33228594 | AQ47: 3.3642161 | AT47: -0.37731532 | AU47: -0.32768915 | AV47: -4.9626176 | AW47: -0.21944944 | AX47: -0.3633462 | AY47: 14.389675 | AZ47: -0.23826368 | BA47: -0.35587318 | BB47: 11.76095 | BE47: -0.3775431 | BF47: -0.41099914 | BG47: 3.3456039 | BH47: -0.26280045 | BI47: -0.32499353 | BJ47: 6.2193086 | BK47: -0.27876515 | BL47: -0.33858959 | BM47: 5.9824439 | BP47: -0.43675436 | BQ47: -0.41521208 | BR47: -2.1542281 | BS47: -0.2854037 | BT47: -0.36193375 | BU47: 7.6530056 | BV47: -0.30534771 | BW47: -0.3710637 | BX47: 6.5715983 | CA47: -0.44668071 | CB47: -0.34782167 | CC47: -9.885904 | CD47: -0.31874145 | CE47: -0.32666996 | CF47: 0.79285065 | CG47: -0.33692833 | CH47: -0.33052192 | CI47: -0.64064078
A48: RPL - RES. CONTÁBIL | B48: 0.40727673 | C48: 0.3405402 | D48: 0.066736531 | E48: 0.18253276 | F48: 0.22404887 | G48: -0.041516106 | H48: 0.23045728 | I48: 0.24941084 | J48: -0.018953557 | M48: 0.30489271 | N48: 0.37919946 | O48: -7.4306747 | P48: 0.24042085 | Q48: 0.26279724 | R48: -2.2376391 | S48: 0.25402742 | T48: 0.28796626 | U48: -3.3938842 | X48: 0.20771829 | Y48: 0.19499663 | Z48: 1.2721663 | AA48: 0.50794877 | AB48: 0.3840441 | AC48: 12.390467 | AD48: 0.44629253 | AE48: 0.34422175 | AF48: 10.207078 | AI48: 0.34648688 | AJ48: 0.20873932 | AK48: 13.774755 | AL48: 0.56896509 | AM48: 0.38847886 | AN48: 18.048623 | AO48: 0.52447383 | AP48: 0.35132941 | AQ48: 17.314442 | AT48: 0.19259063 | AU48: 0.28002928 | AV48: -8.7438647 | AW48: 0.62376157 | AX48: 0.3038495 | AY48: 31.991206 | AZ48: 0.53878566 | BA48: 0.29900571 | BB48: 23.977995 | BE48: 0.25091663 | BF48: 0.10720428 | BG48: 14.371235 | BH48: 0.53369839 | BI48: 0.36227572 | BJ48: 17.142267 | BK48: 0.47923106 | BL48: 0.31128966 | BM48: 16.79414 | BP48: 0.13445967 | BQ48: 0.10528142 | BR48: 2.9178249 | BS48: 0.46921974 | BT48: 0.27325332 | BU48: 19.596642 | BV48: 0.40638137 | BW48: 0.2403302 | BX48: 16.605116 | CA48: 0.13760497 | CB48: 0.20051643 | CC48: -6.2911467 | CD48: 0.43362341 | CE48: 0.32302027 | CF48: 11.060314 | CG48: 0.37921471 | CH48: 0.2994835 | CI48: 7.9731207
A49: Carteira de Crédito Bruta Média | B49: 4.1011904e+08 | C49: 4.1068613e+08 | D49: -0.0013808349 | E49: 1.5131507e+09 | F49: 1.4756567e+09 | G49: 0.025408339 | H49: 1.9232698e+09 | I49: 1.8863429e+09 | J49: 0.01957592 | K49: -36926897 | M49: 4.1038913e+08 | N49: 4.1132381e+08 | O49: -0.0022723683 | P49: 1.5341533e+09 | Q49: 1.4909752e+09 | R49: 0.028959613 | S49: 1.9445424e+09 | T49: 1.902299e+09 | U49: 0.022206491 | V49: -42243386 | X49: 4.0994044e+08 | Y49: 4.1235643e+08 | Z49: -0.0058590008 | AA49: 1.586234e+09 | AB49: 1.5452113e+09 | AC49: 0.026548329 | AD49: 1.9961745e+09 | AE49: 1.9575677e+09 | AF49: 0.019721811 | AG49: -38606781 | AI49: 4.091069e+08 | AJ49: 4.1341872e+08 | AK49: -0.010429672 | AL49: 1.6366293e+09 | AM49: 1.586818e+09 | AN49: 0.031390711 | AO49: 2.0457362e+09 | AP49: 2.0002367e+09 | AQ49: 0.022747069 | AR49: 45499523 | AT49: 4.0744216e+08 | AU49: 4.1450508e+08 | AV49: -0.017039391 | AW49: 1.6599345e+09 | AX49: 1.6238979e+09 | AY49: 0.022191445 | AZ49: 2.0673767e+09 | BA49: 2.038403e+09 | BB49: 0.014213935 | BC49: 28973726 | BE49: 4.0829069e+08 | BF49: 4.1554146e+08 | BG49: -0.017448966 | BH49: 1.71146e+09 | BI49: 1.6633162e+09 | BJ49: 0.028944446 | BK49: 2.1197507e+09 | BL49: 2.0788577e+09 | BM49: 0.019670898 | BN49: 40892997 | BP49: 4.1016483e+08 | BQ49: 4.1658842e+08 | BR49: -0.015419503 | BS49: 1.7749141e+09 | BT49: 1.7088224e+09 | BU49: 0.038676729 | BV49: 2.1850789e+09 | BW49: 2.1254108e+09 | BX49: 0.028073666 | BY49: 59668074 | CA49: 4.0970884e+08 | CB49: 4.1776996e+08 | CC49: -0.019295594 | CD49: 1.8193715e+09 | CE49: 1.756633e+09 | CF49: 0.03571518 | CG49: 2.2290803e+09 | CH49: 2.174403e+09 | CI49: 0.025145912 | CJ49: 54677345
A50: Carteira de Crédito SD Cliente Média | B50: 4.0780772e+08 | C50: 4.0932064e+08 | D50: -0.003696176 | E50: 1.485863e+09 | F50: 1.4518969e+09 | G50: 0.023394275 | H50: 1.8936707e+09 | I50: 1.8612175e+09 | J50: 0.017436519 | K50: -32453154 | M50: 4.0796738e+08 | N50: 4.0987567e+08 | O50: -0.0046557779 | P50: 1.5188489e+09 | Q50: 1.466079e+09 | R50: 0.035993862 | S50: 1.9268162e+09 | T50: 1.8759547e+09 | U50: 0.027112358 | V50: -50861556 | X50: 4.0732782e+08 | Y50: 4.1067494e+08 | Z50: -0.0081502824 | AA50: 1.5600256e+09 | AB50: 1.5164872e+09 | AC50: 0.028709993 | AD50: 1.9673534e+09 | AE50: 1.9271622e+09 | AF50: 0.020855132 | AG50: -40191221 | AI50: 4.0635788e+08 | AJ50: 4.1157754e+08 | AK50: -0.012682081 | AL50: 1.6001062e+09 | AM50: 1.5554035e+09 | AN50: 0.028740273 | AO50: 2.0064641e+09 | AP50: 1.966981e+09 | AQ50: 0.020072924 | AT50: 4.0751697e+08 | AU50: 4.125003e+08 | AV50: -0.012080781 | AW50: 1.6611908e+09 | AX50: 1.5899595e+09 | AY50: 0.044800698 | AZ50: 2.0687078e+09 | BA50: 2.0024598e+09 | BB50: 0.033083296 | BE50: 4.082271e+08 | BF50: 4.1337366e+08 | BG50: -0.01245014 | BH50: 1.7106038e+09 | BI50: 1.6267397e+09 | BJ50: 0.051553452 | BK50: 2.1188309e+09 | BL50: 2.0401134e+09 | BM50: 0.03858486 | BP50: 4.0701131e+08 | BQ50: 4.1425408e+08 | BR50: -0.0174839 | BS50: 1.7321769e+09 | BT50: 1.6693076e+09 | BU50: 0.03766187 | BV50: 2.1391882e+09 | BW50: 2.0835617e+09 | BX50: 0.026697779 | CA50: 4.0642124e+08 | CB50: 4.1526621e+08 | CC50: -0.021299496 | CD50: 1.7738311e+09 | CE50: 1.7140542e+09 | CF50: 0.034874597 | CG50: 2.1802524e+09 | CH50: 2.1293204e+09 | CI50: 0.023919363
R51: 52769846 | AC51: 43538338 | AN51: 44702721 | AY51: 71231297 | BJ51: 83864050 | BU51: 62869248 | CF51: 59776949
A52: Taxa Média Carteira Bruta Média | B52: 0.019001864 | C52: 0.01872293 | D52: 0.014897973 | E52: 0.01390232 | F52: 0.014373662 | G52: -0.032792041 | H52: 0.014989749 | I52: 0.015320565 | J52: -0.021592911 | K52: 0 | M52: 0.017277652 | N52: 0.016967288 | P52: 0.013778186 | Q52: 0.013658581 | S52: 0.014516736 | T52: 0.014374004 | X52: 0.019194187 | Y52: 0.018786966 | AA52: 0.018695955 | AB52: 0.017007776 | AD52: 0.018798274 | AE52: 0.017382557 | AI52: 0.018345501 | AJ52: 0.018235859 | AL52: 0.018505301 | AM52: 0.01555184 | AO52: 0.018473344 | AP52: 0.016106586 | AT52: 0.018596775 | AU52: 0.018878644 | AW52: 0.020021151 | AX52: 0.014523371 | AZ52: 0.019740432 | BA52: 0.015409007 | BE52: 0.019006875 | BF52: 0.018324252 | BH52: 0.017045282 | BI52: 0.015552748 | BK52: 0.017423109 | BL52: 0.016106742 | BP52: 0.019059111 | BQ52: 0.018969887 | BS52: 0.015591658 | BT52: 0.015043158 | BV52: 0.016242539 | BW52: 0.015812812 | CA52: 0.018696147 | CB52: 0.019017201 | CD52: 0.013191795 | CE52: 0.015047607 | CG52: 0.014203504 | CH52: 0.015810289
A53: Taxa Média Carteira SD Cliente Média | B53: 0.019109561 | C53: 0.01878539 | D53: 0.017256526 | E53: 0.014157635 | F53: 0.014608882 | G53: -0.030888553 | H53: 0.015224047 | I53: 0.015527383 | J53: -0.019535578 | K53: 0 | M53: 0.017380215 | N53: 0.017027236 | P53: 0.013917019 | Q53: 0.013890523 | S53: 0.014650286 | T53: 0.014575861 | X53: 0.019317299 | Y53: 0.018863888 | AA53: 0.019010048 | AB53: 0.017329923 | AD53: 0.019073662 | AE53: 0.017656808 | AI53: 0.018469609 | AJ53: 0.018317436 | AL53: 0.018927692 | AM53: 0.015865941 | AO53: 0.018834919 | AP53: 0.0163789 | AT53: 0.018593362 | AU53: 0.018970396 | AW53: 0.020006009 | AX53: 0.014833378 | AZ53: 0.01972773 | BA53: 0.015685591 | BE53: 0.019009836 | BF53: 0.018420347 | BH53: 0.017053813 | BI53: 0.015902444 | BK53: 0.017430673 | BL53: 0.016412629 | BP53: 0.019206781 | BQ53: 0.019076783 | BS53: 0.015976343 | BT53: 0.01539925 | BV53: 0.01659098 | BW53: 0.016130418 | CA53: 0.018847383 | CB53: 0.019131861 | CD53: 0.013530474 | CE53: 0.015421405 | CG53: 0.0145216 | CH53: 0.016145029
A55: Rateio Carteira | B55: 0.21324052 | C55: 0.21771553 | D55: -0.020554384 | E55: 0.78675948 | F55: 0.78228447 | G55: 0.0057204365 | H55: 1 | I55: 1 | J55: 0 | M55: 0.21104663 | N55: 0.21622458 | O55: -0.023947079 | P55: 0.78895337 | Q55: 0.78377542 | R55: 0.0066064167 | S55: 1 | T55: 1 | U55: 0 | X55: 0.20536303 | Y55: 0.21064734 | Z55: -0.025086069 | AA55: 0.79463697 | AB55: 0.78935266 | AC55: 0.0066944905 | AD55: 1 | AE55: 1 | AF55: 0 | AI55: 0.19998028 | AJ55: 0.2066849 | AK55: -0.032438852 | AL55: 0.80001972 | AM55: 0.7933151 | AN55: 0.0084513971 | AO55: 1 | AP55: 1 | AQ55: -1.110223e-16 | AT55: 0.19708172 | AU55: 0.20334796 | AV55: -0.030815319 | AW55: 0.80291828 | AX55: 0.79665204 | AY55: 0.0078657076 | AZ55: 1 | BA55: 1 | BB55: 0 | BE55: 0.1926126 | BF55: 0.19988932 | BG55: -0.036403769 | BH55: 0.8073874 | BI55: 0.80011068 | BJ55: 0.0090946479 | BK55: 1 | BL55: 1 | BM55: 0 | BP55: 0.18771168 | BQ55: 0.19600372 | BR55: -0.042305499 | BS55: 0.81228832 | BT55: 0.80399628 | BU55: 0.010313524 | BV55: 1 | BW55: 1 | BX55: -1.110223e-16 | CA55: 0.18380174 | CB55: 0.19213088 | CC55: -0.043351395 | CD55: 0.81619826 | CE55: 0.80786912 | CF55: 0.010310014 | CG55: 1 | CH55: 1 | CI55: 0
A56: Alocação de Capital | B56: 42383830 | C56: 44061911 | D56: -0.038084612 | E56: 1.5637685e+08 | F56: 1.5832104e+08 | G56: -0.012280061 | H56: 1.9876068e+08 | I56: 2.0238295e+08 | J56: -0.017898113 | M56: 42966341 | N56: 44061634 | O56: -0.024858185 | P56: 1.6062061e+08 | Q56: 1.5971554e+08 | R56: 0.0056667895 | S56: 2.0358695e+08 | T56: 2.0377717e+08 | U56: -0.00093346036 | X56: 42367335 | Y56: 46358319 | Z56: -0.086089926 | AA56: 1.6393725e+08 | AB56: 1.7371718e+08 | AC56: -0.05629799 | AD56: 2.0630459e+08 | AE56: 2.200755e+08 | AF56: -0.062573582 | AI56: 41856844 | AJ56: 47506200 | AK56: -0.1189183 | AL56: 1.6744801e+08 | AM56: 1.8234223e+08 | AN56: -0.081682768 | AO56: 2.0930486e+08 | AP56: 2.2984843e+08 | AQ56: -0.089378789 | AT56: 40861483 | AU56: 48021693 | AV56: -0.14910365 | AW56: 1.664712e+08 | AX56: 1.8813358e+08 | AY56: -0.11514361 | AZ56: 2.0733269e+08 | BA56: 2.3615528e+08 | BB56: -0.12204932 | BE56: 41948257 | BF56: 48421065 | BG56: -0.13367753 | BH56: 1.7583738e+08 | BI56: 1.9381831e+08 | BJ56: -0.092772122 | BK56: 2.1778563e+08 | BL56: 2.4223938e+08 | BM56: -0.10094868 | BP56: 41588337 | BQ56: 48582140 | BR56: -0.14395831 | BS56: 1.79966e+08 | BT56: 1.9928122e+08 | BU56: -0.096924442 | BV56: 2.2155434e+08 | BW56: 2.4786336e+08 | BX56: -0.10614326 | CA56: 41284943 | CB56: 48706871 | CC56: -0.15237948 | CD56: 1.8333177e+08 | CE56: 2.0480194e+08 | CF56: -0.1048338 | CG56: 2.2461672e+08 | CH56: 2.5350881e+08 | CI56: -0.11396879
A58: PL Médio (Banco + Hipo) | H58: 1.9876068e+08 | I58: 2.0238295e+08 | J58: -0.017898113 | S58: 2.0358695e+08 | T58: 2.0377717e+08 | U58: -0.00093346036 | AD58: 2.0630459e+08 | AE58: 2.200755e+08 | AF58: -0.062573582 | AO58: 2.0930486e+08 | AP58: 2.2984843e+08 | AQ58: -0.089378789 | AZ58: 2.0733269e+08 | BA58: 2.3615528e+08 | BB58: -0.12204932 | BK58: 2.1778563e+08 | BL58: 2.4223938e+08 | BM58: -0.10094868 | BV58: 2.2155434e+08 | BW58: 2.4786336e+08 | BX58: -0.10614326 | CG58: 2.2461672e+08 | CH58: 2.5350881e+08 | CI58: -0.11396879
A59: PL Médio (Prudencial + BRCards) | H59: 2.1554038e+08 | S59: 2.0979049e+08 | AD59: 2.144601e+08 | AO59: 2.1963403e+08 | AZ59: 2.1965837e+08 | BK59: 2.3254457e+08 | BV59: 2.387832e+08 | CG59: 2.4429311e+08
A61: Despesas Adm. Diretas + Indiretas | B61: -1088774.4 | C61: -1151833.3 | D61: -0.054746496 | E61: -3729180.6 | F61: -3950637 | G61: -0.056055874 | H61: -4817955 | I61: -5102470.3 | J61: -0.055760294 | M61: -1106026.8 | N61: -951971.65 | O61: 0.16182749 | P61: -4157786.5 | Q61: -4089001.5 | R61: 0.01682194 | S61: -5263813.3 | T61: -5040973.2 | U61: 0.044205774 | X61: -1000224.8 | Y61: -1062689.1 | Z61: -0.058779461 | AA61: -3635830.5 | AB61: -4436094.7 | AC61: -0.18039837 | AD61: -4636055.3 | AE61: -5498783.8 | AF61: -0.15689443 | AI61: -989834.41 | AJ61: -974689.09 | AK61: 0.015538611 | AL61: -4316176.6 | AM61: -4124094.7 | AN61: 0.046575527 | AO61: -5306011 | AP61: -5098783.8 | AQ61: 0.040642476 | AT61: -973320.38 | AU61: -974689.09 | AV61: -0.0014042584 | AW61: -4244167.1 | AX61: -4124094.7 | AY61: 0.029114848 | AZ61: -5217487.5 | BA61: -5098783.8 | BB61: 0.023280782 | BE61: -923210.49 | BF61: -998843.13 | BG61: -0.075720235 | BH61: -4032126.2 | BI61: -4255111.3 | BJ61: -0.052404044 | BK61: -4955336.7 | BL61: -5253954.4 | BM61: -0.056836746 | BP61: -984020.68 | BQ61: -1000511.4 | BR61: -0.016482273 | BS61: -4290825.8 | BT61: -4263099.8 | BU61: 0.0065037359 | BV61: -5274846.5 | BW61: -5263611.1 | BX61: 0.0021345372 | CA61: -990154.16 | CB61: -1000511.4 | CC61: -0.010351928 | CD61: -4317570.9 | CE61: -4263099.8 | CF61: 0.012777354 | CG61: -5307725.1 | CH61: -5263611.1 | CI61: 0.0083809218
A63: Alíquota de IR/CSLL | B63: -0.074250061 | C63: -0.20636728 | E63: -0.3809284 | F63: -0.28137724 | H63: -0.2926179 | I63: -0.26060328 | M63: -0.3326685 | N63: -0.26 | P63: -0.3326685 | Q63: -0.26 | S63: -0.3326685 | T63: -0.26 | X63: -0.33842556 | Y63: -0.39311847 | AA63: -0.33842556 | AB63: -0.23733266 | AD63: -0.33842556 | AE63: -0.26 | AI63: -0.088499259 | AJ63: -0.38629848 | AL63: -0.088499259 | AM63: -0.23804829 | AO63: -0.088499259 | AP63: -0.26 | AT63: -0.34201183 | AU63: -0.2887031 | AW63: -0.34201183 | AX63: -0.25290801 | AZ63: -0.34201183 | BA63: -0.26 | BE63: -0.2719325 | BF63: -0.52893833 | BH63: -0.2719258 | BI63: -0.22739024 | BK63: -0.27192648 | BL63: -0.26 | BP63: -0.31627956 | BQ63: -0.47374972 | BS63: -0.27487949 | BT63: -0.2306482 | BV63: -0.27759626 | BW63: -0.26 | CA63: -0.27034821 | CB63: -0.37534481 | CD63: -0.27034821 | CE63: -0.23926189 | CG63: -0.27034821 | CH63: -0.26

Sheet P&L Acumulado
B1: Data Base -> | F1: De: | G1: 46053 | H1: Até: | I1: 46265 | K1: Proporção anual para Indicadores -> | N1: 1.5
C3: BANCO DIGITAL | F3: CONSIGNADO | I3: IMOBILIARIO | L3: TOTAL
C4: Realizado | D4: Orçado | E4: ∆ (%) | F4: Realizado | G4: Orçado | H4: ∆ (%) | I4: Realizado | J4: Orçado | K4: ∆ (%) | L4: Realizado | M4: Orçado | N4: ∆ (%) | O4: ∆ (R$)
B5: RECEITAS | C5: 0 | D5: 0 | E5: - | F5: 61130865 | G5: 61341232 | H5: -0.0034294538 | I5: 2.4902878e+08 | J5: 2.1980229e+08 | K5: 0.13296715 | L5: 3.1015965e+08 | M5: 2.8114353e+08 | N5: 0.10320749 | O5: 29016118
B6: Operações de Crédito | C6: 0 | D6: 0 | E6: - | F6: 61072126 | G6: 61241499 | H6: -0.0027656614 | I6: 2.1619738e+08 | J6: 1.9412656e+08 | K6: 0.11369292 | L6: 2.772695e+08 | M6: 2.5536806e+08 | N6: 0.085764223 | O6: 21901443
B7: Receita Juros | C7: 0 | D7: 0 | E7: - | F7: 46604603 | G7: 48037071 | H7: -0.029820044 | I7: 1.5974912e+08 | J7: 1.5544955e+08 | K7: 0.027658908 | L7: 2.0635372e+08 | M7: 2.0348662e+08 | N7: 0.014089857 | O7: 2867097.3
B8: Receita CM - Crédito Imobiliário | C8: 0 | D8: 0 | E8: - | F8: 0 | G8: 0 | H8: - | I8: 52508799 | J8: 35288032 | K8: 0.48800586 | L8: 52508799 | M8: 35288032 | N8: 0.48800586 | O8: 17220767
B9: Multa + Mora - Crédito Imobiliário | C9: 0 | D9: 0 | E9: - | F9: 0 | G9: 0 | H9: - | I9: 3435925.9 | J9: 3057354.7 | K9: 0.12382311 | L9: 3435925.9 | M9: 3057354.7 | N9: 0.12382311 | O9: 378571.18
B11: Receita Juros - Cartão | C11: 0 | D11: 0 | E11: - | F11: 14467523 | G11: 13204429 | H11: 0.095656869 | I11: 503533.31 | J11: 331619.74 | K11: 0.51840571 | L11: 14971056 | M11: 13536048 | N11: 0.1060138 | O11: 1435007.9
B12: Receita Serviços | C12: 0 | D12: 0 | E12: - | F12: 0 | G12: 0 | H12: - | I12: 15698583 | J12: 13957800 | K12: 0.12471758 | L12: 15698583 | M12: 13957800 | N12: 0.12471758 | O12: 1740783.1
B13: Receita Interchange | C13: 0 | D13: 0 | E13: - | F13: 58738.824 | G13: 99732.494 | H13: -0.41103624 | I13: 96386.156 | J13: 134638.87 | K13: -0.28411343 | L13: 155124.98 | M13: 234371.36 | N13: -0.33812314 | O13: -79246.38
B14: Receita Comissão CRI | C14: 0 | D14: 0 | E14: - | F14: 0 | G14: 0 | H14: - | I14: 0 | J14: 0 | K14: - | L14: 0 | M14: 0 | N14: - | O14: 0
B15: Receita Cobrança Ext. Cebraco | C15: 0 | D15: 0 | E15: - | F15: 0 | G15: 0 | H15: - | I15: 2629524 | J15: 2343577.5 | K15: 0.12201278 | L15: 2629524 | M15: 2343577.5 | N15: 0.12201278 | O15: 285946.41
B16: Barigui Veículos | C16: 0 | D16: 0 | E16: - | F16: 0 | G16: 0 | H16: - | I16: 0 | J16: 0 | K16: - | L16: 0 | M16: 0 | N16: - | O16: 0
B17: Honorários | C17: 0 | D17: 0 | E17: - | F17: 0 | G17: 0 | H17: - | I17: 0 | J17: 0 | K17: - | L17: 0 | M17: 0 | N17: - | O17: 0
B18: Securitizadora (Patrimônio Separado) | C18: 0 | D18: 0 | E18: - | F18: 0 | G18: 0 | H18: - | I18: 0 | J18: 0 | K18: - | L18: 0 | M18: 0 | N18: - | O18: 0
B19: Resultado Securitizadora e Bariseg | F19: 0 | G19: 0 | H19: - | I19: 14406910 | J19: 9239718.1 | K19: 0.55923698 | L19: 14406910 | M19: 9239718.1 | N19: 0.55923698 | O19: 5167192.1
B20: Resultado de Seguros | C20: 0 | D20: 0 | E20: - | F20: 0 | G20: 0 | H20: - | I20: 7864687.8 | J20: 7276784.4 | K20: 0.080791655 | L20: 7864687.8 | M20: 7276784.4 | N20: 0.080791655 | O20: 587903.45
B21: Resultado Brasil Cards | C21: 0 | D21: 0 | E21: - | F21: 0 | G21: 0 | H21: - | I21: 625046.54 | J21: 64560.135 | K21: 8.6816176 | L21: 625046.54 | M21: 64560.135 | N21: 8.6816176 | O21: 560486.4
B22: Resultado Bari Capital | F22: 0 | G22: 0 | H22: - | I22: -101097.53 | J22: 340278.17 | K22: -1.2971026 | L22: -101097.53 | M22: 340278.17 | N22: -1.2971026 | O22: -441375.7
B23: Resultado Sec | C23: 0 | D23: 0 | E23: - | F23: 0 | G23: 0 | H23: - | I23: 6018273.3 | J23: 1558095.4 | K23: 2.8625833 | L23: 6018273.3 | M23: 1558095.4 | N23: 2.8625833 | O23: 4460177.9
B24: DESPESAS DE ORIGINAÇÃO | C24: 0 | D24: 0 | E24: - | F24: -36197985 | G24: -35595893 | H24: 0.016914645 | I24: -1.2243527e+08 | J24: -1.1573548e+08 | K24: 0.057888741 | L24: -1.5863325e+08 | M24: -1.5133138e+08 | N24: 0.048250888 | O24: 7301873.3
B25: Despesa de Captação | C25: 0 | D25: 0 | E25: - | F25: -36197985 | G25: -35595893 | H25: 0.016914645 | I25: -1.2243527e+08 | J25: -1.1573548e+08 | K25: 0.057888741 | L25: -1.5863325e+08 | M25: -1.5133138e+08 | N25: 0.048250888 | O25: 7301873.3
B26: Inflação | C26: 0 | D26: 0 | E26: - | F26: 0 | G26: 0 | H26: - | I26: -39760954 | J26: -42264572 | K26: -0.059236788 | L26: -39760954 | M26: -42264572 | N26: -0.059236788 | O26: -2503617.5
B27: DI/Pré | C27: 0 | D27: 0 | E27: - | F27: -42904056 | G27: -41486607 | H27: 0.034166421 | I27: -1.0294616e+08 | J27: -90982640 | K27: 0.1314923 | L27: -1.4585021e+08 | M27: -1.3246925e+08 | N27: 0.10101187 | O27: 13380966
B28: Receita Financeira + Outros | C28: 0 | D28: 0 | E28: - | F28: 5043028.8 | G28: 3935987.3 | H28: 0.28126145 | I28: 19259842 | J28: 15174128 | K28: 0.26925529 | L28: 24302871 | M28: 19110115 | N28: 0.27172812 | O28: 5192755.8
B29: Swap | C29: 0 | D29: 0 | E29: - | F29: 1663041.4 | G29: 1954725.9 | H29: -0.14922016 | I29: 1012004 | J29: 2337600.3 | K29: -0.5670757 | L29: 2675045.4 | M29: 4292326.2 | N29: -0.37678423 | O29: -1617280.8
B30: Impostos Diretos | C30: 0 | D30: 0 | E30: - | F30: -1928898.7 | G30: -1266472.1 | H30: 0.52304873 | I30: -7030303.8 | J30: -4490220.4 | K30: 0.56569238 | L30: -8959202.6 | M30: -5756692.5 | N30: 0.55631078 | O30: 3202510.1
B31: MARGEM INTERMEDIAÇÃO | C31: 0 | D31: 0 | E31: - | F31: 23003981 | G31: 24478866 | H31: -0.060251378 | I31: 1.1956321e+08 | J31: 99576591 | K31: 0.20071605 | L31: 1.4256719e+08 | M31: 1.2405546e+08 | N31: 0.14922145 | O31: 18511735
B32: Provisões | C32: 0 | D32: 0 | E32: - | F32: -4649091 | G32: -4856547.8 | H32: -0.042716923 | I32: -11464954 | J32: -11242879 | K32: 0.0197525 | L32: -16114045 | M32: -16099427 | N32: 0.00090799424 | O32: 14618.187
B33: Provisões | F33: -4649091 | G33: -4856547.8 | H33: -0.042716923 | I33: -9495766.1 | J33: -11242879 | K33: -0.15539728 | L33: -14144857 | M33: -16099427 | N33: -0.12140616 | O33: -1954569.5
B34: Desvalorização de BNDU | C34: 0 | D34: 0 | E34: - | F34: 0 | G34: 0 | H34: - | I34: -1969187.7 | J34: 0 | K34: - | L34: -1969187.7 | M34: 0 | N34: - | O34: 1969187.7
B35: MG INTERMEDIAÇÃO LIQ | C35: 0 | D35: 0 | E35: - | F35: 18354890 | G35: 19622319 | H35: -0.064591177 | I35: 1.0809826e+08 | J35: 88333712 | K35: 0.22374861 | L35: 1.2645315e+08 | M35: 1.0795603e+08 | N35: 0.17133936 | O35: 18497117
B36: Despesas Administrativas Diretas | C36: 0 | D36: 0 | E36: - | F36: -3550605.4 | G36: -3855147.6 | H36: -0.078996249 | I36: -17146280 | J36: -18543429 | K36: -0.075344696 | L36: -20696886 | M36: -22398577 | N36: -0.075973186 | O36: -1701691.2
B37: Comissão (Apoio - Comercial - Mídia Paga) | C37: 0 | D37: 0 | E37: - | F37: -492764.12 | G37: -383142.86 | H37: 0.28611067 | I37: -2526406.8 | J37: -1358415.6 | K37: 0.85981873 | L37: -3019170.9 | M37: -1741558.4 | N37: 0.73360296 | O37: 1277612.4
B38: MG CONTRIBUIÇÃO DIRETA | C38: 0 | D38: 0 | E38: - | F38: 14311520 | G38: 15384028 | H38: 0.069715663 | I38: 88425570 | J38: 68431867 | K38: 0.29216948 | L38: 1.0273709e+08 | M38: 83815895 | N38: 0.2257471 | O38: 18921196
B39: Desp. Administrativas Indiretas | C39: 0 | D39: 0 | E39: - | F39: -4495014.7 | G39: -4260590.5 | H39: 0.055021539 | I39: -15361252 | J39: -14961804 | K39: 0.026697849 | L39: -19856267 | M39: -19222395 | N39: 0.032975716 | O39: 633872.24
B40: Amortização | F40: -650580.56 | G40: -653439.96 | H40: -0.0043759185 | I40: -2308362.2 | J40: -2316741.7 | K40: -0.0036169259 | L40: -2958942.8 | M40: -2970181.6 | N40: -0.0037839042 | O40: -11238.883
B41: RESULTADO ANTES IMPOSTO | C41: 0 | D41: 0 | E41: - | F41: 9165925.1 | G41: 10469998 | H41: -0.12455328 | I41: 70755956 | J41: 51153321 | K41: 0.38321334 | L41: 79921881 | M41: 61623319 | N41: 0.29694217 | O41: 18298562
B42: Impostos (IR/CSLL) | C42: 0 | D42: 0 | E42: - | F42: -2561005.1 | G42: -3524588.1 | H42: -0.27338883 | I42: -19884638 | J42: -12500907 | K42: 0.59065566 | L42: -22445643 | M42: -16025495 | N42: 0.40062091 | O42: 6420148.3
B43: RESULTADO CONTÁBIL | C43: #REF! | D43: #REF! | E43: - | F43: 6604920 | G43: 6945409.6 | H43: -0.049023681 | I43: 50871318 | J43: 38652414 | K43: 0.31612265 | L43: 57476238 | M43: 45597824 | N43: 0.26050396 | O43: 11878414
B44: Margem Bruta | C44: 0 | D44: 0 | E44: - | F44: 0.084171555 | G44: 0.088513229 | H44: -0.0043416742 | I44: 0.10671911 | J44: 0.091328416 | K44: 0.015390691 | L44: 0.10229748 | M44: #DIV/0! | N44: -
B45: Margem Liquida | C45: 0 | D45: 0 | E45: - | F45: 0.067160533 | G45: 0.070952419 | H45: -0.0037918857 | I45: 0.096485779 | J45: 0.081016813 | K45: 0.015468966 | L45: 0.090735027 | M45: #DIV/0! | N45: -
B46: Rácio de Eficiência | C46: 0 | D46: 0 | E46: - | F46: -0.34974903 | G46: -0.3315406 | H46: -0.018208433 | I46: -0.27188574 | J46: -0.33647701 | K46: 0.064591267 | L46: -0.2844494 | M46: -0.33550295 | N46: 0.051053546
B47: Rácio de Eficiência Recorrente | C47: 0 | D47: 0 | E47: - | F47: -0.37803025 | G47: #REF! | H47: - | I47: #REF! | J47: #REF! | K47: - | L47: #REF! | M47: #REF! | N47: -
B48: RPL - RES. CONTÁBIL | C48: 0 | D48: 0 | E48: - | F48: #DIV/0! | G48: #REF! | H48: - | I48: #REF! | J48: #REF! | K48: - | L48: #REF! | M48: #REF! | N48: -
B49: Carteira de Crédito Bruta Média | C49: #DIV/0! | D49: #DIV/0! | E49: - | F49: 4.0994813e+08 | G49: 4.1483403e+08 | H49: -0.011777967 | I49: 1.6805315e+09 | J49: 1.63547e+09 | K49: 0.027552593 | L49: 2.0904796e+09 | M49: #DIV/0! | N49: - | O49: #DIV/0!
B50: Carteira de Crédito SD Cliente Média | F50: 4.087928e+08 | G50: 4.128159e+08 | H50: -0.0097455204 | I50: 1.6499967e+09 | J50: 1.6009865e+09 | K50: 0.030612493 | L50: 2.0587895e+09 | M50: 2.0138024e+09 | N50: 0.022339372 | O50: -44987082
B52: Taxa Média Carteira Bruta Média | C52: 0.019026332 | D52: 0.01872293 | E52: 0.016204825
B53: Taxa Média Carteira SD Cliente Média | C53: 0.019134686 | D53: 0.01878539 | E53: 0.018594041
B55: Rateio Carteira | C55: 0.21616784 | D55: 0.21770121 | E55: -0.0070434626
B56: Alocação de Capital | C56: 42965667 | D56: 43078625 | E56: -0.0026221344
B58: PL Médio (Banco + Hipo)
B59: PL Médio (Prudencial + BRCards)
B60: Margem Bruta | C60: 0 | D60: #DIV/0! | E60: #VALUE! | F60: 0.084289625 | G60: 0.08856939 | H60: -0.42797654 | I60: 0.10704574 | J60: 0.091727731 | K60: 1.5318014 | L60: 0.10257728 | M60: 0.091086807 | N60: 1.1490469
B61: Margem Liquida | C61: 0 | D61: #DIV/0! | E61: #VALUE! | F61: 0.067254741 | G61: 0.070997438 | H61: -0.37426965 | I61: 0.096781094 | J61: 0.081371042 | K61: 1.5410052 | L61: 0.0909832 | M61: 0.079265921 | N61: 1.1717279
B62: Rácio de Eficiência | C62: #DIV/0! | D62: #DIV/0! | E62: #VALUE! | F62: 0.34974903 | G62: 0.3315406 | H62: -1.8208433 | I62: 0.27188574 | J62: 0.33647701 | K62: 6.4591267 | L62: 0.2844494 | M62: 0.33550295 | N62: 5.1053546
B63: Rácio de Eficiência Recorrente | C63: #DIV/0! | D63: #DIV/0! | E63: #VALUE! | F63: -0.37803025 | G63: -0.35823465 | H63: -1.9795604 | I63: -0.29119237 | J63: -0.35974294 | K63: 6.8550568 | L63: -0.30520413 | M63: -0.35944532 | N63: 5.4241191
B64: RPL - RES. CONTÁBIL | C64: #DIV/0! | D64: #DIV/0! | E64: #VALUE! | F64: 0.22272288 | G64: 0.21694919 | H64: 0.5773691 | I64: 0.41915146 | J64: 0.31245431 | K64: 10.669715 | L64: 0.38058008 | M64: 0.29281968 | N64: 8.77604
B65: CARTEIRA DE CRÉDITO (MÉDIA DO SEMESTRE) | C65: 4.0937389e+08 | D65: #DIV/0! | E65: - | F65: 4.0937389e+08 | G65: 4.1457099e+08 | H65: -0.012536091 | I65: 1.6754035e+09 | J65: 1.6283504e+09 | K65: 0.028896194 | L65: 2.0847774e+09 | M65: 2.0429214e+09 | N65: 0.020488321 | O65: 41856030
B66: Carteira de Crédito SD Cliente Média | C66: 4.072434e+08 | D66: #DIV/0! | E66: - | F66: 4.072434e+08 | G66: 4.1256131e+08 | H66: -0.012889973 | I66: 1.6508475e+09 | J66: 1.5941852e+09 | K66: 0.035543089 | L66: 2.0580909e+09 | M66: 2.0067465e+09 | N66: 0.025585874
B67: Rateio da Carteira | F67: 0.19636336 | G67: 0.20558715 | I67: 0.80363664 | J67: 0.79441285
B68: Alocação de Capital | F68: 44482991 | G68: 48020987 | I68: 1.8205108e+08 | J68: 1.8555872e+08 | L68: 2.2653407e+08 | M68: 2.3357971e+08
B69: PL Médio | L69: 2.2653407e+08 | M69: 2.3357971e+08
B70: RECEITA ANUALIZADA POR COLABORADOR
B71: S/ CEBRACO | L71: 1501978.6
B72: C/ CEBRACO | L72: 1390850.4
L74: Realizado | M74: Orçado | N74: ∆
J75: Despesas Administrativas | L75: -40553153 | M75: -41620972 | N75: -0.025655792

Sheet Comparativo 2026 x 2025
B1: Data Base -> | F1: De: | G1: 45688 | H1: Até: | I1: 45900 | K1: Proporção anual para Indicadores -> | N1: 1.5
C3: BANCO DIGITAL | F3: CONSIGNADO | I3: IMOBILIARIO | L3: TOTAL
C4: Realizado | D4: Orçado | E4: ∆ (%) | F4: Realizado | G4: Orçado | H4: ∆ (%) | I4: Realizado | J4: Orçado | K4: ∆ (%) | L4: Realizado | M4: Orçado | N4: ∆ (%) | O4: ∆ (R$)
B5: RECEITAS | C5: 0 | D5: 0 | E5: - | F5: 57201693 | G5: 56372066 | H5: 0.014716976 | I5: 1.8161129e+08 | J5: 1.9060209e+08 | K5: -0.047170528 | L5: 2.3881298e+08 | M5: 2.4697415e+08 | N5: -0.033044651 | O5: -8161174.8
B6: Operações de Crédito | C6: 0 | D6: 0 | E6: - | F6: 56891182 | G6: 55762053 | H6: 0.020249051 | I6: 1.5989453e+08 | J6: 1.6878156e+08 | K6: -0.052654019 | L6: 2.1678572e+08 | M6: 2.2454361e+08 | N6: -0.034549631 | O6: -7757898.9
B7: Receita Juros | C7: 0 | D7: 0 | E7: - | F7: 44582919 | G7: 44238396 | H7: 0.0077878698 | I7: 1.1835412e+08 | J7: 1.1567703e+08 | K7: 0.023142819 | L7: 1.6293704e+08 | M7: 1.5991542e+08 | N7: 0.018895084 | O7: 3021615.3
B8: Receita CM - Crédito Imobiliário | C8: 0 | D8: 0 | E8: - | F8: 0 | G8: 0 | H8: - | I8: 38280773 | J8: 51596451 | K8: -0.25807352 | L8: 38280773 | M8: 51596451 | N8: -0.25807352 | O8: -13315678
B9: Multa + Mora - Crédito Imobiliário | C9: 0 | D9: 0 | E9: - | F9: 0 | G9: 0 | H9: - | I9: 2920472.2 | J9: 1188721.4 | K9: 1.456818 | L9: 2920472.2 | M9: 1188721.4 | N9: 1.456818 | O9: 1731750.8
B10: Receita Juros - Cartão | C10: 0 | D10: 0 | E10: - | F10: 12308262 | G10: 11523657 | H10: 0.068086532 | I10: 339168.07 | J10: 319361.31 | K10: 0.062019912 | L10: 12647430 | M10: 11843018 | N10: 0.067922938 | O10: 804412.57
B11: Receita Serviços | C11: 0 | D11: 0 | E11: - | F11: 0 | G11: 295536.06 | H11: -1 | I11: 10400476 | J11: 9307368 | K11: 0.11744549 | L11: 10400476 | M11: 9602904.1 | N11: 0.083055327 | O11: 797572.34
B12: Receita Interchange | C12: 0 | D12: 0 | E12: - | F12: 310510.91 | G12: 314477.18 | H12: -0.01261225 | I12: 419189.74 | J12: 424544.19 | K12: -0.01261225 | L12: 729700.65 | M12: 739021.37 | N12: -0.01261225 | O12: -9320.7223
B13: Receita Comissão CRI | C13: 0 | D13: 0 | E13: - | F13: 0 | G13: 0 | H13: - | I13: 2222657.7 | J13: 4406880 | K13: -0.49563916 | L13: 2222657.7 | M13: 4406880 | N13: -0.49563916 | O13: -2184222.3
B14: Receita Cobrança Ext. Cebraco | C14: 0 | D14: 0 | E14: - | F14: 0 | G14: 0 | H14: - | I14: 3009272.7 | J14: 2240000 | K14: 0.34342532 | L14: 3009272.7 | M14: 2240000 | N14: 0.34342532 | O14: 769272.72
B15: Barigui Veículos | C15: 0 | D15: 0 | E15: - | F15: 0 | G15: 0 | H15: - | I15: 410410.37 | J15: 0 | K15: - | L15: 410410.37 | M15: 0 | N15: - | O15: 410410.37
B16: Honorários | C16: 0 | D16: 0 | E16: - | F16: 0 | G16: 0 | H16: - | I16: 1667065.8 | J16: 0 | K16: - | L16: 1667065.8 | M16: 0 | N16: - | O16: 1667065.8
B17: Securitizadora (Patrimônio Separado) | C17: 0 | D17: 0 | E17: - | F17: 0 | G17: 0 | H17: - | I17: 931428.17 | J17: 0 | K17: - | L17: 931428.17 | M17: 0 | N17: - | O17: 931428.17
B18: Resultado de Seguros | C18: 0 | D18: 0 | E18: - | F18: 0 | G18: 0 | H18: - | I18: 5432634.3 | J18: 5046374.5 | K18: 0.076542041 | L18: 5432634.3 | M18: 5046374.5 | N18: 0.076542041 | O18: 386259.81
B19: Resultado Brasil Cards | C19: 0 | D19: 0 | E19: - | F19: 0 | G19: 0 | H19: - | I19: 232521.7 | J19: 395359.41 | K19: -0.41187261 | L19: 232521.7 | M19: 395359.41 | N19: -0.41187261 | O19: -162837.71
B20: DESPESAS DE ORIGINAÇÃO | C20: 0 | D20: 0 | E20: - | F20: -30170601 | G20: -28718194 | H20: 0.050574457 | I20: -86650295 | J20: -90718020 | K20: -0.044839219 | L20: -1.168209e+08 | M20: -1.1943621e+08 | N20: -0.021897195 | O20: 2615318.1
B21: Despesa de Captação* | C21: 0 | D21: 0 | E21: - | F21: -30170601 | G21: -28718194 | H21: 0.050574457 | I21: -86650295 | J21: -90718020 | K21: -0.044839219 | L21: -1.168209e+08 | M21: -1.1943621e+08 | N21: -0.021897195 | O21: 2615318.1
B22: Inflação | C22: 0 | D22: 0 | E22: - | F22: 0 | G22: 0 | H22: - | I22: -38532564 | J22: -46536540 | K22: -0.17199335 | L22: -38532564 | M22: -46536540 | N22: -0.17199335 | O22: 8003975.2
B23: DI/Pré | C23: 0 | D23: 0 | E23: - | F23: -38083333 | G23: -37029691 | H23: 0.028453987 | I23: -60360530 | J23: -56620763 | K23: 0.066049393 | L23: -98443863 | M23: -93650454 | N23: 0.051184049 | O23: -4793409.4
B24: Receita Financeira + Outros | C24: 0 | D24: 0 | E24: - | F24: 3423388.7 | G24: 3904485.3 | H24: -0.1232164 | I24: 10687446 | J24: 12016868 | K24: -0.11062965 | L24: 14110835 | M24: 15921353 | N24: -0.11371637 | O24: -1810518.6
B25: Swap | C25: 0 | D25: 0 | E25: - | F25: 4489343 | G25: 4407011.2 | H25: 0.018682023 | I25: 1555353.3 | J25: 422414.42 | K25: 2.6820555 | L25: 6044696.4 | M25: 4829425.6 | N25: 0.25163879 | O25: 1215270.8
B26: Impostos Diretos | C26: 0 | D26: 0 | E26: - | F26: -1191640.1 | G26: -1246661.4 | H26: -0.044134951 | I26: -4440462.7 | J26: -4277390 | K26: 0.038124344 | L26: -5632102.7 | M26: -5524051.4 | N26: 0.019560163 | O26: -108051.35
B27: MARGEM INTERMEDIAÇÃO | C27: 0 | D27: 0 | E27: - | F27: 25839451 | G27: 26407211 | H27: -0.021500165 | I27: 90520529 | J27: 95606678 | K27: -0.053198676 | L27: 1.1635998e+08 | M27: 1.2201389e+08 | N27: -0.046338234 | O27: -5653908.1
B28: Provisões | C28: 0 | D28: 0 | E28: - | F28: -3404014.4 | G28: -4778454.7 | H28: -0.2876328 | I28: -11765228 | J28: -5353404.2 | K28: 1.1977097 | L28: -15169243 | M28: -10131859 | N28: 0.49718259 | O28: -5037383.9
B29: Provisões | C29: 0 | D29: 0 | E29: - | F29: -3404014.4 | G29: -4778454.7 | H29: -0.2876328 | I29: -7880148.8 | J29: -5353404.2 | K29: 0.47198838 | L29: -11284163 | M29: -10131859 | N29: 0.11373078 | O29: -1152304.3
B30: Desvalorização e Recuperação de BNDU | C30: 0 | D30: 0 | E30: - | F30: 0 | G30: 0 | H30: - | I30: -3885079.6 | J30: 0 | K30: - | L30: -3885079.6 | M30: 0 | N30: - | O30: -3885079.6
B31: MG INTERMEDIAÇÃO LIQ | C31: 0 | D31: 0 | E31: - | F31: 22435437 | G31: 21628756 | H31: 0.037296686 | I31: 78755301 | J31: 90253273 | K31: -0.12739674 | L31: 1.0119074e+08 | M31: 1.1188203e+08 | N31: -0.095558616 | O31: -10691292
B32: Despesas Administrativas | F32: -11965446 | G32: -12806527 | H32: -0.06567593 | I32: -33958003 | J32: -35313253 | K32: -0.038377947 | L32: -45923449 | M32: -48119780 | N32: -0.045642991 | O32: 2196330.7
B33: Despesas Administrativas Diretas | C33: 0 | D33: 0 | E33: - | F33: -6043160.8 | G33: -5493575.6 | H33: 0.10004145 | I33: -20231964 | J33: -17613199 | K33: 0.14868195 | L33: -26275125 | M33: -23106775 | N33: 0.1371178 | O33: -3168350
B34: Amortização (estoque - projeto banco) | C34: 0 | E34: - | F34: 0 | H34: - | I34: 0 | K34: - | L34: -6053617 | M34: -6043321.5 | N34: 0.0017036243 | O34: -10295.549
B35: Comissão | C35: 0 | D35: 0 | E35: - | F35: -2494051.3 | G35: -213920.83 | H35: 10.658759 | I35: -1815485.3 | J35: -2387642 | K35: -0.23963253 | L35: -4309536.6 | M35: -2601562.8 | N35: 0.65651837 | O35: -1707973.8
B36: MG CONTRIBUIÇÃO DIRETA | C36: 0 | D36: 0 | E36: - | F36: 13898225 | G36: 15921260 | H36: -0.127065 | I36: 56707851 | J36: 70252432 | K36: -0.19279875 | L36: 64552459 | M36: 80130370 | N36: -0.19440708 | O36: -15577911
B37: Desp. Administrativas Indiretas | C37: 0 | D37: 0 | E37: - | F37: -5922285.7 | G37: -7312951.5 | H37: -0.19016478 | I37: -13726039 | J37: -17700054 | K37: -0.22451994 | L37: -19648324 | M37: -25013005 | N37: -0.21447566 | O37: 5364680.7
B38: RESULTADO ANTES IMPOSTO | C38: 0 | D38: 0 | E38: - | F38: 7975939.2 | G38: 8608308.1 | H38: -0.073460308 | I38: 42981813 | J38: 52552379 | K38: -0.1821148 | L38: 44904135 | M38: 55117365 | N38: -0.18529969 | O38: -10213231
B39: Impostos (IR/CSLL) | C39: 0 | D39: 0 | E39: - | F39: -1955387 | G39: -1976823.6 | H39: -0.010843956 | I39: -7013398.7 | J39: -13356571 | K39: -0.47491023 | L39: -8968785.7 | M39: -15333394 | N39: -0.41508153 | O39: 6364608.8
B40: RESULTADO ANTES PARTICIPAÇÃO | C40: 0 | D40: 0 | E40: - | F40: 6020552.2 | G40: 6631484.6 | H40: -0.092126035 | I40: 35968414 | J40: 39195808 | K40: -0.08234028 | L40: 35935349 | M40: 39783971 | N40: -0.096737999 | O40: -3848621.7
B41: PART. CONTROLADAS (SEC) | C41: 0 | D41: 0 | E41: - | F41: 0 | G41: 0 | H41: - | I41: 916457.71 | J41: 1576502.6 | K41: -0.41867669 | L41: 916457.71 | M41: 1576502.6 | N41: -0.41867669 | O41: -660044.88
B42: PART. ALIENAÇÃO CONTROLADAS (BARICOR e GESTÃO) | C42: 0 | D42: 0 | E42: - | F42: 0 | G42: 0 | H42: - | I42: 0 | J42: 0 | K42: - | L42: 0 | M42: 0 | N42: - | O42: 0
B43: Valor líquido | C43: 0 | D43: 0 | E43: - | F43: 0 | G43: 0 | H43: - | I43: 0 | J43: 0 | K43: - | L43: 0 | M43: 0 | N43: - | O43: 0
B44: Taxas e serviços | C44: 0 | D44: 0 | E44: - | F44: 0 | G44: 0 | H44: - | I44: 0 | J44: 0 | K44: - | L44: 0 | M44: 0 | N44: - | O44: 0
B45: Correção sobre a venda parcelada | C45: 0 | D45: 0 | E45: - | F45: 0 | G45: 0 | H45: - | I45: 0 | J45: 0 | K45: - | L45: 0 | M45: 0 | N45: - | O45: 0
B46: ÁGIO BARISEG REF. VENDA BARICOR | C46: 0 | D46: 0 | E46: - | F46: 0 | G46: 0 | H46: - | I46: -1249875 | J46: -1249875 | K46: 0 | L46: -1249875 | M46: -1249875 | N46: 0 | O46: 0
B47: ELO | F47: -187004 | G47: -860000 | I47: -252455.41 | J47: -1140000 | L47: -439459.41 | M47: -2000000 | N47: -0.7802703 | O47: 1560540.6
B48: RESULTADO CONTÁBIL | C48: 0 | D48: 0 | E48: - | F48: 5833548.2 | G48: 5771484.6 | H48: 0.010753492 | I48: 35382541 | J48: 38382435 | K48: -0.078157992 | L48: 35162472 | M48: 38110598 | N48: -0.077357117 | O48: -2948126
B49: Amortização (estoque - projeto banco) | C49: 0 | D49: 0 | E49: - | F49: 0 | G49: 0 | H49: - | I49: 0 | J49: 0 | K49: - | L49: 0 | M49: 0 | N49: - | O49: 0
B50: RESULTADO ANTES IMPOSTO RECORRENTE * | C50: 0 | D50: 0 | E50: - | F50: 7975939.2 | G50: 8608308.1 | H50: -0.073460308 | I50: 43898270 | J50: 54128881 | K50: -0.18900466 | L50: 51874210 | M50: 62737189 | N50: -0.17315057 | O50: -10862980
B51: RESULTADO CONTÁBIL RECORRENTE | C51: 0 | D51: 0 | E51: - | F51: 6020552.2 | G51: 6631484.6 | H51: -0.092126035 | I51: 36884872 | J51: 40772310 | K51: -0.095345067 | L51: 42905424 | M51: 47403795 | N51: -0.094894746 | O51: -4498371.1
B52: Margem Bruta | C52: 0 | D52: 0 | E52: - | F52: 0.097941162 | G52: 0.10152166 | H52: -0.003580502 | I52: 0.10843847 | J52: 0.11851884 | K52: -0.010080369 | L52: 0.10591754 | M52: 0.11437445 | N52: -0.008456909
B53: Margem Liquida | C53: 0 | D53: 0 | E53: - | F53: 0.085038677 | G53: 0.08315105 | H53: 0.0018876273 | I53: 0.094344391 | J53: 0.11188249 | K53: -0.017538098 | L53: 0.092109625 | M53: 0.10487696 | N53: -0.012767335
B54: Rácio de Eficiência | C54: 0 | D54: 0 | E54: - | F54: -0.46306891 | G54: -0.48496326 | H54: 0.021894355 | I54: -0.37514145 | J54: -0.36935969 | K54: -0.0057817621 | L54: -0.39466704 | M54: -0.39437953 | N54: -0.00028751203
B55: Rácio de Eficiência Recorrente | C55: 0 | D55: 0 | E55: - | F55: -0.46306891 | G55: -0.48496326 | H55: 0.021894355 | I55: -0.37514145 | J55: -0.36935969 | K55: -0.0057817621 | L55: -0.44669195 | M55: -0.44390931 | N55: -0.0027826344
B56: RPL - RES. CONTÁBIL | C56: 0 | D56: 0 | E56: - | F56: 0.18133036 | G56: 0.18925367 | H56: -0.0079233042 | I56: 0.34760106 | J56: 0.40583757 | K56: -0.058236514 | L56: 0.26248194 | M56: 0.30470957 | N56: -0.042227622
B57: RPL - RES. CONTÁBIL RECORRENTE | C57: 0 | D57: 0 | E57: - | F57: 0.18714321 | G57: 0.21745406 | H57: -0.1393897 | I57: 0.36236008 | J57: 0.43110697 | K57: -0.15946597 | L57: 0.32028178 | M57: 0.37901241 | N57: -0.15495703
B58: Carteira de Crédito Bruta Média | C58: 0 | D58: 0 | E58: - | F58: 3.957394e+08 | G58: 3.9017107e+08 | H58: 0.014271522 | I58: 1.252146e+09 | J58: 1.2100188e+09 | K58: 0.034815358 | L58: 1.6478854e+09 | M58: 1.6001898e+09 | N58: 0.029806196 | O58: -47695571
B59: Carteira de Crédito SD Cliente (média) | F59: 3.9569177e+08 | G59: 3.8960795e+08 | H59: 0.015615246 | I59: 1.2431108e+09 | J59: 1.1997678e+09 | K59: 0.03612616 | L59: 1.6388025e+09 | M59: 1.5893757e+09 | N59: 0.031098264 | O59: -49426826
H60: -6083824.1 | K60: -43343002 | N60: -49426826
B61: Taxa Média Carteira | C61: 0 | D61: 0 | E61: - | F61: 0.017972064 | G61: 0.017890437 | H61: 8.1626189e-05 | I61: 0.016078066 | J61: 0.017584816 | K61: -0.00150675 | L61: 0.016535375 | M61: 0.017659734 | N61: -0.0011243587
B63: Rateio Carteira | C63: 0 | D63: 0 | E63: - | F63: 0.24014983 | G63: 0.24382799 | H63: -0.0036781563 | I63: 0.75985017 | J63: 0.75617201 | K63: 0.0036781563 | L63: 1 | M63: 1 | N63: 0 | O63: 1
B64: Alocação de Capital | C64: 0 | D64: 0 | E64: - | F64: 48256244 | G64: 45744038 | H64: 0.054918778 | I64: 1.5268599e+08 | J64: 1.4186378e+08 | K64: 0.076285914 | L64: 2.0094224e+08 | M64: 1.8760782e+08 | N64: 0.071076008
B66: PL Médio | L66: 1.738729e+08 | M66: 1.8760782e+08 | N66: -0.073210826
B67: PL Médio (Prudencial + BRCards) | L67: 2.0094224e+08
B69: *Considerando part. Controladas e após Maio/23, ajustando o efeito do ágil. | K69: Check | L69: -0.010000028
L71: -45923449 | M71: -48119780 | N71: -0.045642991
M72: 2196330.7
B78: Análise de descasemento de indexadores | C78: Realizado | D78: Orçado | E78: ∆ (%)
B80: Receita CM de Crédito / Carteira Média | C80: 0.0038215166 | D80: 0.0053301293 | E80: -0.28303491
B81: Despesa CM de Captação / Carteira média Indexada | C81: -0.0040586233 | D81: -0.0054875053 | E81: -0.26038826
B83: Análise de descasemento de despesas | C83: Realizado | D83: Orçado* | E83: ∆ (%) | F83: ∆ (R$)
B84: Carteira de Captação Média | C84: 1.6820734e+09 | D84: 1.6252283e+09 | E84: 0.03497669 | F84: 56845105
B85: Carteira média DI/Pré | C85: 1.1354902e+09 | D85: 1.0235012e+09 | E85: 0.1094176 | F85: 1.1198904e+08
B86: Carteira média Indexada | C86: 5.4658316e+08 | D86: 6.0172709e+08 | E86: -0.091642765 | F86: -55143935
B87: Despesa de Captação | C87: -1.1682078e+08 | D87: -1.1943621e+08 | E87: -0.02189814 | F87: 2615430.9
B88: Despesa de Juros | C88: -1.1922931e+08 | D88: -1.1377115e+08 | E88: 0.047974946 | F88: -5458164.7
B89: Despesa de CM | C89: -17747001 | D89: -26415845 | E89: -0.32816832 | F89: 8668843.4
B90: Despesa FGC + Outros | C90: -2027145.5 | D90: -1742955.6 | E90: 0.16305058 | F90: -284189.92
B91: Receitas De Aplicações Financeiras | C91: 16137980 | D91: 17664309 | E91: -0.086407492 | F91: -1526328.6
B92: Swaps | C92: 6044696.4 | D92: 4829425.6 | E92: 0.25163879 | F92: 1215270.8
I93: Resultado Realizado anualizado | L93: 53903024
I94: PL Realizado Anualizado | L94: 2.556187e+08
I95: ROE Anualizado | L95: 0.21087277

Sheet 2025 Acumulado
A1: Data Base -> | B1: De: | C1: 45688 | D1: Até: | E1: 46022 | G1: Proporção anual para Indicadores -> | J1: 1
B3: CONSIGNADO | E3: IMOBILIARIO | H3: TOTAL
B4: Realizado | C4: Orçado | D4: ∆ (%) | E4: Realizado | F4: Orçado | G4: ∆ (%) | H4: Realizado | I4: Orçado | J4: ∆ (%)
A5: RECEITAS | B5: 88269444 | C5: 84959052 | D5: 0.038964555 | E5: 2.7231386e+08 | F5: 2.9372928e+08 | G5: -0.072908698 | H5: 3.6058331e+08 | I5: 3.7868834e+08 | J5: -0.047809838
A6: Operações de Crédito | B6: 87920541 | C6: 83942000 | D6: 0.047396309 | E6: 2.3506184e+08 | F6: 2.6189443e+08 | G6: -0.10245574 | H6: 3.2298238e+08 | I6: 3.4583643e+08 | J6: -0.0660834
A7: Receita Juros | B7: 68686739 | C7: 66826765 | D7: 0.027832778 | E7: 1.8332712e+08 | F7: 1.8124217e+08 | G7: 0.01150366 | H7: 2.5201386e+08 | I7: 2.4806894e+08 | J7: 0.015902527
A8: Receita CM - Crédito Imobiliário | B8: 0 | C8: 0 | D8: - | E8: 46919033 | F8: 78348182 | G8: -0.40114713 | H8: 46919033 | I8: 78348182 | J8: -0.40114713
A9: Multa + Mora - Crédito Imobiliário | B9: 0 | C9: 0 | D9: - | E9: 4285982.6 | F9: 1816085.3 | G9: 1.3600117 | H9: 4285982.6 | I9: 1816085.3 | J9: 1.3600117
A11: Receita Juros - Cartão | B11: 19233801 | C11: 17115235 | D11: 0.1237825 | E11: 529702.4 | F11: 487987.54 | G11: 0.085483448 | H11: 19763504 | I11: 17603222 | J11: 0.12272079
A12: Receita Serviços | B12: 0 | C12: 531524.41 | D12: -1 | E12: 18145792 | F12: 14301322 | G12: 0.26881923 | H12: 18145792 | I12: 14832846 | J12: 0.223352
A13: Receita Interchange | B13: 348903.31 | C13: 485528.2 | D13: -0.28139436 | E13: 493609.19 | F13: 655463.07 | G13: -0.24693058 | H13: 842512.5 | I13: 1140991.3 | J13: -0.26159602
A14: Receita Comissão CRI | B14: 0 | C14: 0 | D14: - | E14: 4424123.9 | F14: 4857056.4 | G14: -0.089134753 | H14: 4424123.9 | I14: 4857056.4 | J14: -0.089134753
A15: Receita Cobrança Ext. Cebraco | B15: 0 | C15: 0 | D15: - | E15: 3983364.6 | F15: 3360000 | G15: 0.18552517 | H15: 3983364.6 | I15: 3360000 | J15: 0.18552517
A16: Barigui Veículos | B16: 0 | C16: 0 | D16: - | E16: 410438.53 | F16: 0 | G16: - | H16: 410438.53 | I16: 0 | J16: -
A17: Honorários | B17: 0 | C17: 0 | D17: - | E17: 1667265.4 | F17: 0 | G17: - | H17: 1667265.4 | I17: 0 | J17: -
A18: Securitizadora (Patrimônio Separado) | B18: 0 | C18: 0 | D18: - | E18: 931451.97 | F18: 0 | G18: - | H18: 931451.97 | I18: 0 | J18: -
A19: Resultado de Seguros | B19: 0 | C19: 0 | D19: - | E19: 8976643.7 | F19: 7888318.4 | G19: 0.13796671 | H19: 8976643.7 | I19: 7888318.4 | J19: 0.13796671
A20: Resultado Brasil Cards | B20: 0 | C20: 0 | D20: - | E20: 683540.55 | F20: 772697.59 | G20: -0.11538413 | H20: 683540.55 | I20: 772697.59 | J20: -0.11538413
A21: Resultado Bari Capital | B21: 0 | C21: 0 | D21: - | E21: 544951.51 | F21: 0 | G21: - | H21: 544951.51 | I21: 0 | J21: -
A22: DESPESAS DE ORIGINAÇÃO | B22: -48653179 | C22: -45170057 | D22: 0.077111318 | E22: -1.3205401e+08 | F22: -1.4210875e+08 | G22: -0.070753802 | H22: -1.8070719e+08 | I22: -1.872788e+08 | J22: -0.035089991
A23: Despesa de Captação* | B23: -48653179 | C23: -45170057 | D23: 0.077111318 | E23: -1.3205401e+08 | F23: -1.4210875e+08 | G23: -0.070753802 | H23: -1.8070719e+08 | I23: -1.872788e+08 | J23: -0.035089991
A24: Inflação | B24: 0 | C24: 0 | D24: - | E24: -53112595 | F24: -77654065 | G24: -0.31603587 | H24: -53112595 | I24: -77654065 | J24: -0.31603587
A25: DI/Pré | B25: -61004861 | C25: -57980136 | D25: 0.0521683 | E25: -1.0075194e+08 | F25: -84729262 | G25: 0.18910446 | H25: -1.617568e+08 | I25: -1.427094e+08 | J25: 0.13346988
A26: Receita Financeira + Outros | B26: 5493918.9 | C26: 5922496 | D26: -0.072364259 | E26: 18476785 | F26: 18971719 | G26: -0.026087963 | H26: 23970704 | I26: 24894215 | J26: -0.037097395
A27: Swap | B27: 6857763.2 | C27: 6887583.7 | D27: -0.0043295954 | E27: 3333739.2 | F27: 1302860.2 | G27: 1.558785 | H27: 10191502 | I27: 8190443.9 | J27: 0.24431625
A28: Impostos Diretos | B28: -1591790.6 | C28: -1792668.1 | D28: -0.11205502 | E28: -6527501.5 | F28: -6510661.1 | G28: 0.0025865869 | H28: -8119292.1 | I28: -8303329.1 | J28: -0.022164249
A29: MARGEM INTERMEDIAÇÃO | B29: 38024474 | C29: 37996328 | D29: 0.00074076924 | E29: 1.3373235e+08 | F29: 1.4510987e+08 | G29: -0.078406283 | H29: 1.7175682e+08 | I29: 1.831062e+08 | J29: -0.061982495
A30: Provisões | B30: -5498186.1 | C30: -7372217.8 | D30: -0.25420189 | E30: -14656115 | F30: -7837978.3 | G30: 0.86988464 | H30: -20154301 | I30: -15210196 | J30: 0.32505204
A31: Provisões | B31: -5498186.1 | C31: -7372217.8 | D31: -0.25420189 | E31: -10630352 | F31: -7837978.3 | G31: 0.35626198 | H31: -16128538 | I31: -15210196 | J31: 0.060376731
A32: Desvalorização e Recuperação de BNDU | B32: 0 | C32: 0 | D32: - | E32: -4025763.3 | F32: 0 | G32: - | H32: -4025763.3 | I32: 0 | J32: -
A33: MG INTERMEDIAÇÃO LIQ | B33: 32526288 | C33: 30624110 | D33: 0.062113747 | E33: 1.1907623e+08 | F33: 1.372719e+08 | G33: -0.13255199 | H33: 1.5160252e+08 | I33: 1.6789601e+08 | J33: -0.097045099
A34: Despesas Administrativas | B34: -17658238 | C34: -20638806 | D34: -0.1444157 | E34: -52085354 | F34: -55082877 | G34: -0.054418408 | H34: -69743592 | I34: -75721682 | J34: -0.078948193
A35: Despesas Administrativas Diretas | B35: -9020916.1 | C35: -8317602.1 | D35: 0.084557301 | E35: -30259436 | F35: -26684630 | G35: 0.13396497 | H35: -39280352 | I35: -35002232 | J35: 0.12222419
A36: Amortização (estoque - projeto banco) | B36: 0 | D36: - | E36: 0 | G36: - | H36: -8210141.8 | I36: -8194948.9 | J36: 0.0018539271
A37: Comissão | B37: -2713906.1 | C37: -283764.47 | D37: 8.563939 | E37: -2649708.1 | F37: -2628323.4 | G37: 0.0081362759 | H37: -5363614.2 | I37: -2912087.8 | J37: 0.84184493
A38: MG CONTRIBUIÇÃO DIRETA | B38: 20791466 | C38: 22022743 | D38: -0.055909356 | E38: 86167089 | F38: 1.0795894e+08 | G38: -0.20185315 | H38: 98748413 | I38: 1.2178674e+08 | J38: -0.1891694
A39: Desp. Administrativas Indiretas | B39: -8637322 | C39: -12321203 | D39: -0.29898715 | E39: -21825918 | F39: -28398246 | G39: -0.23143429 | H39: -30463240 | I39: -40719450 | J39: -0.25187495
A40: RESULTADO ANTES IMPOSTO | B40: 12154144 | C40: 9701539.8 | D40: 0.25280565 | E40: 64341171 | F40: 79560696 | G40: -0.19129452 | H40: 68285173 | I40: 81067287 | J40: -0.15767289
A41: Impostos (IR/CSLL) | B41: -2350694.6 | C41: -2591942.2 | D41: -0.093076003 | E41: -10196005 | F41: -20766279 | G41: -0.50901147 | H41: -12546699 | I41: -23358221 | J41: -0.46285724
A42: RESULTADO ANTES PARTICIPAÇÃO | B42: 9803449.3 | C42: 7109597.6 | D42: 0.37890354 | E42: 54145166 | F42: 58794417 | G42: -0.0790764 | H42: 55738474 | I42: 57709066 | J42: -0.034147009
A43: PART. CONTROLADAS (SEC) | B43: 0 | C43: 0 | D43: - | E43: 1868106.3 | F43: 2222827 | G43: -0.15958088 | H43: 1868106.3 | I43: 2222827 | J43: -0.15958088
A44: PART. ALIENAÇÃO CONTROLADAS (BARICOR e GESTÃO) | B44: 0 | C44: 0 | D44: - | E44: 0 | F44: 0 | G44: - | H44: 0 | I44: 0 | J44: -
A45: Valor líquido | B45: 0 | C45: 0 | D45: - | E45: 0 | F45: 0 | G45: - | H45: 0 | I45: 0 | J45: -
A46: Taxas e serviços | B46: 0 | C46: 0 | D46: - | E46: 0 | F46: 0 | G46: - | H46: 0 | I46: 0 | J46: -
A47: Correção sobre a venda parcelada | B47: 0 | C47: 0 | D47: - | E47: 0 | F47: 0 | G47: - | H47: 0 | I47: 0 | J47: -
A48: ÁGIO BARISEG REF. VENDA BARICOR | B48: 0 | C48: 0 | D48: - | E48: -1249875 | F48: -1249875 | G48: 0 | H48: -1249875 | I48: -1249875 | J48: 0
A49: ELO | B49: -186920.01 | C49: -1290000 | E49: -321978.76 | F49: -1710000 | H49: -508898.76 | I49: -3000000 | J49: -0.83036708
A50: RESULTADO CONTÁBIL | B50: 9803449.3 | C50: 7109597.6 | D50: 0.37890354 | E50: 54763397 | F50: 59767369 | G50: -0.08372414 | H50: 56356705 | I50: 58682018 | J50: -0.039625643
A51: Amortização (estoque - projeto banco) | B51: 0 | C51: 0 | D51: - | E51: 0 | F51: 0 | G51: - | H51: 0 | I51: 0 | J51: -
A52: RESULTADO ANTES IMPOSTO RECORRENTE * | B52: 12154144 | C52: 10991540 | D52: 0.10577263 | E52: 66209277 | F52: 83493523 | G52: -0.20701301 | H52: 78363421 | I52: 94485063 | J52: -0.17062635
A53: RESULTADO CONTÁBIL RECORRENTE | B53: 9803449.3 | C53: 8399597.6 | D53: 0.16713321 | E53: 56013272 | F53: 62727244 | G53: -0.10703438 | H53: 65816722 | I53: 71126842 | J53: -0.074657045
A54: Margem Bruta | B54: 0.094871575 | C54: 0.096879823 | D54: -0.0020082481 | E54: 0.10329451 | F54: 0.11412002 | G54: -0.010825505 | H54: 0.10130338 | I54: 0.11005595 | J54: -0.0087525717
A55: Margem Liquida | B55: 0.081153527 | C55: 0.078082766 | D55: 0.003070761 | E55: 0.091974168 | F55: 0.10795593 | G55: -0.01598176 | H55: 0.089416229 | I55: 0.10091386 | J55: -0.011497634
A56: Rácio de Eficiência | B56: -0.46439138 | C56: -0.54317896 | D56: 0.078787575 | E56: -0.38947461 | F56: -0.37959427 | G56: -0.0098803405 | H56: -0.4060601 | I56: -0.41353969 | J56: 0.0074795932
A57: Rácio de Eficiência Recorrente | B57: -0.46439138 | C57: -0.54317896 | D57: 0.078787575 | E57: -0.38947461 | F57: -0.37959427 | G57: -0.0098803405 | H57: -0.45386106 | I57: -0.45829486 | J57: 0.0044337973
A58: RPL - RES. CONTÁBIL | B58: 0.2003762 | C58: 0.15417526 | D58: 0.046200942 | E58: 0.34651776 | F58: 0.39976701 | G58: -0.053249252 | H58: 0.27230139 | I58: 0.2999808 | J58: -0.027679412
A59: RPL - RES. CONTÁBIL RECORRENTE | B59: 0.2003762 | C59: 0.18214957 | D59: 0.018226632 | E59: 0.3544264 | F59: 0.41956478 | G59: -0.06513838 | H59: 0.31800981 | I59: 0.36359839 | J59: -0.045588582
A60: Carteira de Crédito Bruta Média | B60: 4.0079944e+08 | C60: 3.9220063e+08 | D60: 0.02192452 | E60: 1.2946704e+09 | F60: 1.271555e+09 | G60: 0.018178877 | H60: 1.6954699e+09 | I60: 1.6637556e+09 | J60: 0.019061845
A61: Carteira de Crédito SD Cliente (média) | B61: 4.0075181e+08 | C61: 3.912727e+08 | D61: 0.024226339 | E61: 1.2872629e+09 | F61: 1.256423e+09 | G61: 0.024545851 | H61: 1.6880147e+09 | I61: 1.6476957e+09 | J61: 0.024469977
A63: Taxa Média Carteira | B63: 0.018282417 | C63: 0.017877983 | D63: 0.00040443436 | E63: 0.01521716 | F63: 0.017370373 | G63: -0.0021532126 | H63: 0.015944883 | I63: 0.017490913 | J63: -0.00154603
A65: Rateio Carteira | B65: 0.23639432 | C65: 0.23573212 | D65: 0.00066220157 | E65: 0.76360568 | F65: 0.76426788 | G65: -0.00066220157 | H65: 1 | I65: 1 | J65: 0
A66: Alocação de Capital | B66: 48925218 | C66: 46113738 | D66: 0.060968372 | E66: 1.5803922e+08 | F66: 1.4950551e+08 | G66: 0.057079623 | H66: 2.0696444e+08 | I66: 1.9561924e+08 | J66: 0.057996326
B67: -0.19340684 | E67: -0.15846782 | H67: -0.18373973 | I67: -0.28813375
A68: PL Médio | H68: 1.7916388e+08 | I68: 1.9561924e+08 | J68: -0.084119324
A69: PL Médio (Prudencial + BRCards) | H69: 2.0696444e+08

Sheet BASE DASH
A1: DASHBOARD P&L 2026
A2: Aba
A4: Resultados
B6: Principais Resultados
C7: 46023 | D7: 46054 | E7: ∆ 02/26 | F7: 46082 | G7: ∆ 03/26 | H7: 46113 | I7: ∆ 04/26 | J7: 46143 | K7: ∆ 05/26 | L7: =EDATE(J7,1) -> 46174 | M7: ∆ 06/26
B8: Resultado Conglomerado Financeiro | C8: =RESULTADO!CC8 -> 1823210.1 | D8: =RESULTADO!CD8 -> 2383715.7 | E8: =(D8/C8)-1 -> 0.30742786 | F8: =RESULTADO!CE8 -> 4565343.7 | G8: =(F8/D8)-1 -> 0.91522156 | H8: =RESULTADO!CF8 -> 6998345 | I8: =(H8/F8)-1 -> 0.53292839 | J8: =RESULTADO!CG8 -> 6574996.5 | K8: =(J8/H8)-1 -> -0.060492656 | L8: =RESULTADO!CH8 -> 4794631.1 | M8: =(L8/J8)-1 -> -0.27077816
B9: Resultado Coligadas | C9: =RESULTADO!CC19 -> 1948578.9 | D9: =RESULTADO!CD19 -> 1926006.6 | E9: =(D9/C9)-1 -> -0.011583975 | F9: =RESULTADO!CE19 -> 3021711.4 | G9: =(F9/D9)-1 -> 0.56889979 | H9: =RESULTADO!CF19 -> 2088290.6 | I9: =(H9/F9)-1 -> -0.3089047 | J9: =RESULTADO!CG19 -> 2711002.9 | K9: =(J9/H9)-1 -> 0.29819238 | L9: =RESULTADO!CH19 -> 3820296.8 | M9: =(L9/J9)-1 -> 0.40918213
B10: Resultado Conglomerado + Coligadas | C10: =RESULTADO!CC21 -> 3771789.1 | D10: =RESULTADO!CD21 -> 4309722.3 | E10: =(D10/C10)-1 -> 0.1426202 | F10: =RESULTADO!CE21 -> 7587055.1 | G10: =(F10/D10)-1 -> 0.76045103 | H10: =RESULTADO!CF21 -> 9086635.6 | I10: =(H10/F10)-1 -> 0.19764987 | J10: =RESULTADO!CG21 -> 9285999.4 | K10: =(J10/H10)-1 -> 0.021940337 | L10: =RESULTADO!CH21 -> 8614927.9 | M10: =(L10/J10)-1 -> -0.072267025
B11: Resultado Total | C11: =RESULTADO!CC26 -> 3817153.8 | D11: =RESULTADO!CD26 -> 4359452.6 | E11: =(D11/C11)-1 -> 0.14206889 | F11: =RESULTADO!CE26 -> 7672682.9 | G11: =(F11/D11)-1 -> 0.76001062 | H11: =RESULTADO!CF26 -> 9147910.1 | I11: =(H11/F11)-1 -> 0.19227006 | J11: =RESULTADO!CG26 -> 9308989.8 | K11: =(J11/H11)-1 -> 0.017608362 | L11: =RESULTADO!CH26 -> 8697469.9 | M11: =(L11/J11)-1 -> -0.065691325
C13: Resultado Total Acumulado em 2026
C14: 46023 | D14: 46054 | E14: 46082 | F14: 46113 | G14: 46143 | H14: =L7 -> 46174
C15: =C11 -> 3817153.8 | D15: =SUM(C11,D11) -> 8176606.4 | E15: =SUM(C11,D11,F11) -> 15849289 | F15: =C11+D11+F11+H11 -> 24997199 | G15: =SUM(C11,D11,F11,H11,J11) -> 34306189 | H15: =G15+L11 -> 43003659
C17: Composição do Resultado Total Acumulado
C18: 46023 | D18: 46054 | E18: 46082 | F18: 46113 | G18: 46143 | H18: =L7 -> 46174
B19: Consignado | C19: ='P&L Mensal - Anualizado'!B42 -> 1438495.7 | D19: 1101623.1 | E19: ='P&L Mensal - Anualizado'!X42 -> 733372.52 | F19: ='P&L Mensal - Anualizado'!AI42 -> 1208570.6 | G19: ='P&L Mensal - Anualizado'!AT42 -> 655794.9 | H19: ='P&L Mensal - Anualizado'!BE42 -> 877126.28
B20: Imobiliário | C20: ='P&L Mensal - Anualizado'!E42 -> 2378658.1 | D20: 3257829.5 | E20: ='P&L Mensal - Anualizado'!AA42 -> 6939310.4 | F20: ='P&L Mensal - Anualizado'!AL42 -> 7939339.5 | G20: ='P&L Mensal - Anualizado'!AW42 -> 8653194.9 | H20: ='P&L Mensal - Anualizado'!BH42 -> 7820343.6
C22: Resultado Contábil Acumulado x Orçado 2026
C23: 46023 | D23: 46054 | E23: 46082 | F23: 46113 | G23: 46143 | H23: =L7 -> 46174
B24: Realizado | C24: =C15 -> 3817153.8 | D24: =D15 -> 8176606.4 | E24: =E15 -> 15849289 | F24: =F15 -> 24997199 | G24: =G15 -> 34306189 | H24: =H15 -> 43003659
B25: Orçado | C25: =73400000 -> 73400000 | D25: =73400000 -> 73400000 | E25: =73400000 -> 73400000 | F25: =73400000 -> 73400000 | G25: =73400000 -> 73400000 | H25: =73400000 -> 73400000
B26: Restante | C26: =C25-C24 -> 69582846 | D26: =D25-D24 -> 65223394 | E26: =E25-E24 -> 57550711 | F26: =F25-F24 -> 48402801 | G26: =G25-G24 -> 39093811 | H26: =H25-H24 -> 30396341
B27: Total da Meta % | C27: =(C24/C25) -> 0.05200482 | D27: =(D24/D25) -> 0.11139791 | E27: =(E24/E25) -> 0.21593037 | F27: =(F24/F25) -> 0.3405613 | G27: =(G24/G25) -> 0.46738677 | H27: =(H24/H25) -> 0.58588091
A29: P&L Mensal
C32: Principais Linhas do P&L Mensal
C33: 46023 | F33: 46054 | I33: ∆ 02/26 | L33: 46082 | O33: ∆ 03/26 | R33: 46113 | U33: ∆ 04/26 | X33: 46143 | AA33: ∆ 05/26 | AD33: =L7 -> 46174 | AG33: ∆ 06/26
C34: Consignado | D34: Imobiliário | E34: Total | F34: Consignado | G34: Imobiliário | H34: Total | I34: ∆ Consignado | J34: ∆ Imobiliário | K34: ∆ Total | L34: Consignado | M34: Imobiliário | N34: Total | O34: ∆ Consignado | P34: ∆ Imobiliário | Q34: ∆ Total | R34: Consignado | S34: Imobiliário | T34: Total | U34: ∆ Consignado | V34: ∆ Imobiliário | W34: ∆ Total | X34: Consignado | Y34: Imobiliário | Z34: Total | AA34: ∆ Consignado | AB34: ∆ Imobiliário | AC34: ∆ Total | AD34: Consignado | AE34: Imobiliário | AF34: Total | AG34: ∆ Consignado | AH34: ∆ Imobiliário | AI34: ∆ Total
B35: Receitas | C35: ='P&L Mensal - Anualizado'!B5 -> 7802027.9 | D35: ='P&L Mensal - Anualizado'!E5 -> 23859887 | E35: =D35+C35 -> 31661915 | F35: ='P&L Mensal - Anualizado'!M5 -> 7098724.1 | G35: ='P&L Mensal - Anualizado'!P5 -> 23773864 | H35: =G35+F35 -> 30872588 | I35: =F35/C35-1 -> -0.090143719 | J35: =G35/D35-1 -> -0.0036053538 | K35: =H35/E35-1 -> -0.024929861 | L35: ='P&L Mensal - Anualizado'!X5 -> 7877352.9 | M35: ='P&L Mensal - Anualizado'!AA5 -> 33774613 | N35: =M35+L35 -> 41651965 | O35: =L35/F35-1 -> 0.10968575 | P35: =M35/G35-1 -> 0.42066146 | Q35: =N35/H35-1 -> 0.3491569 | R35: ='P&L Mensal - Anualizado'!AI5 -> 7513769.7 | S35: ='P&L Mensal - Anualizado'!AL5 -> 34391853 | T35: =S35+R35 -> 41905623 | U35: =R35/L35-1 -> -0.04615551 | V35: =S35/M35-1 -> 0.018275293 | W35: =T35/N35-1 -> 0.0060899333 | X35: ='P&L Mensal - Anualizado'!AT5 -> 7585530.4 | Y35: ='P&L Mensal - Anualizado'!AW5 -> 37483958 | Z35: =Y35+X35 -> 45069488 | AA35: =X35/R35-1 -> 0.0095505616 | AB35: =Y35/S35-1 -> 0.089908042 | AC35: =Z35/T35-1 -> 0.07549977 | AD35: ='P&L Mensal - Anualizado'!BE5 -> 7768119.1 | AE35: ='P&L Mensal - Anualizado'!BH5 -> 34678251 | AF35: ='P&L Mensal - Anualizado'!BK5 -> 42446371 | AG35: =AD35/X35-1 -> 0.024070662 | AH35: =AE35/Y35-1 -> -0.074850854 | AI35: =AF35/Z35-1 -> -0.058201626
B36: Despesas de Originação | C36: ='P&L Mensal - Anualizado'!B21 -> -4115579.3 | D36: ='P&L Mensal - Anualizado'!E21 -> -13893293 | E36: =D36+C36 -> -18008872 | F36: ='P&L Mensal - Anualizado'!M21 -> -3458538.1 | G36: ='P&L Mensal - Anualizado'!P21 -> -11194223 | H36: =G36+F36 -> -14652761 | I36: =F36/C36-1 -> -0.15964731 | J36: =G36/D36-1 -> -0.19427144 | K36: =H36/E36-1 -> -0.18635877 | L36: ='P&L Mensal - Anualizado'!X21 -> -4803644.1 | M36: ='P&L Mensal - Anualizado'!AA21 -> -17862654 | N36: =M36+L36 -> -22666298 | O36: =L36/F36-1 -> 0.38892327 | P36: =M36/G36-1 -> 0.59570289 | Q36: =N36/H36-1 -> 0.54689603 | R36: ='P&L Mensal - Anualizado'!AI21 -> -4383516.3 | S36: ='P&L Mensal - Anualizado'!AL21 -> -17657422 | T36: =S36+R36 -> -22040938 | U36: =R36/L36-1 -> -0.087460219 | V36: =S36/M36-1 -> -0.01148947 | W36: =T36/N36-1 -> -0.027589869 | X36: ='P&L Mensal - Anualizado'!AT21 -> -4480613.7 | Y36: ='P&L Mensal - Anualizado'!AW21 -> -15739911 | Z36: =Y36+X36 -> -20220525 | AA36: =X36/R36-1 -> 0.022150564 | AB36: =Y36/S36-1 -> -0.10859516 | AC36: =Z36/T36-1 -> -0.082592362 | AD36: ='P&L Mensal - Anualizado'!BE21 -> -4804004.9 | AE36: ='P&L Mensal - Anualizado'!BH21 -> -17194338 | AF36: ='P&L Mensal - Anualizado'!BK21 -> -21998343 | AG36: =AD36/X36-1 -> 0.072175649 | AH36: =AE36/Y36-1 -> 0.092403741 | AI36: =AF36/Z36-1 -> 0.087921451
B37: Margem de Intermediação | C37: ='P&L Mensal - Anualizado'!B30 -> 3504281.6 | D37: ='P&L Mensal - Anualizado'!E30 -> 9570904.2 | E37: =D37+C37 -> 13075186 | F37: ='P&L Mensal - Anualizado'!M30 -> 3464917.2 | G37: ='P&L Mensal - Anualizado'!P30 -> 11886877 | H37: =G37+F37 -> 15351794 | I37: =F37/C37-1 -> -0.011233232 | J37: =G37/D37-1 -> 0.24198055 | K37: =H37/E37-1 -> 0.1741167 | L37: ='P&L Mensal - Anualizado'!X30 -> 2853178.9 | M37: ='P&L Mensal - Anualizado'!AA30 -> 15040297 | N37: =M37+L37 -> 17893476 | O37: =L37/F37-1 -> -0.17655207 | P37: =M37/G37-1 -> 0.26528587 | Q37: =N37/H37-1 -> 0.16556255 | R37: ='P&L Mensal - Anualizado'!AI30 -> 2958757.4 | S37: ='P&L Mensal - Anualizado'!AL30 -> 15845885 | T37: =S37+R37 -> 18804642 | U37: =R37/L37-1 -> 0.037003822 | V37: =S37/M37-1 -> 0.053561935 | W37: =T37/N37-1 -> 0.050921685 | X37: ='P&L Mensal - Anualizado'!AT30 -> 2791893.9 | Y37: ='P&L Mensal - Anualizado'!AW30 -> 20634238 | Z37: =Y37+X37 -> 23426132 | AA37: =X37/R37-1 -> -0.056396503 | AB37: =Y37/S37-1 -> 0.30218278 | AC37: =Z37/T37-1 -> 0.24576325 | AD37: ='P&L Mensal - Anualizado'!BE30 -> 2640144.9 | AE37: ='P&L Mensal - Anualizado'!BH30 -> 16335295 | AF37: ='P&L Mensal - Anualizado'!BK30 -> 18975440 | AG37: =AD37/X37-1 -> -0.054353414 | AH37: =AE37/Y37-1 -> -0.20834029 | AI37: =AF37/Z37-1 -> -0.18998835
B38: Provisões | C38: ='P&L Mensal - Anualizado'!B31 -> -725978.64 | D38: ='P&L Mensal - Anualizado'!E31 -> -1516697.2 | E38: =D38+C38 -> -2242675.9 | F38: ='P&L Mensal - Anualizado'!M31 -> -403888.51 | G38: ='P&L Mensal - Anualizado'!P31 -> -1775414.1 | H38: =G38+F38 -> -2179302.6 | I38: =F38/C38-1 -> -0.44366337 | J38: =G38/D38-1 -> 0.17057913 | K38: =H38/E38-1 -> -0.028257869 | L38: ='P&L Mensal - Anualizado'!X31 -> -610260.52 | M38: ='P&L Mensal - Anualizado'!AA31 -> -439697.65 | N38: =M38+L38 -> -1049958.2 | O38: =L38/F38-1 -> 0.51096282 | P38: =M38/G38-1 -> -0.75234079 | Q38: =N38/H38-1 -> -0.51821369 | R38: ='P&L Mensal - Anualizado'!AI31 -> -483020.98 | S38: ='P&L Mensal - Anualizado'!AL31 -> -2252289.5 | T38: =S38+R38 -> -2735310.5 | U38: =R38/L38-1 -> -0.20850036 | V38: =S38/M38-1 -> 4.1223597 | W38: =T38/N38-1 -> 1.6051614 | X38: ='P&L Mensal - Anualizado'!AT31 -> -706208.48 | Y38: ='P&L Mensal - Anualizado'!AW31 -> -2828879.5 | Z38: =Y38+X38 -> -3535088 | AA38: =X38/R38-1 -> 0.46206585 | AB38: =Y38/S38-1 -> 0.25600173 | AC38: =Z38/T38-1 -> 0.29239003 | AD38: ='P&L Mensal - Anualizado'!BE31 -> -455481.61 | AE38: ='P&L Mensal - Anualizado'!BH31 -> -1360932.6 | AF38: ='P&L Mensal - Anualizado'!BK31 -> -1816414.2 | AG38: =AD38/X38-1 -> -0.35503237 | AH38: =AE38/Y38-1 -> -0.51891462 | AI38: =AF38/Z38-1 -> -0.48617568
B39: MG INTERMEDIAÇÃO LIQ | C39: ='P&L Mensal - Anualizado'!B34 -> 2778303 | D39: ='P&L Mensal - Anualizado'!E34 -> 8054207 | E39: =D39+C39 -> 10832510 | F39: ='P&L Mensal - Anualizado'!M34 -> 3061028.7 | G39: ='P&L Mensal - Anualizado'!P34 -> 10111463 | H39: =G39+F39 -> 13172492 | I39: =F39/C39-1 -> 0.10176202 | J39: =G39/D39-1 -> 0.25542624 | K39: =H39/E39-1 -> 0.21601471 | L39: ='P&L Mensal - Anualizado'!X34 -> 2242918.4 | M39: ='P&L Mensal - Anualizado'!AA34 -> 14600600 | N39: =M39+L39 -> 16843518 | O39: =L39/F39-1 -> -0.26726646 | P39: =M39/G39-1 -> 0.44396514 | Q39: =N39/H39-1 -> 0.27868886 | R39: ='P&L Mensal - Anualizado'!AI34 -> 2475736.5 | S39: ='P&L Mensal - Anualizado'!AL34 -> 13593595 | T39: =S39+R39 -> 16069332 | U39: =R39/L39-1 -> 0.1038014 | V39: =S39/M39-1 -> -0.068970073 | W39: =T39/N39-1 -> -0.04596346 | X39: ='P&L Mensal - Anualizado'!AT34 -> 2085685.4 | Y39: ='P&L Mensal - Anualizado'!AW34 -> 17805359 | Z39: =Y39+X39 -> 19891044 | AA39: =X39/R39-1 -> -0.15754951 | AB39: =Y39/S39-1 -> 0.3098344 | AC39: =Z39/T39-1 -> 0.23782647 | AD39: ='P&L Mensal - Anualizado'!BE34 -> 2184663.3 | AE39: ='P&L Mensal - Anualizado'!BH34 -> 14974362 | AF39: ='P&L Mensal - Anualizado'!BK34 -> 17159026 | AG39: =AD39/X39-1 -> 0.047455818 | AH39: =AE39/Y39-1 -> -0.15899687 | AI39: =AF39/Z39-1 -> -0.13734917
B40: Despesas Administrativas | C40: ='P&L Mensal - Anualizado'!B35+'P&L Mensal - Anualizado'!B38 -> -1088774.4 | D40: ='P&L Mensal - Anualizado'!E35+'P&L Mensal - Anualizado'!E38 -> -3729180.6 | E40: =D40+C40 -> -4817955 | F40: ='P&L Mensal - Anualizado'!M35+'P&L Mensal - Anualizado'!M38 -> -1106026.8 | G40: ='P&L Mensal - Anualizado'!P35+'P&L Mensal - Anualizado'!P38 -> -4157786.5 | H40: =G40+F40 -> -5263813.3 | I40: =F40/C40-1 -> 0.015845722 | J40: =G40/D40-1 -> 0.11493299 | K40: =H40/E40-1 -> 0.092540982 | L40: ='P&L Mensal - Anualizado'!X35+'P&L Mensal - Anualizado'!X38 -> -1000224.8 | M40: ='P&L Mensal - Anualizado'!AA35+'P&L Mensal - Anualizado'!AA38 -> -3635830.5 | N40: =M40+L40 -> -4636055.3 | O40: =L40/F40-1 -> -0.095659553 | P40: =M40/G40-1 -> -0.12553699 | Q40: =N40/H40-1 -> -0.11925918 | R40: ='P&L Mensal - Anualizado'!AI35+'P&L Mensal - Anualizado'!AI38 -> -989834.41 | S40: ='P&L Mensal - Anualizado'!AL35+'P&L Mensal - Anualizado'!AL38 -> -4316176.6 | T40: =S40+R40 -> -5306011 | U40: =R40/L40-1 -> -0.010388057 | V40: =S40/M40-1 -> 0.18712263 | W40: =T40/N40-1 -> 0.14450987 | X40: ='P&L Mensal - Anualizado'!AT35+'P&L Mensal - Anualizado'!AT38 -> -973320.38 | Y40: ='P&L Mensal - Anualizado'!AW35+'P&L Mensal - Anualizado'!AW38 -> -4244167.1 | Z40: =Y40+X40 -> -5217487.5 | AA40: =X40/R40-1 -> -0.016683629 | AB40: =Y40/S40-1 -> -0.016683629 | AC40: =Z40/T40-1 -> -0.016683629 | AD40: ='P&L Mensal - Anualizado'!BE35+'P&L Mensal - Anualizado'!BE38 -> -923210.49 | AE40: ='P&L Mensal - Anualizado'!BH35+'P&L Mensal - Anualizado'!BH38 -> -4032126.2 | AF40: ='P&L Mensal - Anualizado'!BK35+'P&L Mensal - Anualizado'!BK38 -> -4955336.7 | AG40: =AD40/X40-1 -> -0.051483443 | AH40: =AE40/Y40-1 -> -0.049960536 | AI40: =AF40/Z40-1 -> -0.050244634
B41: Impostos Diretos | C41: ='P&L Mensal - Anualizado'!B29 -> -182166.93 | D41: ='P&L Mensal - Anualizado'!E29 -> -395690.12 | E41: =D41+C41 -> -577857.05 | F41: ='P&L Mensal - Anualizado'!M29 -> -175268.7 | G41: ='P&L Mensal - Anualizado'!P29 -> -692764.18 | H41: =G41+F41 -> -868032.88 | I41: =F41/C41-1 -> -0.037867629 | J41: =G41/D41-1 -> 0.75077452 | K41: =H41/E41-1 -> 0.5021585 | L41: ='P&L Mensal - Anualizado'!X29 -> -220529.89 | M41: ='P&L Mensal - Anualizado'!AA29 -> -871661.11 | N41: =M41+L41 -> -1092191 | O41: =L41/F41-1 -> 0.25823889 | P41: =M41/G41-1 -> 0.2582364 | Q41: =N41/H41-1 -> 0.2582369 | R41: ='P&L Mensal - Anualizado'!AI29 -> -171495.89 | S41: ='P&L Mensal - Anualizado'!AL29 -> -888547.03 | T41: =S41+R41 -> -1060042.9 | U41: =R41/L41-1 -> -0.22234629 | V41: =S41/M41-1 -> 0.01937212 | W41: =T41/N41-1 -> -0.029434485 | X41: ='P&L Mensal - Anualizado'!AT29 -> -313022.82 | Y41: ='P&L Mensal - Anualizado'!AW29 -> -1109808.2 | Z41: =Y41+X41 -> -1422831 | AA41: =X41/R41-1 -> 0.82524972 | AB41: =Y41/S41-1 -> 0.24901458 | AC41: =Z41/T41-1 -> 0.34223907 | AD41: ='P&L Mensal - Anualizado'!BE29 -> -323969.33 | AE41: ='P&L Mensal - Anualizado'!BH29 -> -1148618.5 | AF41: ='P&L Mensal - Anualizado'!BK29 -> -1472587.9 | AG41: =AD41/X41-1 -> 0.034970302 | AH41: =AE41/Y41-1 -> 0.034970302 | AI41: =AF41/Z41-1 -> 0.034970302
B42: Comissão | C42: ='P&L Mensal - Anualizado'!B36 -> -37516.142 | D42: ='P&L Mensal - Anualizado'!E36 -> -133011.78 | E42: =D42+C42 -> -170527.92 | F42: ='P&L Mensal - Anualizado'!M36 -> -223720.53 | G42: ='P&L Mensal - Anualizado'!P36 -> -793190.98 | H42: =G42+F42 -> -1016911.5 | I42: =F42/C42-1 -> 4.9633139 | J42: =G42/D42-1 -> 4.9633139 | K42: =H42/E42-1 -> 4.9633139 | L42: ='P&L Mensal - Anualizado'!X36 -> -40765.595 | M42: ='P&L Mensal - Anualizado'!AA36 -> -144532.27 | N42: =M42+L42 -> -185297.86 | O42: =L42/F42-1 -> -0.8177834 | P42: =M42/G42-1 -> -0.81778378 | Q42: =N42/H42-1 -> -0.81778369 | R42: ='P&L Mensal - Anualizado'!AI36 -> -91815.924 | S42: ='P&L Mensal - Anualizado'!AL36 -> -325529.18 | T42: =S42+R42 -> -417345.11 | U42: =R42/L42-1 -> 1.2522896 | V42: =S42/M42-1 -> 1.2522942 | W42: =T42/N42-1 -> 1.2522932 | X42: ='P&L Mensal - Anualizado'!AT36 -> -35594.348 | Y42: ='P&L Mensal - Anualizado'!AW36 -> -126198.14 | Z42: =Y42+X42 -> -161792.49 | AA42: =X42/R42-1 -> -0.61232925 | AB42: =Y42/S42-1 -> -0.61232925 | AC42: =Z42/T42-1 -> -0.61232925 | AD42: ='P&L Mensal - Anualizado'!BE36 -> 16837.295 | AE42: ='P&L Mensal - Anualizado'!BH36 -> 59695.865 | AF42: ='P&L Mensal - Anualizado'!BK36 -> 76533.16 | AG42: =AD42/X42-1 -> -1.4730328 | AH42: =AE42/Y42-1 -> -1.4730328 | AI42: =AF42/Z42-1 -> -1.4730328
B43: Amortização | C43: ='P&L Mensal - Anualizado'!B39 -> -98141.795 | D43: ='P&L Mensal - Anualizado'!E39 -> -349715.66 | E43: =D43+C43 -> -447857.46 | F43: ='P&L Mensal - Anualizado'!M39 -> -95397.185 | G43: ='P&L Mensal - Anualizado'!P39 -> -338226.38 | H43: =G43+F43 -> -433623.57 | I43: =F43/C43-1 -> -0.027965761 | J43: =G43/D43-1 -> -0.032853204 | K43: =H43/E43-1 -> -0.031782188 | L43: ='P&L Mensal - Anualizado'!X39 -> -93401.924 | M43: ='P&L Mensal - Anualizado'!AA39 -> -331152.28 | N43: =M43+L43 -> -424554.2 | O43: =L43/F43-1 -> -0.020915307 | P43: =M43/G43-1 -> -0.020915307 | Q43: =N43/H43-1 -> -0.020915307 | R43: ='P&L Mensal - Anualizado'!AI39 -> -68173.244 | S43: ='P&L Mensal - Anualizado'!AL39 -> -241705.14 | T43: =S43+R43 -> -309878.38 | U43: =R43/L43-1 -> -0.27010879 | V43: =S43/M43-1 -> -0.27010879 | W43: =T43/N43-1 -> -0.27010879 | X43: ='P&L Mensal - Anualizado'!AT39 -> -80103.962 | Y43: ='P&L Mensal - Anualizado'!AW39 -> -284004.96 | Z43: =Y43+X43 -> -364108.92 | AA43: =X43/R43-1 -> 0.17500588 | AB43: =Y43/S43-1 -> 0.17500588 | AC43: =Z43/T43-1 -> 0.17500588 | AD43: ='P&L Mensal - Anualizado'!BE39 -> -73558.008 | AE43: ='P&L Mensal - Anualizado'!BH39 -> -260796.57 | AF43: ='P&L Mensal - Anualizado'!BK39 -> -334354.58 | AG43: =AD43/X43-1 -> -0.08171824 | AH43: =AE43/Y43-1 -> -0.08171824 | AI43: =AF43/Z43-1 -> -0.08171824
B44: RESULTADO ANTES DO IMPOSTO | C44: ='P&L Mensal - Anualizado'!B40 -> 1553870.6 | D44: ='P&L Mensal - Anualizado'!E40 -> 3842298.9 | E44: =D44+C44 -> 5396169.6 | F44: ='P&L Mensal - Anualizado'!M40 -> 1635884.2 | G44: ='P&L Mensal - Anualizado'!P40 -> 4822258.9 | H44: =G44+F44 -> 6458143.1 | I44: =F44/C44-1 -> 0.052780151 | J44: =G44/D44-1 -> 0.25504522 | K44: =H44/E44-1 -> 0.19680136 | L44: ='P&L Mensal - Anualizado'!X40 -> 1108526.1 | M44: ='P&L Mensal - Anualizado'!AA40 -> 10489085 | N44: =M44+L44 -> 11597611 | O44: =L44/F44-1 -> -0.32236884 | P44: =M44/G44-1 -> 1.1751393 | Q44: =N44/H44-1 -> 0.79581199 | R44: ='P&L Mensal - Anualizado'!AI40 -> 1325912.9 | S44: ='P&L Mensal - Anualizado'!AL40 -> 8710184.4 | T44: =S44+R44 -> 10036097 | U44: =R44/L44-1 -> 0.19610437 | V44: =S44/M44-1 -> -0.16959538 | W44: =T44/N44-1 -> -0.13464097 | X44: ='P&L Mensal - Anualizado'!AT40 -> 996666.71 | Y44: ='P&L Mensal - Anualizado'!AW40 -> 13150989 | Z44: =Y44+X44 -> 14147655 | AA44: =X44/R44-1 -> -0.2483166 | AB44: =Y44/S44-1 -> 0.50984044 | AC44: =Z44/T44-1 -> 0.40967698 | AD44: ='P&L Mensal - Anualizado'!BE40 -> 1204732.1 | AE44: ='P&L Mensal - Anualizado'!BH40 -> 10741136 | AF44: ='P&L Mensal - Anualizado'!BK40 -> 11945868 | AG44: =AD44/X44-1 -> 0.20876125 | AH44: =AE44/Y44-1 -> -0.18324501 | AI44: =AF44/Z44-1 -> -0.15562916
B45: Impostos (IR/CSLL) | C45: ='P&L Mensal - Anualizado'!B41 -> -115374.99 | D45: ='P&L Mensal - Anualizado'!E41 -> -1463640.8 | E45: =D45+C45 -> -1579015.8 | F45: ='P&L Mensal - Anualizado'!M41 -> -544207.13 | G45: ='P&L Mensal - Anualizado'!P41 -> -1604213.6 | H45: =G45+F45 -> -2148420.8 | I45: =F45/C45-1 -> 3.7168553 | J45: =G45/D45-1 -> 0.096043264 | K45: =H45/E45-1 -> 0.36060753 | L45: ='P&L Mensal - Anualizado'!X41 -> -375153.56 | M45: ='P&L Mensal - Anualizado'!AA41 -> -3549774.4 | N45: =M45+L45 -> -3924927.9 | O45: =L45/F45-1 -> -0.31064196 | P45: =M45/G45-1 -> 1.2127816 | Q45: =N45/H45-1 -> 0.82688976 | R45: ='P&L Mensal - Anualizado'!AI41 -> -117342.31 | S45: ='P&L Mensal - Anualizado'!AL41 -> -770844.86 | T45: =S45+R45 -> -888187.17 | U45: =R45/L45-1 -> -0.68721526 | V45: =S45/M45-1 -> -0.7828468 | W45: =T45/N45-1 -> -0.77370612 | X45: ='P&L Mensal - Anualizado'!AT41 -> -340871.81 | Y45: ='P&L Mensal - Anualizado'!AW41 -> -4497793.7 | Z45: =Y45+X45 -> -4838665.5 | AA45: =X45/R45-1 -> 1.9049352 | AB45: =Y45/S45-1 -> 4.8348883 | AC45: =Z45/T45-1 -> 4.4477994 | AD45: ='P&L Mensal - Anualizado'!BE41 -> -327605.81 | AE45: ='P&L Mensal - Anualizado'!BH41 -> -2920791.9 | AF45: ='P&L Mensal - Anualizado'!BK41 -> -3248397.7 | AG45: =AD45/X45-1 -> -0.038917842 | AH45: =AE45/Y45-1 -> -0.35061675 | AI45: =AF45/Z45-1 -> -0.32865834
B46: RESULTADO CONTÁBIL | C46: ='P&L Mensal - Anualizado'!B42 -> 1438495.7 | D46: ='P&L Mensal - Anualizado'!E42 -> 2378658.1 | E46: =D46+C46 -> 3817153.8 | F46: ='P&L Mensal - Anualizado'!M42 -> 1091677 | G46: ='P&L Mensal - Anualizado'!P42 -> 3218045.3 | H46: =G46+F46 -> 4309722.3 | I46: =F46/C46-1 -> -0.24109813 | J46: =G46/D46-1 -> 0.35288263 | K46: =H46/E46-1 -> 0.12904079 | L46: ='P&L Mensal - Anualizado'!X42 -> 733372.52 | M46: ='P&L Mensal - Anualizado'!AA42 -> 6939310.4 | N46: =M46+L46 -> 7672682.9 | O46: =L46/F46-1 -> -0.32821476 | P46: =M46/G46-1 -> 1.1563744 | Q46: =N46/H46-1 -> 0.78031954 | R46: ='P&L Mensal - Anualizado'!AI42 -> 1208570.6 | S46: ='P&L Mensal - Anualizado'!AL42 -> 7939339.5 | T46: =S46+R46 -> 9147910.1 | U46: =R46/L46-1 -> 0.64796272 | V46: =S46/M46-1 -> 0.14411074 | W46: =T46/N46-1 -> 0.19227006 | X46: ='P&L Mensal - Anualizado'!AT42 -> 655794.9 | Y46: ='P&L Mensal - Anualizado'!AW42 -> 8653194.9 | Z46: =Y46+X46 -> 9308989.8 | AA46: =X46/R46-1 -> -0.45737973 | AB46: =Y46/S46-1 -> 0.0899137 | AC46: =Z46/T46-1 -> 0.017608362 | AD46: ='P&L Mensal - Anualizado'!BE42 -> 877126.28 | AE46: ='P&L Mensal - Anualizado'!BH42 -> 7820343.6 | AF46: ='P&L Mensal - Anualizado'!BK42 -> 8697469.9 | AG46: =AD46/X46-1 -> 0.33750092 | AH46: =AE46/Y46-1 -> -0.096247833 | AI46: =AF46/Z46-1 -> -0.065691325
C48: Realizado x Orçado por linha principal
C49: 46023 | I49: 46054 | O49: 46082 | U49: 46113 | AA49: 46143 | AG49: =L7 -> 46174
C50: Consignado | E50: Imobiliário | G50: Total | I50: Consignado | K50: Imobiliário | M50: Total | O50: Consignado | Q50: Imobiliário | S50: Total | U50: Consignado | W50: Imobiliário | Y50: Total | AA50: Consignado | AC50: Imobiliário | AE50: Total | AG50: Consignado | AI50: Imobiliário | AK50: Total
C51: Realizado | D51: Orçado | E51: Realizado | F51: Orçado | G51: Realizado | H51: Orçado | I51: Realizado | J51: Orçado | K51: Realizado | L51: Orçado | M51: Realizado | N51: Orçado | O51: Realizado | P51: Orçado | Q51: Realizado | R51: Orçado | S51: Realizado | T51: Orçado | U51: Realizado | V51: Orçado | W51: Realizado | X51: Orçado | Y51: Realizado | Z51: Orçado | AA51: Realizado | AB51: Orçado | AC51: Realizado | AD51: Orçado | AE51: Realizado | AF51: Orçado | AG51: Realizado | AH51: Orçado | AI51: Realizado | AJ51: Orçado | AK51: Realizado | AL51: Orçado
B52: Receitas | C52: ='P&L Mensal - Anualizado'!B5 -> 7802027.9 | D52: ='P&L Mensal - Anualizado'!C5 -> 7701714.3 | E52: ='P&L Mensal - Anualizado'!E5 -> 23859887 | F52: ='P&L Mensal - Anualizado'!F5 -> 24532548 | G52: ='P&L Mensal - Anualizado'!H5 -> 31661915 | H52: ='P&L Mensal - Anualizado'!I5 -> 32234263 | I52: ='P&L Mensal - Anualizado'!M5 -> 7098724.1 | J52: ='P&L Mensal - Anualizado'!N5 -> 6991516.2 | K52: ='P&L Mensal - Anualizado'!P5 -> 23773864 | L52: ='P&L Mensal - Anualizado'!Q5 -> 23417973 | M52: ='P&L Mensal - Anualizado'!S5 -> 30872588 | N52: ='P&L Mensal - Anualizado'!T5 -> 30409489 | O52: ='P&L Mensal - Anualizado'!X5 -> 7877352.9 | P52: ='P&L Mensal - Anualizado'!Y5 -> 7759392.7 | Q52: ='P&L Mensal - Anualizado'!AA5 -> 33774613 | R52: ='P&L Mensal - Anualizado'!AB5 -> 29464374 | S52: ='P&L Mensal - Anualizado'!AD5 -> 41651965 | T52: ='P&L Mensal - Anualizado'!AE5 -> 37223767 | U52: ='P&L Mensal - Anualizado'!AI5 -> 7513769.7 | V52: ='P&L Mensal - Anualizado'!AJ5 -> 7551512 | W52: ='P&L Mensal - Anualizado'!AL5 -> 34391853 | X52: ='P&L Mensal - Anualizado'!AM5 -> 27827307 | Y52: ='P&L Mensal - Anualizado'!AO5 -> 41905623 | Z52: ='P&L Mensal - Anualizado'!AP5 -> 35378819 | AA52: ='P&L Mensal - Anualizado'!AT5 -> 7585530.4 | AB52: ='P&L Mensal - Anualizado'!AU5 -> 7837760.5 | AC52: ='P&L Mensal - Anualizado'!AW5 -> 37483958 | AD52: ='P&L Mensal - Anualizado'!AX5 -> 26639239 | AE52: ='P&L Mensal - Anualizado'!AZ5 -> 45069488 | AF52: ='P&L Mensal - Anualizado'!BA5 -> 34477000 | AG52: ='P&L Mensal - Anualizado'!BE5 -> 7768119.1 | AH52: ='P&L Mensal - Anualizado'!BF5 -> 7626952.8 | AI52: ='P&L Mensal - Anualizado'!BH5 -> 34678251 | AJ52: ='P&L Mensal - Anualizado'!BI5 -> 29052906 | AK52: ='P&L Mensal - Anualizado'!BK5 -> 42446371 | AL52: ='P&L Mensal - Anualizado'!BL5 -> 36679859
B53: Despesas de Originação | C53: ='P&L Mensal - Anualizado'!B21 -> -4115579.3 | D53: ='P&L Mensal - Anualizado'!C21 -> -4007372 | E53: ='P&L Mensal - Anualizado'!E21 -> -13893293 | F53: ='P&L Mensal - Anualizado'!F21 -> -13901145 | G53: ='P&L Mensal - Anualizado'!H21 -> -18008872 | H53: ='P&L Mensal - Anualizado'!I21 -> -17908517 | I53: ='P&L Mensal - Anualizado'!M21 -> -3458538.1 | J53: ='P&L Mensal - Anualizado'!N21 -> -3324628.9 | K53: ='P&L Mensal - Anualizado'!P21 -> -11194223 | L53: ='P&L Mensal - Anualizado'!Q21 -> -12699380 | M53: ='P&L Mensal - Anualizado'!S21 -> -14652761 | N53: ='P&L Mensal - Anualizado'!T21 -> -16024009 | O53: ='P&L Mensal - Anualizado'!X21 -> -4803644.1 | P53: ='P&L Mensal - Anualizado'!Y21 -> -4620516.9 | Q53: ='P&L Mensal - Anualizado'!AA21 -> -17862654 | R53: ='P&L Mensal - Anualizado'!AB21 -> -15301310 | S53: ='P&L Mensal - Anualizado'!AD21 -> -22666298 | T53: ='P&L Mensal - Anualizado'!AE21 -> -19921827 | U53: ='P&L Mensal - Anualizado'!AI21 -> -4383516.3 | V53: ='P&L Mensal - Anualizado'!AJ21 -> -4409897.3 | W53: ='P&L Mensal - Anualizado'!AL21 -> -17657422 | X53: ='P&L Mensal - Anualizado'!AM21 -> -13769320 | Y53: ='P&L Mensal - Anualizado'!AO21 -> -22040938 | Z53: ='P&L Mensal - Anualizado'!AP21 -> -18179217 | AA53: ='P&L Mensal - Anualizado'!AT21 -> -4480613.7 | AB53: ='P&L Mensal - Anualizado'!AU21 -> -4475939 | AC53: ='P&L Mensal - Anualizado'!AW21 -> -15739911 | AD53: ='P&L Mensal - Anualizado'!AX21 -> -13995733 | AE53: ='P&L Mensal - Anualizado'!AZ21 -> -20220525 | AF53: ='P&L Mensal - Anualizado'!BA21 -> -18471672 | AG53: ='P&L Mensal - Anualizado'!BE21 -> -4804004.9 | AH53: ='P&L Mensal - Anualizado'!BF21 -> -4848789.1 | AI53: ='P&L Mensal - Anualizado'!BH21 -> -17194338 | AJ53: ='P&L Mensal - Anualizado'!BI21 -> -14559699 | AK53: ='P&L Mensal - Anualizado'!BK21 -> -21998343 | AL53: ='P&L Mensal - Anualizado'!BL21 -> -19408488
B54: Margem de Intermediação | C54: ='P&L Mensal - Anualizado'!B30 -> 3504281.6 | D54: ='P&L Mensal - Anualizado'!C30 -> 3559264.4 | E54: ='P&L Mensal - Anualizado'!E30 -> 9570904.2 | F54: ='P&L Mensal - Anualizado'!F30 -> 10152489 | G54: ='P&L Mensal - Anualizado'!H30 -> 13075186 | H54: ='P&L Mensal - Anualizado'!I30 -> 13711754 | I54: ='P&L Mensal - Anualizado'!M30 -> 3464917.2 | J54: ='P&L Mensal - Anualizado'!N30 -> 3528656.9 | K54: ='P&L Mensal - Anualizado'!P30 -> 11886877 | L54: ='P&L Mensal - Anualizado'!Q30 -> 10228503 | M54: ='P&L Mensal - Anualizado'!S30 -> 15351794 | N54: ='P&L Mensal - Anualizado'!T30 -> 13757160 | O54: ='P&L Mensal - Anualizado'!X30 -> 2853178.9 | P54: ='P&L Mensal - Anualizado'!Y30 -> 2969870 | Q54: ='P&L Mensal - Anualizado'!AA30 -> 15040297 | R54: ='P&L Mensal - Anualizado'!AB30 -> 13563862 | S54: ='P&L Mensal - Anualizado'!AD30 -> 17893476 | T54: ='P&L Mensal - Anualizado'!AE30 -> 16533732 | U54: ='P&L Mensal - Anualizado'!AI30 -> 2958757.4 | V54: ='P&L Mensal - Anualizado'!AJ30 -> 2973212.1 | W54: ='P&L Mensal - Anualizado'!AL30 -> 15845885 | X54: ='P&L Mensal - Anualizado'!AM30 -> 13460923 | Y54: ='P&L Mensal - Anualizado'!AO30 -> 18804642 | Z54: ='P&L Mensal - Anualizado'!AP30 -> 16434135 | AA54: ='P&L Mensal - Anualizado'!AT30 -> 2791893.9 | AB54: ='P&L Mensal - Anualizado'!AU30 -> 3205174.7 | AC54: ='P&L Mensal - Anualizado'!AW30 -> 20634238 | AD54: ='P&L Mensal - Anualizado'!AX30 -> 12088122 | AE54: ='P&L Mensal - Anualizado'!AZ30 -> 23426132 | AF54: ='P&L Mensal - Anualizado'!BA30 -> 15293297 | AG54: ='P&L Mensal - Anualizado'!BE30 -> 2640144.9 | AH54: ='P&L Mensal - Anualizado'!BF30 -> 2608153.5 | AI54: ='P&L Mensal - Anualizado'!BH30 -> 16335295 | AJ54: ='P&L Mensal - Anualizado'!BI30 -> 13890443 | AK54: ='P&L Mensal - Anualizado'!BK30 -> 18975440 | AL54: ='P&L Mensal - Anualizado'!BL30 -> 16498597
B55: Provisões | C55: ='P&L Mensal - Anualizado'!B31 -> -725978.64 | D55: ='P&L Mensal - Anualizado'!C31 -> -724707 | E55: ='P&L Mensal - Anualizado'!E31 -> -1516697.2 | F55: ='P&L Mensal - Anualizado'!F31 -> -1528471.5 | G55: ='P&L Mensal - Anualizado'!H31 -> -2242675.9 | H55: ='P&L Mensal - Anualizado'!I31 -> -2253178.5 | I55: ='P&L Mensal - Anualizado'!M31 -> -403888.51 | J55: ='P&L Mensal - Anualizado'!N31 -> -555191.52 | K55: ='P&L Mensal - Anualizado'!P31 -> -1775414.1 | L55: ='P&L Mensal - Anualizado'!Q31 -> -916664.33 | M55: ='P&L Mensal - Anualizado'!S31 -> -2179302.6 | N55: ='P&L Mensal - Anualizado'!T31 -> -1471855.9 | O55: ='P&L Mensal - Anualizado'!X31 -> -610260.52 | P55: ='P&L Mensal - Anualizado'!Y31 -> -577819.12 | Q55: ='P&L Mensal - Anualizado'!AA31 -> -439697.65 | R55: ='P&L Mensal - Anualizado'!AB31 -> -1292046.2 | S55: ='P&L Mensal - Anualizado'!AD31 -> -1049958.2 | T55: ='P&L Mensal - Anualizado'!AE31 -> -1869865.4 | U55: ='P&L Mensal - Anualizado'!AI31 -> -483020.98 | V55: ='P&L Mensal - Anualizado'!AJ31 -> -572342.1 | W55: ='P&L Mensal - Anualizado'!AL31 -> -2252289.5 | X55: ='P&L Mensal - Anualizado'!AM31 -> -1105001.8 | Y55: ='P&L Mensal - Anualizado'!AO31 -> -2735310.5 | Z55: ='P&L Mensal - Anualizado'!AP31 -> -1677343.9 | AA55: ='P&L Mensal - Anualizado'!AT31 -> -706208.48 | AB55: ='P&L Mensal - Anualizado'!AU31 -> -579408.77 | AC55: ='P&L Mensal - Anualizado'!AW31 -> -2828879.5 | AD55: ='P&L Mensal - Anualizado'!AX31 -> -1110416.4 | AE55: ='P&L Mensal - Anualizado'!AZ31 -> -3535088 | AF55: ='P&L Mensal - Anualizado'!BA31 -> -1689825.2 | AG55: ='P&L Mensal - Anualizado'!BE31 -> -455481.61 | AH55: ='P&L Mensal - Anualizado'!BF31 -> -569041.42 | AI55: ='P&L Mensal - Anualizado'!BH31 -> -1360932.6 | AJ55: ='P&L Mensal - Anualizado'!BI31 -> -1629488.8 | AK55: ='P&L Mensal - Anualizado'!BK31 -> -1816414.2 | AL55: ='P&L Mensal - Anualizado'!BL31 -> -2198530.2
B56: MG INTERMEDIAÇÃO LIQ | C56: ='P&L Mensal - Anualizado'!B34 -> 2778303 | D56: ='P&L Mensal - Anualizado'!C34 -> 2834557.4 | E56: ='P&L Mensal - Anualizado'!E34 -> 8054207 | F56: ='P&L Mensal - Anualizado'!F34 -> 8624017.8 | G56: ='P&L Mensal - Anualizado'!H34 -> 10832510 | H56: ='P&L Mensal - Anualizado'!I34 -> 11458575 | I56: ='P&L Mensal - Anualizado'!M34 -> 3061028.7 | J56: ='P&L Mensal - Anualizado'!N34 -> 2973465.4 | K56: ='P&L Mensal - Anualizado'!P34 -> 10111463 | L56: ='P&L Mensal - Anualizado'!Q34 -> 9311839.1 | M56: ='P&L Mensal - Anualizado'!S34 -> 13172492 | N56: ='P&L Mensal - Anualizado'!T34 -> 12285305 | O56: ='P&L Mensal - Anualizado'!X34 -> 2242918.4 | P56: ='P&L Mensal - Anualizado'!Y34 -> 2392050.8 | Q56: ='P&L Mensal - Anualizado'!AA34 -> 14600600 | R56: ='P&L Mensal - Anualizado'!AB34 -> 12271816 | S56: ='P&L Mensal - Anualizado'!AD34 -> 16843518 | T56: ='P&L Mensal - Anualizado'!AE34 -> 14663866 | U56: ='P&L Mensal - Anualizado'!AI34 -> 2475736.5 | V56: ='P&L Mensal - Anualizado'!AJ34 -> 2400870 | W56: ='P&L Mensal - Anualizado'!AL34 -> 13593595 | X56: ='P&L Mensal - Anualizado'!AM34 -> 12355922 | Y56: ='P&L Mensal - Anualizado'!AO34 -> 16069332 | Z56: ='P&L Mensal - Anualizado'!AP34 -> 14756792 | AA56: ='P&L Mensal - Anualizado'!AT34 -> 2085685.4 | AB56: ='P&L Mensal - Anualizado'!AU34 -> 2625765.9 | AC56: ='P&L Mensal - Anualizado'!AW34 -> 17805359 | AD56: ='P&L Mensal - Anualizado'!AX34 -> 10977706 | AE56: ='P&L Mensal - Anualizado'!AZ34 -> 19891044 | AF56: ='P&L Mensal - Anualizado'!BA34 -> 13603472 | AG56: ='P&L Mensal - Anualizado'!BE34 -> 2184663.3 | AH56: ='P&L Mensal - Anualizado'!BF34 -> 2039112.1 | AI56: ='P&L Mensal - Anualizado'!BH34 -> 14974362 | AJ56: ='P&L Mensal - Anualizado'!BI34 -> 12260955 | AK56: ='P&L Mensal - Anualizado'!BK34 -> 17159026 | AL56: ='P&L Mensal - Anualizado'!BL34 -> 14300067
B57: Despesas Administrativas | C57: ='P&L Mensal - Anualizado'!B35+'P&L Mensal - Anualizado'!B38 -> -1088774.4 | D57: ='P&L Mensal - Anualizado'!C35+'P&L Mensal - Anualizado'!C38 -> -1151833.3 | E57: ='P&L Mensal - Anualizado'!E35+'P&L Mensal - Anualizado'!E38 -> -3729180.6 | F57: ='P&L Mensal - Anualizado'!F35+'P&L Mensal - Anualizado'!F38 -> -3950637 | G57: ='P&L Mensal - Anualizado'!H35+'P&L Mensal - Anualizado'!H38 -> -4817955 | H57: ='P&L Mensal - Anualizado'!I35+'P&L Mensal - Anualizado'!I38 -> -5102470.3 | I57: ='P&L Mensal - Anualizado'!M35+'P&L Mensal - Anualizado'!M38 -> -1106026.8 | J57: ='P&L Mensal - Anualizado'!N35+'P&L Mensal - Anualizado'!N38 -> -951971.65 | K57: ='P&L Mensal - Anualizado'!P35+'P&L Mensal - Anualizado'!P38 -> -4157786.5 | L57: ='P&L Mensal - Anualizado'!Q35+'P&L Mensal - Anualizado'!Q38 -> -4089001.5 | M57: ='P&L Mensal - Anualizado'!S35+'P&L Mensal - Anualizado'!S38 -> -5263813.3 | N57: ='P&L Mensal - Anualizado'!T35+'P&L Mensal - Anualizado'!T38 -> -5040973.2 | O57: ='P&L Mensal - Anualizado'!X35+'P&L Mensal - Anualizado'!X38 -> -1000224.8 | P57: ='P&L Mensal - Anualizado'!Y35+'P&L Mensal - Anualizado'!Y38 -> -1062689.1 | Q57: ='P&L Mensal - Anualizado'!AA35+'P&L Mensal - Anualizado'!AA38 -> -3635830.5 | R57: ='P&L Mensal - Anualizado'!AB35+'P&L Mensal - Anualizado'!AB38 -> -4436094.7 | S57: ='P&L Mensal - Anualizado'!AD35+'P&L Mensal - Anualizado'!AD38 -> -4636055.3 | T57: ='P&L Mensal - Anualizado'!AE35+'P&L Mensal - Anualizado'!AE38 -> -5498783.8 | U57: ='P&L Mensal - Anualizado'!AI35+'P&L Mensal - Anualizado'!AI38 -> -989834.41 | V57: ='P&L Mensal - Anualizado'!AJ35+'P&L Mensal - Anualizado'!AJ38 -> -974689.09 | W57: ='P&L Mensal - Anualizado'!AL35+'P&L Mensal - Anualizado'!AL38 -> -4316176.6 | X57: ='P&L Mensal - Anualizado'!AM35+'P&L Mensal - Anualizado'!AM38 -> -4124094.7 | Y57: ='P&L Mensal - Anualizado'!AO35+'P&L Mensal - Anualizado'!AO38 -> -5306011 | Z57: ='P&L Mensal - Anualizado'!AP35+'P&L Mensal - Anualizado'!AP38 -> -5098783.8 | AA57: ='P&L Mensal - Anualizado'!AT35+'P&L Mensal - Anualizado'!AT38 -> -973320.38 | AB57: ='P&L Mensal - Anualizado'!AU35+'P&L Mensal - Anualizado'!AU38 -> -974689.09 | AC57: ='P&L Mensal - Anualizado'!AW35+'P&L Mensal - Anualizado'!AW38 -> -4244167.1 | AD57: ='P&L Mensal - Anualizado'!AX35+'P&L Mensal - Anualizado'!AX38 -> -4124094.7 | AE57: ='P&L Mensal - Anualizado'!AZ35+'P&L Mensal - Anualizado'!AZ38 -> -5217487.5 | AF57: ='P&L Mensal - Anualizado'!BA35+'P&L Mensal - Anualizado'!BA38 -> -5098783.8 | AG57: ='P&L Mensal - Anualizado'!BE35+'P&L Mensal - Anualizado'!BE38 -> -923210.49 | AH57: ='P&L Mensal - Anualizado'!BF35+'P&L Mensal - Anualizado'!BF38 -> -998843.13 | AI57: ='P&L Mensal - Anualizado'!BH35+'P&L Mensal - Anualizado'!BH38 -> -4032126.2 | AJ57: ='P&L Mensal - Anualizado'!BI35+'P&L Mensal - Anualizado'!BI38 -> -4255111.3 | AK57: ='P&L Mensal - Anualizado'!BK35+'P&L Mensal - Anualizado'!BK38 -> -4955336.7 | AL57: ='P&L Mensal - Anualizado'!BL35+'P&L Mensal - Anualizado'!BL38 -> -5253954.4
B58: Impostos Diretos | C58: ='P&L Mensal - Anualizado'!B29 -> -182166.93 | D58: ='P&L Mensal - Anualizado'!C29 -> -135078 | E58: ='P&L Mensal - Anualizado'!E29 -> -395690.12 | F58: ='P&L Mensal - Anualizado'!F29 -> -478914 | G58: ='P&L Mensal - Anualizado'!H29 -> -577857.05 | H58: ='P&L Mensal - Anualizado'!I29 -> -613992 | I58: ='P&L Mensal - Anualizado'!M29 -> -175268.7 | J58: ='P&L Mensal - Anualizado'!N29 -> -138230.37 | K58: ='P&L Mensal - Anualizado'!P29 -> -692764.18 | L58: ='P&L Mensal - Anualizado'!Q29 -> -490089.49 | M58: ='P&L Mensal - Anualizado'!S29 -> -868032.88 | N58: ='P&L Mensal - Anualizado'!T29 -> -628319.86 | O58: ='P&L Mensal - Anualizado'!X29 -> -220529.89 | P58: ='P&L Mensal - Anualizado'!Y29 -> -169005.8 | Q58: ='P&L Mensal - Anualizado'!AA29 -> -871661.11 | R58: ='P&L Mensal - Anualizado'!AB29 -> -599202.39 | S58: ='P&L Mensal - Anualizado'!AD29 -> -1092191 | T58: ='P&L Mensal - Anualizado'!AE29 -> -768208.19 | U58: ='P&L Mensal - Anualizado'!AI29 -> -171495.89 | V58: ='P&L Mensal - Anualizado'!AJ29 -> -168402.62 | W58: ='P&L Mensal - Anualizado'!AL29 -> -888547.03 | X58: ='P&L Mensal - Anualizado'!AM29 -> -597063.83 | Y58: ='P&L Mensal - Anualizado'!AO29 -> -1060042.9 | Z58: ='P&L Mensal - Anualizado'!AP29 -> -765466.45 | AA58: ='P&L Mensal - Anualizado'!AT29 -> -313022.82 | AB58: ='P&L Mensal - Anualizado'!AU29 -> -156646.84 | AC58: ='P&L Mensal - Anualizado'!AW29 -> -1109808.2 | AD58: ='P&L Mensal - Anualizado'!AX29 -> -555384.26 | AE58: ='P&L Mensal - Anualizado'!AZ29 -> -1422831 | AF58: ='P&L Mensal - Anualizado'!BA29 -> -712031.11 | AG58: ='P&L Mensal - Anualizado'!BE29 -> -323969.33 | AH58: ='P&L Mensal - Anualizado'!BF29 -> -170010.17 | AI58: ='P&L Mensal - Anualizado'!BH29 -> -1148618.5 | AJ58: ='P&L Mensal - Anualizado'!BI29 -> -602763.35 | AK58: ='P&L Mensal - Anualizado'!BK29 -> -1472587.9 | AL58: ='P&L Mensal - Anualizado'!BL29 -> -772773.52
B59: Comissão | C59: ='P&L Mensal - Anualizado'!B36 -> -37516.142 | D59: ='P&L Mensal - Anualizado'!C36 -> 0 | E59: ='P&L Mensal - Anualizado'!E36 -> -133011.78 | F59: ='P&L Mensal - Anualizado'!F36 -> -180000 | G59: ='P&L Mensal - Anualizado'!H36 -> -170527.92 | H59: ='P&L Mensal - Anualizado'!I36 -> -180000 | I59: ='P&L Mensal - Anualizado'!M36 -> -223720.53 | J59: ='P&L Mensal - Anualizado'!N36 -> -42428.571 | K59: ='P&L Mensal - Anualizado'!P36 -> -793190.98 | L59: ='P&L Mensal - Anualizado'!Q36 -> -150428.57 | M59: ='P&L Mensal - Anualizado'!S36 -> -1016911.5 | N59: ='P&L Mensal - Anualizado'!T36 -> -192857.14 | O59: ='P&L Mensal - Anualizado'!X36 -> -40765.595 | P59: ='P&L Mensal - Anualizado'!Y36 -> 0 | Q59: ='P&L Mensal - Anualizado'!AA36 -> -144532.27 | R59: ='P&L Mensal - Anualizado'!AB36 -> -233766.23 | S59: ='P&L Mensal - Anualizado'!AD36 -> -185297.86 | T59: ='P&L Mensal - Anualizado'!AE36 -> -233766.23 | U59: ='P&L Mensal - Anualizado'!AI36 -> -91815.924 | V59: ='P&L Mensal - Anualizado'!AJ36 -> 0 | W59: ='P&L Mensal - Anualizado'!AL36 -> -325529.18 | X59: ='P&L Mensal - Anualizado'!AM36 -> -202207.79 | Y59: ='P&L Mensal - Anualizado'!AO36 -> -417345.11 | Z59: ='P&L Mensal - Anualizado'!AP36 -> -202207.79 | AA59: ='P&L Mensal - Anualizado'!AT36 -> -35594.348 | AB59: ='P&L Mensal - Anualizado'!AU36 -> 0 | AC59: ='P&L Mensal - Anualizado'!AW36 -> -126198.14 | AD59: ='P&L Mensal - Anualizado'!AX36 -> -209220.78 | AE59: ='P&L Mensal - Anualizado'!AZ36 -> -161792.49 | AF59: ='P&L Mensal - Anualizado'!BA36 -> -209220.78 | AG59: ='P&L Mensal - Anualizado'!BE36 -> 16837.295 | AH59: ='P&L Mensal - Anualizado'!BF36 -> -48857.143 | AI59: ='P&L Mensal - Anualizado'!BH36 -> 59695.865 | AJ59: ='P&L Mensal - Anualizado'!BI36 -> -173220.78 | AK59: ='P&L Mensal - Anualizado'!BK36 -> 76533.16 | AL59: ='P&L Mensal - Anualizado'!BL36 -> -222077.92
B60: Amortização | C60: ='P&L Mensal - Anualizado'!B39 -> -98141.795 | D60: ='P&L Mensal - Anualizado'!C39 -> -107178.79 | E60: ='P&L Mensal - Anualizado'!E39 -> -349715.66 | F60: ='P&L Mensal - Anualizado'!F39 -> -379997.52 | G60: ='P&L Mensal - Anualizado'!H39 -> -447857.46 | H60: ='P&L Mensal - Anualizado'!I39 -> -487176.31 | I60: ='P&L Mensal - Anualizado'!M39 -> -95397.185 | J60: ='P&L Mensal - Anualizado'!N39 -> -97517.009 | K60: ='P&L Mensal - Anualizado'!P39 -> -338226.38 | L60: ='P&L Mensal - Anualizado'!Q39 -> -345742.12 | M60: ='P&L Mensal - Anualizado'!S39 -> -433623.57 | N60: ='P&L Mensal - Anualizado'!T39 -> -443259.13 | O60: ='P&L Mensal - Anualizado'!X39 -> -93401.924 | P60: ='P&L Mensal - Anualizado'!Y39 -> -88082.166 | Q60: ='P&L Mensal - Anualizado'!AA39 -> -331152.28 | R60: ='P&L Mensal - Anualizado'!AB39 -> -312291.32 | S60: ='P&L Mensal - Anualizado'!AD39 -> -424554.2 | T60: ='P&L Mensal - Anualizado'!AE39 -> -400373.48 | U60: ='P&L Mensal - Anualizado'!AI39 -> -68173.244 | V60: ='P&L Mensal - Anualizado'!AJ39 -> -79650.623 | W60: ='P&L Mensal - Anualizado'!AL39 -> -241705.14 | X60: ='P&L Mensal - Anualizado'!AM39 -> -282397.66 | Y60: ='P&L Mensal - Anualizado'!AO39 -> -309878.38 | Z60: ='P&L Mensal - Anualizado'!AP39 -> -362048.29 | AA60: ='P&L Mensal - Anualizado'!AT39 -> -80103.962 | AB60: ='P&L Mensal - Anualizado'!AU39 -> -75611.866 | AC60: ='P&L Mensal - Anualizado'!AW39 -> -284004.96 | AD60: ='P&L Mensal - Anualizado'!AX39 -> -268078.43 | AE60: ='P&L Mensal - Anualizado'!AZ39 -> -364108.92 | AF60: ='P&L Mensal - Anualizado'!BA39 -> -343690.3 | AG60: ='P&L Mensal - Anualizado'!BE39 -> -73558.008 | AH60: ='P&L Mensal - Anualizado'!BF39 -> -73105.71 | AI60: ='P&L Mensal - Anualizado'!BH39 -> -260796.57 | AJ60: ='P&L Mensal - Anualizado'!BI39 -> -259192.97 | AK60: ='P&L Mensal - Anualizado'!BK39 -> -334354.58 | AL60: ='P&L Mensal - Anualizado'!BL39 -> -332298.68
B61: RESULTADO ANTES DO IMPOSTO | C61: ='P&L Mensal - Anualizado'!B40 -> 1553870.6 | D61: ='P&L Mensal - Anualizado'!C40 -> 1575545.3 | E61: ='P&L Mensal - Anualizado'!E40 -> 3842298.9 | F61: ='P&L Mensal - Anualizado'!F40 -> 4113383.2 | G61: ='P&L Mensal - Anualizado'!H40 -> 5396169.6 | H61: ='P&L Mensal - Anualizado'!I40 -> 5688928.6 | I61: ='P&L Mensal - Anualizado'!M40 -> 1635884.2 | J61: ='P&L Mensal - Anualizado'!N40 -> 1881548.2 | K61: ='P&L Mensal - Anualizado'!P40 -> 4822258.9 | L61: ='P&L Mensal - Anualizado'!Q40 -> 4726666.9 | M61: ='P&L Mensal - Anualizado'!S40 -> 6458143.1 | N61: ='P&L Mensal - Anualizado'!T40 -> 6608215.1 | O61: ='P&L Mensal - Anualizado'!X40 -> 1108526.1 | P61: ='P&L Mensal - Anualizado'!Y40 -> 1241279.6 | Q61: ='P&L Mensal - Anualizado'!AA40 -> 10489085 | R61: ='P&L Mensal - Anualizado'!AB40 -> 7289663.3 | S61: ='P&L Mensal - Anualizado'!AD40 -> 11597611 | T61: ='P&L Mensal - Anualizado'!AE40 -> 8530942.9 | U61: ='P&L Mensal - Anualizado'!AI40 -> 1325912.9 | V61: ='P&L Mensal - Anualizado'!AJ40 -> 1346530.3 | W61: ='P&L Mensal - Anualizado'!AL40 -> 8710184.4 | X61: ='P&L Mensal - Anualizado'!AM40 -> 7747221.4 | Y61: ='P&L Mensal - Anualizado'!AO40 -> 10036097 | Z61: ='P&L Mensal - Anualizado'!AP40 -> 9093751.7 | AA61: ='P&L Mensal - Anualizado'!AT40 -> 996666.71 | AB61: ='P&L Mensal - Anualizado'!AU40 -> 1575464.9 | AC61: ='P&L Mensal - Anualizado'!AW40 -> 13150989 | AD61: ='P&L Mensal - Anualizado'!AX40 -> 6376311.7 | AE61: ='P&L Mensal - Anualizado'!AZ40 -> 14147655 | AF61: ='P&L Mensal - Anualizado'!BA40 -> 7951776.6 | AG61: ='P&L Mensal - Anualizado'!BE40 -> 1204732.1 | AH61: ='P&L Mensal - Anualizado'!BF40 -> 918306.07 | AI61: ='P&L Mensal - Anualizado'!BH40 -> 10741136 | AJ61: ='P&L Mensal - Anualizado'!BI40 -> 7573429.6 | AK61: ='P&L Mensal - Anualizado'!BK40 -> 11945868 | AL61: ='P&L Mensal - Anualizado'!BL40 -> 8491735.7
B62: Impostos (IR/CSLL) | C62: ='P&L Mensal - Anualizado'!B41 -> -115374.99 | D62: ='P&L Mensal - Anualizado'!C41 -> -325141 | E62: ='P&L Mensal - Anualizado'!E41 -> -1463640.8 | F62: ='P&L Mensal - Anualizado'!F41 -> -1157412.4 | G62: ='P&L Mensal - Anualizado'!H41 -> -1579015.8 | H62: ='P&L Mensal - Anualizado'!I41 -> -1482553.4 | I62: ='P&L Mensal - Anualizado'!M41 -> -544207.13 | J62: ='P&L Mensal - Anualizado'!N41 -> -489202.52 | K62: ='P&L Mensal - Anualizado'!P41 -> -1604213.6 | L62: ='P&L Mensal - Anualizado'!Q41 -> -1228933.4 | M62: ='P&L Mensal - Anualizado'!S41 -> -2148420.8 | N62: ='P&L Mensal - Anualizado'!T41 -> -1718135.9 | O62: ='P&L Mensal - Anualizado'!X41 -> -375153.56 | P62: ='P&L Mensal - Anualizado'!Y41 -> -487969.93 | Q62: ='P&L Mensal - Anualizado'!AA41 -> -3549774.4 | R62: ='P&L Mensal - Anualizado'!AB41 -> -1730075.2 | S62: ='P&L Mensal - Anualizado'!AD41 -> -3924927.9 | T62: ='P&L Mensal - Anualizado'!AE41 -> -2218045.1 | U62: ='P&L Mensal - Anualizado'!AI41 -> -117342.31 | V62: ='P&L Mensal - Anualizado'!AJ41 -> -520162.59 | W62: ='P&L Mensal - Anualizado'!AL41 -> -770844.86 | X62: ='P&L Mensal - Anualizado'!AM41 -> -1844212.8 | Y62: ='P&L Mensal - Anualizado'!AO41 -> -888187.17 | Z62: ='P&L Mensal - Anualizado'!AP41 -> -2364375.4 | AA62: ='P&L Mensal - Anualizado'!AT41 -> -340871.81 | AB62: ='P&L Mensal - Anualizado'!AU41 -> -454841.62 | AC62: ='P&L Mensal - Anualizado'!AW41 -> -4497793.7 | AD62: ='P&L Mensal - Anualizado'!AX41 -> -1612620.3 | AE62: ='P&L Mensal - Anualizado'!AZ41 -> -4838665.5 | AF62: ='P&L Mensal - Anualizado'!BA41 -> -2067461.9 | AG62: ='P&L Mensal - Anualizado'!BE41 -> -327605.81 | AH62: ='P&L Mensal - Anualizado'!BF41 -> -485727.28 | AI62: ='P&L Mensal - Anualizado'!BH41 -> -2920791.9 | AJ62: ='P&L Mensal - Anualizado'!BI41 -> -1722124 | AK62: ='P&L Mensal - Anualizado'!BK41 -> -3248397.7 | AL62: ='P&L Mensal - Anualizado'!BL41 -> -2207851.3
B63: RESULTADO CONTÁBIL | C63: ='P&L Mensal - Anualizado'!B42 -> 1438495.7 | D63: ='P&L Mensal - Anualizado'!C42 -> 1250404.3 | E63: ='P&L Mensal - Anualizado'!E42 -> 2378658.1 | F63: ='P&L Mensal - Anualizado'!F42 -> 2955970.8 | G63: ='P&L Mensal - Anualizado'!H42 -> 3817153.8 | H63: ='P&L Mensal - Anualizado'!I42 -> 4206375.1 | I63: ='P&L Mensal - Anualizado'!M42 -> 1091677 | J63: ='P&L Mensal - Anualizado'!N42 -> 1392345.6 | K63: ='P&L Mensal - Anualizado'!P42 -> 3218045.3 | L63: ='P&L Mensal - Anualizado'!Q42 -> 3497733.5 | M63: ='P&L Mensal - Anualizado'!S42 -> 4309722.3 | N63: ='P&L Mensal - Anualizado'!T42 -> 4890079.2 | O63: ='P&L Mensal - Anualizado'!X42 -> 733372.52 | P63: ='P&L Mensal - Anualizado'!Y42 -> 753309.65 | Q63: ='P&L Mensal - Anualizado'!AA42 -> 6939310.4 | R63: ='P&L Mensal - Anualizado'!AB42 -> 5559588.1 | S63: ='P&L Mensal - Anualizado'!AD42 -> 7672682.9 | T63: ='P&L Mensal - Anualizado'!AE42 -> 6312897.7 | U63: ='P&L Mensal - Anualizado'!AI42 -> 1208570.6 | V63: ='P&L Mensal - Anualizado'!AJ42 -> 826367.67 | W63: ='P&L Mensal - Anualizado'!AL42 -> 7939339.5 | X63: ='P&L Mensal - Anualizado'!AM42 -> 5903008.6 | Y63: ='P&L Mensal - Anualizado'!AO42 -> 9147910.1 | Z63: ='P&L Mensal - Anualizado'!AP42 -> 6729376.2 | AA63: ='P&L Mensal - Anualizado'!AT42 -> 655794.9 | AB63: ='P&L Mensal - Anualizado'!AU42 -> 1120623.3 | AC63: ='P&L Mensal - Anualizado'!AW42 -> 8653194.9 | AD63: ='P&L Mensal - Anualizado'!AX42 -> 4763691.4 | AE63: ='P&L Mensal - Anualizado'!AZ42 -> 9308989.8 | AF63: ='P&L Mensal - Anualizado'!BA42 -> 5884314.7 | AG63: ='P&L Mensal - Anualizado'!BE42 -> 877126.28 | AH63: ='P&L Mensal - Anualizado'!BF42 -> 432578.79 | AI63: ='P&L Mensal - Anualizado'!BH42 -> 7820343.6 | AJ63: ='P&L Mensal - Anualizado'!BI42 -> 5851305.6 | AK63: ='P&L Mensal - Anualizado'!BK42 -> 8697469.9 | AL63: ='P&L Mensal - Anualizado'!BL42 -> 6283884.4
A65: P&L Acumulado
C67: Principais Linhas do P&L Acumulado
C68: Acumulado 2026 | F68: Acumulado 2025 | I68: ∆ 2026 x 2025
C69: Consignado | D69: Imobiliário | E69: Total | F69: Consignado | G69: Imobiliário | H69: Total | I69: ∆ Consignado | J69: ∆ Imobiliário | K69: ∆ Total
B70: Receitas | C70: ='P&L Acumulado'!F5 -> 61130865 | D70: ='P&L Acumulado'!I5 -> 2.4902878e+08 | E70: ='P&L Acumulado'!L5 -> 3.1015965e+08 | F70: ='Comparativo 2026 x 2025'!#REF! -> #REF! | G70: ='Comparativo 2026 x 2025'!#REF! -> #REF! | H70: ='Comparativo 2026 x 2025'!D5 -> 0 | I70: =C70/F70-1 -> #REF! | J70: =D70/G70-1 -> #REF! | K70: =E70/H70-1 -> #DIV/0!
B71: Despesas de Originação | C71: ='P&L Acumulado'!F24 -> -36197985 | D71: ='P&L Acumulado'!I24 -> -1.2243527e+08 | E71: ='P&L Acumulado'!L24 -> -1.5863325e+08 | F71: ='Comparativo 2026 x 2025'!#REF! -> #REF! | G71: ='Comparativo 2026 x 2025'!#REF! -> #REF! | H71: ='Comparativo 2026 x 2025'!D20 -> 0 | I71: =C71/F71-1 -> #REF! | J71: =D71/G71-1 -> #REF! | K71: =E71/H71-1 -> #DIV/0!
B72: Margem de Intermediação | C72: ='P&L Acumulado'!F31 -> 23003981 | D72: ='P&L Acumulado'!I31 -> 1.1956321e+08 | E72: ='P&L Acumulado'!L31 -> 1.4256719e+08 | F72: ='Comparativo 2026 x 2025'!#REF! -> #REF! | G72: ='Comparativo 2026 x 2025'!#REF! -> #REF! | H72: ='Comparativo 2026 x 2025'!D27 -> 0 | I72: =C72/F72-1 -> #REF! | J72: =D72/G72-1 -> #REF! | K72: =E72/H72-1 -> #DIV/0!
B73: Provisões | C73: ='P&L Acumulado'!F32 -> -4649091 | D73: ='P&L Acumulado'!I32 -> -11464954 | E73: ='P&L Acumulado'!L32 -> -16114045 | F73: ='Comparativo 2026 x 2025'!#REF! -> #REF! | G73: ='Comparativo 2026 x 2025'!#REF! -> #REF! | H73: ='Comparativo 2026 x 2025'!D28 -> 0 | I73: =C73/F73-1 -> #REF! | J73: =D73/G73-1 -> #REF! | K73: =E73/H73-1 -> #DIV/0!
B74: MG INTERMEDIAÇÃO LIQ | C74: ='P&L Acumulado'!F35 -> 18354890 | D74: ='P&L Acumulado'!I35 -> 1.0809826e+08 | E74: ='P&L Acumulado'!L35 -> 1.2645315e+08 | F74: ='Comparativo 2026 x 2025'!#REF! -> #REF! | G74: ='Comparativo 2026 x 2025'!#REF! -> #REF! | H74: ='Comparativo 2026 x 2025'!D31 -> 0 | I74: =C74/F74-1 -> #REF! | J74: =D74/G74-1 -> #REF! | K74: =E74/H74-1 -> #DIV/0!
B75: Despesas Administrativas | C75: ='P&L Acumulado'!F36+'P&L Acumulado'!F39 -> -8045620.1 | D75: ='P&L Acumulado'!I36+'P&L Acumulado'!I39 -> -32507532 | E75: ='P&L Acumulado'!L36+'P&L Acumulado'!L39 -> -40553153 | F75: ='Comparativo 2026 x 2025'!#REF!+'Comparativo 2026 x 2025'!#REF! -> #REF! | G75: ='Comparativo 2026 x 2025'!#REF!+'Comparativo 2026 x 2025'!#REF! -> #REF! | H75: ='Comparativo 2026 x 2025'!D32+'Comparativo 2026 x 2025'!D36 -> 0 | I75: =C75/F75-1 -> #REF! | J75: =D75/G75-1 -> #REF! | K75: =E75/H75-1 -> #DIV/0!
B76: Impostos Diretos | C76: ='P&L Acumulado'!F30 -> -1928898.7 | D76: ='P&L Acumulado'!I30 -> -7030303.8 | E76: ='P&L Acumulado'!L30 -> -8959202.6 | F76: ='Comparativo 2026 x 2025'!#REF! -> #REF! | G76: ='Comparativo 2026 x 2025'!#REF! -> #REF! | H76: ='Comparativo 2026 x 2025'!D26 -> 0 | I76: =C76/F76-1 -> #REF! | J76: =D76/G76-1 -> #REF! | K76: =E76/H76-1 -> #DIV/0!
B77: Comissão | C77: ='P&L Acumulado'!F37 -> -492764.12 | D77: ='P&L Acumulado'!I37 -> -2526406.8 | E77: ='P&L Acumulado'!L37 -> -3019170.9 | F77: ='Comparativo 2026 x 2025'!#REF! -> #REF! | G77: ='Comparativo 2026 x 2025'!#REF! -> #REF! | H77: ='Comparativo 2026 x 2025'!D34 -> 0 | I77: =C77/F77-1 -> #REF! | J77: =D77/G77-1 -> #REF! | K77: =E77/H77-1 -> #DIV/0!
B78: Amortização | C78: ='P&L Acumulado'!F40 -> -650580.56 | D78: ='P&L Acumulado'!I40 -> -2308362.2 | E78: ='P&L Acumulado'!L40 -> -2958942.8 | F78: ='Comparativo 2026 x 2025'!#REF! -> #REF! | G78: ='Comparativo 2026 x 2025'!#REF! -> #REF! | H78: ='Comparativo 2026 x 2025'!D33 -> 0 | I78: =IF(F78=0,"",C78/F78-1) -> #REF! | J78: =IF(G78=0,"",D78/G78-1) -> #REF! | K78: =E78/H78-1 -> #DIV/0!
B79: RESULTADO ANTES DO IMPOSTO | C79: ='P&L Acumulado'!F41 -> 9165925.1 | D79: ='P&L Acumulado'!I41 -> 70755956 | E79: ='P&L Acumulado'!L41 -> 79921881 | F79: ='Comparativo 2026 x 2025'!#REF! -> #REF! | G79: ='Comparativo 2026 x 2025'!#REF! -> #REF! | H79: ='Comparativo 2026 x 2025'!D37 -> 0 | I79: =C79/F79-1 -> #REF! | J79: =D79/G79-1 -> #REF! | K79: =E79/H79-1 -> #DIV/0!
B80: Impostos (IR/CSLL) | C80: ='P&L Acumulado'!F42 -> -2561005.1 | D80: ='P&L Acumulado'!I42 -> -19884638 | E80: ='P&L Acumulado'!L42 -> -22445643 | F80: ='Comparativo 2026 x 2025'!#REF! -> #REF! | G80: ='Comparativo 2026 x 2025'!#REF! -> #REF! | H80: ='Comparativo 2026 x 2025'!D38 -> 0 | I80: =C80/F80-1 -> #REF! | J80: =D80/G80-1 -> #REF! | K80: =E80/H80-1 -> #DIV/0!
B81: RESULTADO CONTÁBIL | C81: ='P&L Acumulado'!F43 -> 6604920 | D81: ='P&L Acumulado'!I43 -> 50871318 | E81: ='P&L Acumulado'!L43 -> 57476238 | F81: ='Comparativo 2026 x 2025'!#REF! -> #REF! | G81: ='Comparativo 2026 x 2025'!#REF! -> #REF! | H81: ='Comparativo 2026 x 2025'!D47 -> 0 | I81: =C81/F81-1 -> #REF! | J81: =D81/G81-1 -> #REF! | K81: =E81/H81-1 -> #DIV/0!
C83: Realizado x Orçado por linha principal
C84: Acumulado 2026
C85: Consignado | E85: Imobiliário | G85: Total
C86: Realizado | D86: Orçado | E86: Realizado | F86: Orçado | G86: Realizado | H86: Orçado
B87: Receitas | C87: ='P&L Acumulado'!F5 -> 61130865 | D87: ='P&L Acumulado'!G5 -> 61341232 | E87: ='P&L Acumulado'!I5 -> 2.4902878e+08 | F87: ='P&L Acumulado'!J5 -> 2.1980229e+08 | G87: ='P&L Acumulado'!L5 -> 3.1015965e+08 | H87: ='P&L Acumulado'!M5 -> 2.8114353e+08
B88: Despesas de Originação | C88: ='P&L Acumulado'!F24 -> -36197985 | D88: ='P&L Acumulado'!G24 -> -35595893 | E88: ='P&L Acumulado'!I24 -> -1.2243527e+08 | F88: ='P&L Acumulado'!J24 -> -1.1573548e+08 | G88: ='P&L Acumulado'!L24 -> -1.5863325e+08 | H88: ='P&L Acumulado'!M24 -> -1.5133138e+08
B89: Margem de Intermediação | C89: ='P&L Acumulado'!F31 -> 23003981 | D89: ='P&L Acumulado'!G31 -> 24478866 | E89: ='P&L Acumulado'!I31 -> 1.1956321e+08 | F89: ='P&L Acumulado'!J31 -> 99576591 | G89: ='P&L Acumulado'!L31 -> 1.4256719e+08 | H89: ='P&L Acumulado'!M31 -> 1.2405546e+08
B90: Provisões | C90: ='P&L Acumulado'!F32 -> -4649091 | D90: ='P&L Acumulado'!G32 -> -4856547.8 | E90: ='P&L Acumulado'!I32 -> -11464954 | F90: ='P&L Acumulado'!J32 -> -11242879 | G90: ='P&L Acumulado'!L32 -> -16114045 | H90: ='P&L Acumulado'!M32 -> -16099427
B91: MG INTERMEDIAÇÃO LIQ | C91: ='P&L Acumulado'!F35 -> 18354890 | D91: ='P&L Acumulado'!G35 -> 19622319 | E91: ='P&L Acumulado'!I35 -> 1.0809826e+08 | F91: ='P&L Acumulado'!J35 -> 88333712 | G91: ='P&L Acumulado'!L35 -> 1.2645315e+08 | H91: ='P&L Acumulado'!M35 -> 1.0795603e+08
B92: Despesas Administrativas | C92: ='P&L Acumulado'!F36+'P&L Acumulado'!F39 -> -8045620.1 | D92: ='P&L Acumulado'!G36+'P&L Acumulado'!G39 -> -8115738.1 | E92: ='P&L Acumulado'!I36+'P&L Acumulado'!I39 -> -32507532 | F92: ='P&L Acumulado'!J36+'P&L Acumulado'!J39 -> -33505233 | G92: ='P&L Acumulado'!L36+'P&L Acumulado'!L39 -> -40553153 | H92: ='P&L Acumulado'!M36+'P&L Acumulado'!M39 -> -41620972
B93: Impostos Diretos | C93: ='P&L Acumulado'!F30 -> -1928898.7 | D93: ='P&L Acumulado'!G30 -> -1266472.1 | E93: ='P&L Acumulado'!I30 -> -7030303.8 | F93: ='P&L Acumulado'!J30 -> -4490220.4 | G93: ='P&L Acumulado'!L30 -> -8959202.6 | H93: ='P&L Acumulado'!M30 -> -5756692.5
B94: Comissão | C94: ='P&L Acumulado'!F37 -> -492764.12 | D94: ='P&L Acumulado'!G37 -> -383142.86 | E94: ='P&L Acumulado'!I37 -> -2526406.8 | F94: ='P&L Acumulado'!J37 -> -1358415.6 | G94: ='P&L Acumulado'!L37 -> -3019170.9 | H94: ='P&L Acumulado'!M37 -> -1741558.4
B95: Amortização | C95: ='P&L Acumulado'!F40 -> -650580.56 | D95: ='P&L Acumulado'!G40 -> -653439.96 | E95: ='P&L Acumulado'!I40 -> -2308362.2 | F95: ='P&L Acumulado'!J40 -> -2316741.7 | G95: ='P&L Acumulado'!L40 -> -2958942.8 | H95: ='P&L Acumulado'!M40 -> -2970181.6
B96: RESULTADO ANTES DO IMPOSTO | C96: ='P&L Acumulado'!F41 -> 9165925.1 | D96: ='P&L Acumulado'!G41 -> 10469998 | E96: ='P&L Acumulado'!I41 -> 70755956 | F96: ='P&L Acumulado'!J41 -> 51153321 | G96: ='P&L Acumulado'!L41 -> 79921881 | H96: ='P&L Acumulado'!M41 -> 61623319
B97: Impostos (IR/CSLL) | C97: ='P&L Acumulado'!F42 -> -2561005.1 | D97: ='P&L Acumulado'!G42 -> -3524588.1 | E97: ='P&L Acumulado'!I42 -> -19884638 | F97: ='P&L Acumulado'!J42 -> -12500907 | G97: ='P&L Acumulado'!L42 -> -22445643 | H97: ='P&L Acumulado'!M42 -> -16025495
B98: RESULTADO CONTÁBIL | C98: ='P&L Acumulado'!F43 -> 6604920 | D98: ='P&L Acumulado'!G43 -> 6945409.6 | E98: ='P&L Acumulado'!I43 -> 50871318 | F98: ='P&L Acumulado'!J43 -> 38652414 | G98: ='P&L Acumulado'!L43 -> 57476238 | H98: ='P&L Acumulado'!M43 -> 45597824
A100: P&L Acumulado
C102: Principais Linhas do P&L Acumulado
C103: Acumulado 2026 | F103: Acumulado 2025 | I103: ∆ 2026 x 2025
C104: Consignado | D104: Imobiliário | E104: Total | F104: Consignado | G104: Imobiliário | H104: Total | I104: ∆ Consignado | J104: ∆ Imobiliário | K104: ∆ Total
B105: Margem de Intermediação Acumulada 2026 | C105: ='P&L Acumulado'!F31 -> 23003981 | D105: ='P&L Acumulado'!I31 -> 1.1956321e+08 | E105: ='P&L Acumulado'!L31 -> 1.4256719e+08 | F105: ='Comparativo 2026 x 2025'!#REF! -> #REF! | G105: ='Comparativo 2026 x 2025'!#REF! -> #REF! | H105: ='Comparativo 2026 x 2025'!D27 -> 0 | I105: =C105/F105-1 -> #REF! | J105: =D105/G105-1 -> #REF! | K105: =E105/H105-1 -> #DIV/0!
B106: MG Intermediação Líquida Acumulada 2026 | C106: ='P&L Acumulado'!F35 -> 18354890 | D106: ='P&L Acumulado'!I35 -> 1.0809826e+08 | E106: ='P&L Acumulado'!L35 -> 1.2645315e+08 | F106: ='Comparativo 2026 x 2025'!#REF! -> #REF! | G106: ='Comparativo 2026 x 2025'!#REF! -> #REF! | H106: ='Comparativo 2026 x 2025'!D31 -> 0 | I106: =C106/F106-1 -> #REF! | J106: =D106/G106-1 -> #REF! | K106: =E106/H106-1 -> #DIV/0!
B107: MG Contribuição Direta Acumulada 2026 | C107: ='P&L Acumulado'!F38 -> 14311520 | D107: ='P&L Acumulado'!I38 -> 88425570 | E107: ='P&L Acumulado'!L38 -> 1.0273709e+08 | F107: ='Comparativo 2026 x 2025'!#REF! -> #REF! | G107: ='Comparativo 2026 x 2025'!#REF! -> #REF! | H107: ='Comparativo 2026 x 2025'!D35 -> 0 | I107: =C107/F107-1 -> #REF! | J107: =D107/G107-1 -> #REF! | K107: =E107/H107-1 -> #DIV/0!
B108: Resultado Antes do Imposto Acumulado 2026 | C108: ='P&L Acumulado'!F41 -> 9165925.1 | D108: ='P&L Acumulado'!I41 -> 70755956 | E108: ='P&L Acumulado'!L41 -> 79921881 | F108: ='Comparativo 2026 x 2025'!#REF! -> #REF! | G108: ='Comparativo 2026 x 2025'!#REF! -> #REF! | H108: ='Comparativo 2026 x 2025'!D37 -> 0 | I108: =C108/F108-1 -> #REF! | J108: =D108/G108-1 -> #REF! | K108: =E108/H108-1 -> #DIV/0!
B109: Resultado Contábil Acumulado 2026 | C109: ='P&L Acumulado'!F43 -> 6604920 | D109: ='P&L Acumulado'!I43 -> 50871318 | E109: ='P&L Acumulado'!L43 -> 57476238 | F109: ='Comparativo 2026 x 2025'!#REF! -> #REF! | G109: ='Comparativo 2026 x 2025'!#REF! -> #REF! | H109: ='Comparativo 2026 x 2025'!D47 -> 0 | I109: =C109/F109-1 -> #REF! | J109: =D109/G109-1 -> #REF! | K109: =E109/H109-1 -> #DIV/0!
